Workbook
Name Apparel: #REF!
Name Apparel: #REF!
Name Brand: #REF!
Name Brand: #REF!
Name Colour: #REF!
Name Colour: #REF!
Name Department: #REF!
Name Department: #REF!
Name DesignPrintColour: #REF!
Name DesignPrintColour: #REF!
Name DesignType: #REF!
Name DesignType: #REF!
Name Dimension: #REF!
Name Dimension: #REF!
Name ExactFabric: #REF!
Name ExactFabric: #REF!
Name Fabric: #REF!
Name Fabric: #REF!
Name Fit: #REF!
Name Fit: #REF!
Name Gender: #REF!
Name Gender: #REF!
Name GenderSequence: #REF!
Name GenderSequence: #REF!
Name IsExempt: #REF!
Name IsExempt: #REF!
Name ListingVariation: #REF!
Name ListingVariation: #REF!
Name Machine: #REF!
Name Machine: #REF!
Name Neck: #REF!
Name Neck: #REF!
Name Orientation: #REF!
Name Orientation: #REF!
Name PackagingBox: #REF!
Name PackagingBox: #REF!
Name PrintingStatus: #REF!
Name PrintingStatus: #REF!
Name PrintingType: #REF!
Name PrintingType: #REF!
Name PrintPosition: #REF!
Name PrintPosition: #REF!
Name PrintPositionCount: #REF!
Name PrintPositionCount: #REF!
Name PrintSize: #REF!
Name PrintSize: #REF!
Name ProductCode: #REF!
Name ProductCode: #REF!
Name ProductType: #REF!
Name ProductType: #REF!
Name Shape: #REF!
Name Shape: #REF!
Name ShippingCarrier: #REF!
Name ShippingCarrier: #REF!
Name ShippingPackage: #REF!
Name ShippingPackage: #REF!
Name ShippingService: #REF!
Name ShippingService: #REF!
Name Size: #REF!
Name Size: #REF!

Sheet 00-Content
A1: serial | B1: tilke
A2: 1
A3: 2
A4: 3
A5: 4
A6: 5
A7: 6
A8: 7
A9: 8
A10: 9
A11: 10
A12: 11
A13: 12

Sheet Guide
A1: Code | B1: Product Tile | C1: Code | D1: Average Product Weight (g) | E1: Average Packaging Weight (g) | F1: Total Shipping Weight (g) | G1: Typical UK Shipping Fit | H1: Weight Source | T1: 1 | U1: 2 | V1: 3 | W1: 4 | X1: 5 | Y1: 6 | Z1: 7 | AA1: 8 | AB1: 9 | AC1: 10 | AD1: 12 | AE1: 13 | AF1: 14 | AG1: 15 | AH1: 16 | AI1: 17 | AJ1: 18 | AK1: 19 | AL1: 20 | AM1: 21 | AN1: 22 | AO1: 23 | BX1: A0 | BY1: 841 | BZ1: 1189 | CA1: 84.1 | CB1: 118.9 | CC1: 33.1 | CD1: 46.8
A2: PT1 | B2: 1. POD APPAREL (CLOTHING) | C2: PT1 | P2: Front | Q2: Top | T2: F1 | U2: Front | W2: Left | X2: Chest | Y2: Top | Z2: Bottom | AB2: {=_xlfn.TEXTJOIN(" ",TRUE,IF(TRIM(U2:AA2)="","",TRIM(U2:AA2)))} -> Front Left Chest Top Bottom | AC2: {=_xlfn.TEXTJOIN("-",TRUE,IF(TRIM(U2:AA2)="","",TRIM(U2:AA2)))} -> Front-Left-Chest-Top-Bottom | AD2: {=_xlfn.TEXTJOIN("",TRUE,LEFT(U2:AA2,1))} -> FLCTB | AE2: {=_xlfn.TEXTJOIN("/",TRUE,LEFT(U2:AA2,1))&"/"} -> F/L/C/T/B/ | AF2: {=_xlfn.TEXTJOIN("-",TRUE,LEFT(U2:AA2,1))&"-"} -> F-L-C-T-B- | BX2: A1 | BY2: 594 | BZ2: 841 | CA2: 59.4 | CB2: 84.1 | CC2: 23.4 | CD2: 33.1
A3: PT2 | B3: T-SHIRTS | C3: PT2 | P3: Back | Q3: Bottom | T3: F2 | U3: Front | W3: Right | X3: Chest | Y3: Top | Z3: Bottom | AB3: {=_xlfn.TEXTJOIN(" ",TRUE,IF(TRIM(U3:AA3)="","",TRIM(U3:AA3)))} -> Front Right Chest Top Bottom | AC3: {=_xlfn.TEXTJOIN("-",TRUE,IF(TRIM(U3:AA3)="","",TRIM(U3:AA3)))} -> Front-Right-Chest-Top-Bottom | AD3: {=_xlfn.TEXTJOIN("",TRUE,LEFT(U3:AA3,1))} -> FRCTB | AE3: {=_xlfn.TEXTJOIN("/",TRUE,LEFT(U3:AA3,1))&"/"} -> F/R/C/T/B/ | AF3: {=_xlfn.TEXTJOIN("-",TRUE,LEFT(U3:AA3,1))&"-"} -> F-R-C-T-B- | BX3: A2 | BY3: 420 | BZ3: 594 | CA3: 42 | CB3: 59.4 | CC3: 16.5 | CD3: 23.4
A4: PT3 | B4: Unisex Basic T-shirt | C4: PT3 | D4: 200 | E4: 60 | F4: 260 | G4: Large Letter / Small Parcel | H4: Estimated | P4: Left | Q4: Left | T4: F3 | U4: Front | W4: Middle | X4: Chest | Y4: Top | Z4: Bottom | AB4: {=_xlfn.TEXTJOIN(" ",TRUE,IF(TRIM(U4:AA4)="","",TRIM(U4:AA4)))} -> Front Middle Chest Top Bottom | AC4: {=_xlfn.TEXTJOIN("-",TRUE,IF(TRIM(U4:AA4)="","",TRIM(U4:AA4)))} -> Front-Middle-Chest-Top-Bottom | AD4: {=_xlfn.TEXTJOIN("",TRUE,LEFT(U4:AA4,1))} -> FMCTB | AE4: {=_xlfn.TEXTJOIN("/",TRUE,LEFT(U4:AA4,1))&"/"} -> F/M/C/T/B/ | AF4: {=_xlfn.TEXTJOIN("-",TRUE,LEFT(U4:AA4,1))&"-"} -> F-M-C-T-B- | BX4: A3 | BY4: 297 | BZ4: 420 | CA4: 29.7 | CB4: 42 | CC4: 11.7 | CD4: 16.5
A5: PT4 | B5: Premium T-shirt | C5: PT4 | D5: 240 | E5: 60 | F5: 300 | G5: Royal Mail Small Parcel | H5: Estimated | P5: Right | Q5: Right | T5: F4 | U5: Front | W5: Top | X5: Centre | AB5: {=_xlfn.TEXTJOIN(" ",TRUE,IF(TRIM(U5:AA5)="","",TRIM(U5:AA5)))} -> Front Top Centre | AC5: {=_xlfn.TEXTJOIN("-",TRUE,IF(TRIM(U5:AA5)="","",TRIM(U5:AA5)))} -> Front-Top-Centre | AD5: {=_xlfn.TEXTJOIN("",TRUE,LEFT(U5:AA5,1))} -> FTC | AE5: {=_xlfn.TEXTJOIN("/",TRUE,LEFT(U5:AA5,1))&"/"} -> F/T/C/ | AF5: {=_xlfn.TEXTJOIN("-",TRUE,LEFT(U5:AA5,1))&"-"} -> F-T-C- | AG5: A4 | AH5: A3 | AI5: A2/80 | BX5: A4 | BY5: 210 | BZ5: 297 | CA5: 21 | CB5: 29.7 | CC5: 8.3 | CD5: 11.7
A6: PT5 | B6: Heavy Cotton Tee | C6: PT5 | D6: 240 | E6: 60 | F6: 300 | G6: Royal Mail Small Parcel | H6: Estimated | P6: Top | Q6: Centre | T6: F5 | U6: Front | W6: Left | X6: Middle | Y6: Top | Z6: Bottom | AB6: {=_xlfn.TEXTJOIN(" ",TRUE,IF(TRIM(U6:AA6)="","",TRIM(U6:AA6)))} -> Front Left Middle Top Bottom | AC6: {=_xlfn.TEXTJOIN("-",TRUE,IF(TRIM(U6:AA6)="","",TRIM(U6:AA6)))} -> Front-Left-Middle-Top-Bottom | AD6: {=_xlfn.TEXTJOIN("",TRUE,LEFT(U6:AA6,1))} -> FLMTB | AE6: {=_xlfn.TEXTJOIN("/",TRUE,LEFT(U6:AA6,1))&"/"} -> F/L/M/T/B/ | AF6: {=_xlfn.TEXTJOIN("-",TRUE,LEFT(U6:AA6,1))&"-"} -> F-L-M-T-B- | BX6: A5 | BY6: 148 | BZ6: 210 | CA6: 14.8 | CB6: 21 | CC6: 5.8 | CD6: 8.3
A7: PT6 | B7: Oversized Streetwear Tee | C7: PT6 | D7: 240 | E7: 60 | F7: 300 | G7: Royal Mail Small Parcel | H7: Estimated | P7: Bottom | Q7: Middle | T7: F6 | U7: Front | W7: Right | X7: Middle | Y7: Top | Z7: Bottom | AB7: {=_xlfn.TEXTJOIN(" ",TRUE,IF(TRIM(U7:AA7)="","",TRIM(U7:AA7)))} -> Front Right Middle Top Bottom | AC7: {=_xlfn.TEXTJOIN("-",TRUE,IF(TRIM(U7:AA7)="","",TRIM(U7:AA7)))} -> Front-Right-Middle-Top-Bottom | AD7: {=_xlfn.TEXTJOIN("",TRUE,LEFT(U7:AA7,1))} -> FRMTB | AE7: {=_xlfn.TEXTJOIN("/",TRUE,LEFT(U7:AA7,1))&"/"} -> F/R/M/T/B/ | AF7: {=_xlfn.TEXTJOIN("-",TRUE,LEFT(U7:AA7,1))&"-"} -> F-R-M-T-B- | BX7: A6 | BY7: 105 | BZ7: 148 | CA7: 10.5 | CB7: 14.8 | CC7: 4.1 | CD7: 5.8
A8: PT7 | B8: Women’s Fitted Tee | C8: PT7 | D8: 200 | E8: 60 | F8: 260 | G8: Large Letter / Small Parcel | H8: Estimated | P8: Sleeve | Q8: Corner | T8: F7 | U8: Front | W8: Middle | X8: Centre | Y8: Top | Z8: Bottom | AB8: {=_xlfn.TEXTJOIN(" ",TRUE,IF(TRIM(U8:AA8)="","",TRIM(U8:AA8)))} -> Front Middle Centre Top Bottom | AC8: {=_xlfn.TEXTJOIN("-",TRUE,IF(TRIM(U8:AA8)="","",TRIM(U8:AA8)))} -> Front-Middle-Centre-Top-Bottom | AD8: {=_xlfn.TEXTJOIN("",TRUE,LEFT(U8:AA8,1))} -> FMCTB | AE8: {=_xlfn.TEXTJOIN("/",TRUE,LEFT(U8:AA8,1))&"/"} -> F/M/C/T/B/ | AF8: {=_xlfn.TEXTJOIN("-",TRUE,LEFT(U8:AA8,1))&"-"} -> F-M-C-T-B- | BX8: A7 | BY8: 74 | BZ8: 105 | CA8: 7.4 | CB8: 10.5 | CC8: 2.9 | CD8: 4.1
A9: PT8 | B9: Ringer Tee | C9: PT8 | D9: 200 | E9: 60 | F9: 260 | G9: Large Letter / Small Parcel | H9: Estimated | P9: Half | Q9: Chest | T9: F8 | U9: Front | W9: Left | X9: Chest | AB9: {=_xlfn.TEXTJOIN(" ",TRUE,IF(TRIM(U9:AA9)="","",TRIM(U9:AA9)))} -> Front Left Chest | AC9: {=_xlfn.TEXTJOIN("-",TRUE,IF(TRIM(U9:AA9)="","",TRIM(U9:AA9)))} -> Front-Left-Chest | AD9: {=_xlfn.TEXTJOIN("",TRUE,LEFT(U9:AA9,1))} -> FLC | AE9: {=_xlfn.TEXTJOIN("/",TRUE,LEFT(U9:AA9,1))&"/"} -> F/L/C/ | AF9: {=_xlfn.TEXTJOIN("-",TRUE,LEFT(U9:AA9,1))&"-"} -> F-L-C- | AG9: A9 | AH9: A8 | AI9: A7 | BX9: A8 | BY9: 52 | BZ9: 74 | CA9: 5.2 | CB9: 7.4 | CC9: 2 | CD9: 2.9
A10: PT9 | B10: Long Sleeve T-shirt | C10: PT9 | D10: 240 | E10: 60 | F10: 300 | G10: Royal Mail Small Parcel | H10: Estimated | P10: Short | T10: F9 | U10: Front | W10: Right | X10: Chest | AB10: {=_xlfn.TEXTJOIN(" ",TRUE,IF(TRIM(U10:AA10)="","",TRIM(U10:AA10)))} -> Front Right Chest | AC10: {=_xlfn.TEXTJOIN("-",TRUE,IF(TRIM(U10:AA10)="","",TRIM(U10:AA10)))} -> Front-Right-Chest | AD10: {=_xlfn.TEXTJOIN("",TRUE,LEFT(U10:AA10,1))} -> FRC | AE10: {=_xlfn.TEXTJOIN("/",TRUE,LEFT(U10:AA10,1))&"/"} -> F/R/C/ | AF10: {=_xlfn.TEXTJOIN("-",TRUE,LEFT(U10:AA10,1))&"-"} -> F-R-C- | BX10: A9 | BY10: 37 | BZ10: 52 | CA10: 3.7 | CB10: 5.2 | CC10: 1.5 | CD10: 2
A11: PT10 | B11: Pocket T-shirt | C11: PT10 | D11: 200 | E11: 60 | F11: 260 | G11: Large Letter / Small Parcel | H11: Estimated | P11: Full | T11: F10 | U11: Front | W11: Bottom | X11: Left | Y11: Corner | AB11: {=_xlfn.TEXTJOIN(" ",TRUE,IF(TRIM(U11:AA11)="","",TRIM(U11:AA11)))} -> Front Bottom Left Corner | AC11: {=_xlfn.TEXTJOIN("-",TRUE,IF(TRIM(U11:AA11)="","",TRIM(U11:AA11)))} -> Front-Bottom-Left-Corner | AD11: {=_xlfn.TEXTJOIN("",TRUE,LEFT(U11:AA11,1))} -> FBLC | AE11: {=_xlfn.TEXTJOIN("/",TRUE,LEFT(U11:AA11,1))&"/"} -> F/B/L/C/ | AF11: {=_xlfn.TEXTJOIN("-",TRUE,LEFT(U11:AA11,1))&"-"} -> F-B-L-C- | BX11: A10 | BY11: 26 | BZ11: 37 | CA11: 2.6 | CB11: 3.7 | CC11: 1 | CD11: 1.5
A12: PT11 | B12: V-neck Tee | C12: PT11 | D12: 200 | E12: 60 | F12: 260 | G12: Large Letter / Small Parcel | H12: Estimated | P12: inside Neck | T12: F11 | U12: Front | W12: Bottom | X12: Right | Y12: Corner | AB12: {=_xlfn.TEXTJOIN(" ",TRUE,IF(TRIM(U12:AA12)="","",TRIM(U12:AA12)))} -> Front Bottom Right Corner | AC12: {=_xlfn.TEXTJOIN("-",TRUE,IF(TRIM(U12:AA12)="","",TRIM(U12:AA12)))} -> Front-Bottom-Right-Corner | AD12: {=_xlfn.TEXTJOIN("",TRUE,LEFT(U12:AA12,1))} -> FBRC | AE12: {=_xlfn.TEXTJOIN("/",TRUE,LEFT(U12:AA12,1))&"/"} -> F/B/R/C/ | AF12: {=_xlfn.TEXTJOIN("-",TRUE,LEFT(U12:AA12,1))&"-"} -> F-B-R-C- | BX12: A11 | BY12: 18 | BZ12: 26 | CA12: 1.8 | CB12: 2.6 | CC12: 0.7 | CD12: 1
A13: PT12 | B13: Kids Custom T-shirt | C13: PT12 | D13: 140 | E13: 50 | F13: 190 | G13: Large Letter / Small Parcel | H13: Estimated | P13: outside Neck | T13: F12 | U13: Front | W13: Top | X13: Left | Y13: Corner | Z13: Top | AA13: Left | AB13: {=_xlfn.TEXTJOIN(" ",TRUE,IF(TRIM(U13:AA13)="","",TRIM(U13:AA13)))} -> Front Top Left Corner Top Left | AC13: {=_xlfn.TEXTJOIN("-",TRUE,IF(TRIM(U13:AA13)="","",TRIM(U13:AA13)))} -> Front-Top-Left-Corner-Top-Left | AD13: {=_xlfn.TEXTJOIN("",TRUE,LEFT(U13:AA13,1))} -> FTLCTL | AE13: {=_xlfn.TEXTJOIN("/",TRUE,LEFT(U13:AA13,1))&"/"} -> F/T/L/C/T/L/ | AF13: {=_xlfn.TEXTJOIN("-",TRUE,LEFT(U13:AA13,1))&"-"} -> F-T-L-C-T-L- | BX13: A12 | BY13: 13 | BZ13: 18 | CA13: 1.3 | CB13: 1.8 | CC13: 0.5 | CD13: 0.7
A14: PT13 | B14: SWEATSHIRTS & HOODIES | C14: PT13 | T14: F13 | U14: Front | W14: Top | X14: Right | Y14: Corner | Z14: Top | AA14: Right | AB14: {=_xlfn.TEXTJOIN(" ",TRUE,IF(TRIM(U14:AA14)="","",TRIM(U14:AA14)))} -> Front Top Right Corner Top Right | AC14: {=_xlfn.TEXTJOIN("-",TRUE,IF(TRIM(U14:AA14)="","",TRIM(U14:AA14)))} -> Front-Top-Right-Corner-Top-Right | AD14: {=_xlfn.TEXTJOIN("",TRUE,LEFT(U14:AA14,1))} -> FTRCTR | AE14: {=_xlfn.TEXTJOIN("/",TRUE,LEFT(U14:AA14,1))&"/"} -> F/T/R/C/T/R/ | AF14: {=_xlfn.TEXTJOIN("-",TRUE,LEFT(U14:AA14,1))&"-"} -> F-T-R-C-T-R- | BX14: A13 | BY14: 9 | BZ14: 13 | CA14: 0.9 | CB14: 1.3 | CC14: 0.4 | CD14: 0.5
A15: PT14 | B15: Classic Pullover Hoodie | C15: PT14 | D15: 750 | E15: 80 | F15: 830 | G15: Royal Mail Small Parcel | H15: Estimated | T15: F14 | U15: Front | W15: Top | X15: Left | Y15: Corner | AB15: {=_xlfn.TEXTJOIN(" ",TRUE,IF(TRIM(U15:AA15)="","",TRIM(U15:AA15)))} -> Front Top Left Corner | AC15: {=_xlfn.TEXTJOIN("-",TRUE,IF(TRIM(U15:AA15)="","",TRIM(U15:AA15)))} -> Front-Top-Left-Corner | AD15: {=_xlfn.TEXTJOIN("",TRUE,LEFT(U15:AA15,1))} -> FTLC | AE15: {=_xlfn.TEXTJOIN("/",TRUE,LEFT(U15:AA15,1))&"/"} -> F/T/L/C/ | AF15: {=_xlfn.TEXTJOIN("-",TRUE,LEFT(U15:AA15,1))&"-"} -> F-T-L-C- | BX15: 2A0 | BY15: 1189 | BZ15: 1682 | CA15: 118.9 | CB15: 168.2 | CC15: 46.8 | CD15: 66.2
A16: PT15 | B16: Zip Hoodie | C16: PT15 | D16: 800 | E16: 90 | F16: 890 | G16: Royal Mail Small Parcel | H16: Estimated | T16: F15 | U16: Front | W16: Top | X16: Right | Y16: Corner | AB16: {=_xlfn.TEXTJOIN(" ",TRUE,IF(TRIM(U16:AA16)="","",TRIM(U16:AA16)))} -> Front Top Right Corner | AC16: {=_xlfn.TEXTJOIN("-",TRUE,IF(TRIM(U16:AA16)="","",TRIM(U16:AA16)))} -> Front-Top-Right-Corner | AD16: {=_xlfn.TEXTJOIN("",TRUE,LEFT(U16:AA16,1))} -> FTRC | AE16: {=_xlfn.TEXTJOIN("/",TRUE,LEFT(U16:AA16,1))&"/"} -> F/T/R/C/ | AF16: {=_xlfn.TEXTJOIN("-",TRUE,LEFT(U16:AA16,1))&"-"} -> F-T-R-C- | BX16: 4A0 | BY16: 1682 | BZ16: 2378 | CA16: 168.2 | CB16: 237.8 | CC16: 66.2 | CD16: 93.6
A17: PT16 | B17: Heavy Blend Hoodie | C17: PT16 | D17: 750 | E17: 80 | F17: 830 | G17: Royal Mail Small Parcel | H17: Estimated | T17: F16 | U17: Front | W17: Top | X17: Left | Y17: Bottom | Z17: Right | AA17: Corner | AB17: {=_xlfn.TEXTJOIN(" ",TRUE,IF(TRIM(U17:AA17)="","",TRIM(U17:AA17)))} -> Front Top Left Bottom Right Corner | AC17: {=_xlfn.TEXTJOIN("-",TRUE,IF(TRIM(U17:AA17)="","",TRIM(U17:AA17)))} -> Front-Top-Left-Bottom-Right-Corner | AD17: {=_xlfn.TEXTJOIN("",TRUE,LEFT(U17:AA17,1))} -> FTLBRC | AE17: {=_xlfn.TEXTJOIN("/",TRUE,LEFT(U17:AA17,1))&"/"} -> F/T/L/B/R/C/ | AF17: {=_xlfn.TEXTJOIN("-",TRUE,LEFT(U17:AA17,1))&"-"} -> F-T-L-B-R-C- | BX17: A0+ | BY17: 914 | BZ17: 1292 | CA17: 91.4 | CB17: 129.2 | CC17: 36 | CD17: 50.9
A18: PT17 | B18: Crewneck Sweatshirt | C18: PT17 | D18: 520 | E18: 80 | F18: 600 | G18: Royal Mail Small Parcel | H18: Estimated | T18: F17 | U18: Front | W18: Top | X18: Right | Y18: Corner | Z18: Left | AA18: Corner | AB18: {=_xlfn.TEXTJOIN(" ",TRUE,IF(TRIM(U18:AA18)="","",TRIM(U18:AA18)))} -> Front Top Right Corner Left Corner | AC18: {=_xlfn.TEXTJOIN("-",TRUE,IF(TRIM(U18:AA18)="","",TRIM(U18:AA18)))} -> Front-Top-Right-Corner-Left-Corner | AD18: {=_xlfn.TEXTJOIN("",TRUE,LEFT(U18:AA18,1))} -> FTRCLC | AE18: {=_xlfn.TEXTJOIN("/",TRUE,LEFT(U18:AA18,1))&"/"} -> F/T/R/C/L/C/ | AF18: {=_xlfn.TEXTJOIN("-",TRUE,LEFT(U18:AA18,1))&"-"} -> F-T-R-C-L-C- | BX18: A1+ | BY18: 609 | BZ18: 914 | CA18: 60.9 | CB18: 91.4 | CC18: 24 | CD18: 36
A19: PT18 | B19: Oversized Hoodie | C19: PT18 | D19: 750 | E19: 80 | F19: 830 | G19: Royal Mail Small Parcel | H19: Estimated | T19: F18 | U19: Front | W19: Bottom | X19: Left | Y19: Corner | Z19: Top | AA19: Left | AB19: {=_xlfn.TEXTJOIN(" ",TRUE,IF(TRIM(U19:AA19)="","",TRIM(U19:AA19)))} -> Front Bottom Left Corner Top Left | AC19: {=_xlfn.TEXTJOIN("-",TRUE,IF(TRIM(U19:AA19)="","",TRIM(U19:AA19)))} -> Front-Bottom-Left-Corner-Top-Left | AD19: {=_xlfn.TEXTJOIN("",TRUE,LEFT(U19:AA19,1))} -> FBLCTL | AE19: {=_xlfn.TEXTJOIN("/",TRUE,LEFT(U19:AA19,1))&"/"} -> F/B/L/C/T/L/ | AF19: {=_xlfn.TEXTJOIN("-",TRUE,LEFT(U19:AA19,1))&"-"} -> F-B-L-C-T-L- | BX19: A3+ | BY19: 329 | BZ19: 483 | CA19: 32.9 | CB19: 48.3 | CC19: 13 | CD19: 19
A20: PT19 | B20: College Hoodie | C20: PT19 | D20: 750 | E20: 80 | F20: 830 | G20: Royal Mail Small Parcel | H20: Estimated | T20: F19 | U20: Front | W20: Bottom | X20: Right | Y20: Corner | Z20: Top | AA20: Left | AB20: {=_xlfn.TEXTJOIN(" ",TRUE,IF(TRIM(U20:AA20)="","",TRIM(U20:AA20)))} -> Front Bottom Right Corner Top Left | AC20: {=_xlfn.TEXTJOIN("-",TRUE,IF(TRIM(U20:AA20)="","",TRIM(U20:AA20)))} -> Front-Bottom-Right-Corner-Top-Left | AD20: {=_xlfn.TEXTJOIN("",TRUE,LEFT(U20:AA20,1))} -> FBRCTL | AE20: {=_xlfn.TEXTJOIN("/",TRUE,LEFT(U20:AA20,1))&"/"} -> F/B/R/C/T/L/ | AF20: {=_xlfn.TEXTJOIN("-",TRUE,LEFT(U20:AA20,1))&"-"} -> F-B-R-C-T-L-
A21: PT20 | B21: Crop Hoodie | C21: PT20 | D21: 550 | E21: 80 | F21: 630 | G21: Royal Mail Small Parcel | H21: Estimated | T21: F20 | U21: Front | W21: Bottom | X21: Left | Y21: Corner | Z21: Top | AA21: Right | AB21: {=_xlfn.TEXTJOIN(" ",TRUE,IF(TRIM(U21:AA21)="","",TRIM(U21:AA21)))} -> Front Bottom Left Corner Top Right | AC21: {=_xlfn.TEXTJOIN("-",TRUE,IF(TRIM(U21:AA21)="","",TRIM(U21:AA21)))} -> Front-Bottom-Left-Corner-Top-Right | AD21: {=_xlfn.TEXTJOIN("",TRUE,LEFT(U21:AA21,1))} -> FBLCTR | AE21: {=_xlfn.TEXTJOIN("/",TRUE,LEFT(U21:AA21,1))&"/"} -> F/B/L/C/T/R/ | AF21: {=_xlfn.TEXTJOIN("-",TRUE,LEFT(U21:AA21,1))&"-"} -> F-B-L-C-T-R-
A22: PT21 | B22: Kids Hoodie | C22: PT21 | D22: 500 | E22: 80 | F22: 580 | G22: Royal Mail Small Parcel | H22: Estimated | T22: F21 | U22: Front | W22: Bottom | X22: Right | Y22: Corner | Z22: Top | AA22: Right | AB22: {=_xlfn.TEXTJOIN(" ",TRUE,IF(TRIM(U22:AA22)="","",TRIM(U22:AA22)))} -> Front Bottom Right Corner Top Right | AC22: {=_xlfn.TEXTJOIN("-",TRUE,IF(TRIM(U22:AA22)="","",TRIM(U22:AA22)))} -> Front-Bottom-Right-Corner-Top-Right | AD22: {=_xlfn.TEXTJOIN("",TRUE,LEFT(U22:AA22,1))} -> FBRCTR | AE22: {=_xlfn.TEXTJOIN("/",TRUE,LEFT(U22:AA22,1))&"/"} -> F/B/R/C/T/R/ | AF22: {=_xlfn.TEXTJOIN("-",TRUE,LEFT(U22:AA22,1))&"-"} -> F-B-R-C-T-R-
A23: PT22 | B23: TANK TopS | C23: PT22 | T23: F22 | U23: Front | W23: Left | X23: Middle | Z23: Top | AA23: Left | AB23: {=_xlfn.TEXTJOIN(" ",TRUE,IF(TRIM(U23:AA23)="","",TRIM(U23:AA23)))} -> Front Left Middle Top Left | AC23: {=_xlfn.TEXTJOIN("-",TRUE,IF(TRIM(U23:AA23)="","",TRIM(U23:AA23)))} -> Front-Left-Middle-Top-Left | AD23: {=_xlfn.TEXTJOIN("",TRUE,LEFT(U23:AA23,1))} -> FLMTL | AE23: {=_xlfn.TEXTJOIN("/",TRUE,LEFT(U23:AA23,1))&"/"} -> F/L/M/T/L/ | AF23: {=_xlfn.TEXTJOIN("-",TRUE,LEFT(U23:AA23,1))&"-"} -> F-L-M-T-L-
A24: PT23 | B24: Unisex Tank | C24: PT23 | D24: 180 | E24: 60 | F24: 240 | G24: Large Letter / Small Parcel | H24: Estimated | T24: F23 | U24: Front | W24: Right | X24: Middle | Z24: Top | AA24: Left | AB24: {=_xlfn.TEXTJOIN(" ",TRUE,IF(TRIM(U24:AA24)="","",TRIM(U24:AA24)))} -> Front Right Middle Top Left | AC24: {=_xlfn.TEXTJOIN("-",TRUE,IF(TRIM(U24:AA24)="","",TRIM(U24:AA24)))} -> Front-Right-Middle-Top-Left | AD24: {=_xlfn.TEXTJOIN("",TRUE,LEFT(U24:AA24,1))} -> FRMTL | AE24: {=_xlfn.TEXTJOIN("/",TRUE,LEFT(U24:AA24,1))&"/"} -> F/R/M/T/L/ | AF24: {=_xlfn.TEXTJOIN("-",TRUE,LEFT(U24:AA24,1))&"-"} -> F-R-M-T-L-
A25: PT24 | B25: Women’s Racerback | C25: PT24 | T25: F24 | U25: Front | W25: Middle | X25: Centre | Z25: Top | AA25: Left | AB25: {=_xlfn.TEXTJOIN(" ",TRUE,IF(TRIM(U25:AA25)="","",TRIM(U25:AA25)))} -> Front Middle Centre Top Left | AC25: {=_xlfn.TEXTJOIN("-",TRUE,IF(TRIM(U25:AA25)="","",TRIM(U25:AA25)))} -> Front-Middle-Centre-Top-Left | AD25: {=_xlfn.TEXTJOIN("",TRUE,LEFT(U25:AA25,1))} -> FMCTL | AE25: {=_xlfn.TEXTJOIN("/",TRUE,LEFT(U25:AA25,1))&"/"} -> F/M/C/T/L/ | AF25: {=_xlfn.TEXTJOIN("-",TRUE,LEFT(U25:AA25,1))&"-"} -> F-M-C-T-L-
A26: PT25 | B26: Gym Tank / Fitness Vest | C26: PT25 | D26: 180 | E26: 60 | F26: 240 | G26: Large Letter / Small Parcel | H26: Estimated | T26: F25 | U26: Front | W26: Left | X26: Middle | Z26: Top | AA26: Right | AB26: {=_xlfn.TEXTJOIN(" ",TRUE,IF(TRIM(U26:AA26)="","",TRIM(U26:AA26)))} -> Front Left Middle Top Right | AC26: {=_xlfn.TEXTJOIN("-",TRUE,IF(TRIM(U26:AA26)="","",TRIM(U26:AA26)))} -> Front-Left-Middle-Top-Right | AD26: {=_xlfn.TEXTJOIN("",TRUE,LEFT(U26:AA26,1))} -> FLMTR | AE26: {=_xlfn.TEXTJOIN("/",TRUE,LEFT(U26:AA26,1))&"/"} -> F/L/M/T/R/ | AF26: {=_xlfn.TEXTJOIN("-",TRUE,LEFT(U26:AA26,1))&"-"} -> F-L-M-T-R-
A27: PT26 | B27: Bottom S | C27: PT26 | T27: F26 | U27: Front | W27: Right | X27: Middle | Z27: Top | AA27: Right | AB27: {=_xlfn.TEXTJOIN(" ",TRUE,IF(TRIM(U27:AA27)="","",TRIM(U27:AA27)))} -> Front Right Middle Top Right | AC27: {=_xlfn.TEXTJOIN("-",TRUE,IF(TRIM(U27:AA27)="","",TRIM(U27:AA27)))} -> Front-Right-Middle-Top-Right | AD27: {=_xlfn.TEXTJOIN("",TRUE,LEFT(U27:AA27,1))} -> FRMTR | AE27: {=_xlfn.TEXTJOIN("/",TRUE,LEFT(U27:AA27,1))&"/"} -> F/R/M/T/R/ | AF27: {=_xlfn.TEXTJOIN("-",TRUE,LEFT(U27:AA27,1))&"-"} -> F-R-M-T-R-
A28: PT27 | B28: Joggers | C28: PT27 | D28: 500 | E28: 90 | F28: 590 | G28: Royal Mail Small Parcel | H28: Estimated | T28: F27 | U28: Front | W28: Middle | X28: Centre | Z28: Top | AA28: Right | AB28: {=_xlfn.TEXTJOIN(" ",TRUE,IF(TRIM(U28:AA28)="","",TRIM(U28:AA28)))} -> Front Middle Centre Top Right | AC28: {=_xlfn.TEXTJOIN("-",TRUE,IF(TRIM(U28:AA28)="","",TRIM(U28:AA28)))} -> Front-Middle-Centre-Top-Right | AD28: {=_xlfn.TEXTJOIN("",TRUE,LEFT(U28:AA28,1))} -> FMCTR | AE28: {=_xlfn.TEXTJOIN("/",TRUE,LEFT(U28:AA28,1))&"/"} -> F/M/C/T/R/ | AF28: {=_xlfn.TEXTJOIN("-",TRUE,LEFT(U28:AA28,1))&"-"} -> F-M-C-T-R-
A29: PT28 | B29: Sweatpants | C29: PT28 | D29: 500 | E29: 90 | F29: 590 | G29: Royal Mail Small Parcel | H29: Estimated | T29: F28 | U29: Front | W29: Bottom | X29: Left | Y29: Right | AB29: {=_xlfn.TEXTJOIN(" ",TRUE,IF(TRIM(U29:AA29)="","",TRIM(U29:AA29)))} -> Front Bottom Left Right | AC29: {=_xlfn.TEXTJOIN("-",TRUE,IF(TRIM(U29:AA29)="","",TRIM(U29:AA29)))} -> Front-Bottom-Left-Right | AD29: {=_xlfn.TEXTJOIN("",TRUE,LEFT(U29:AA29,1))} -> FBLR | AE29: {=_xlfn.TEXTJOIN("/",TRUE,LEFT(U29:AA29,1))&"/"} -> F/B/L/R/ | AF29: {=_xlfn.TEXTJOIN("-",TRUE,LEFT(U29:AA29,1))&"-"} -> F-B-L-R-
A30: PT29 | B30: Shorts | C30: PT29 | D30: 250 | E30: 70 | F30: 320 | G30: Royal Mail Small Parcel | H30: Estimated | T30: F29 | U30: Front | W30: Centre | X30: Left | Y30: Right | AB30: {=_xlfn.TEXTJOIN(" ",TRUE,IF(TRIM(U30:AA30)="","",TRIM(U30:AA30)))} -> Front Centre Left Right | AC30: {=_xlfn.TEXTJOIN("-",TRUE,IF(TRIM(U30:AA30)="","",TRIM(U30:AA30)))} -> Front-Centre-Left-Right | AD30: {=_xlfn.TEXTJOIN("",TRUE,LEFT(U30:AA30,1))} -> FCLR | AE30: {=_xlfn.TEXTJOIN("/",TRUE,LEFT(U30:AA30,1))&"/"} -> F/C/L/R/ | AF30: {=_xlfn.TEXTJOIN("-",TRUE,LEFT(U30:AA30,1))&"-"} -> F-C-L-R-
A31: PT30 | B31: Leggings | C31: PT30 | D31: 220 | E31: 70 | F31: 290 | G31: Royal Mail Small Parcel | H31: Estimated | T31: F30 | U31: Front | W31: Bottom | X31: Corner | Z31: Top | AA31: Bottom | AB31: {=_xlfn.TEXTJOIN(" ",TRUE,IF(TRIM(U31:AA31)="","",TRIM(U31:AA31)))} -> Front Bottom Corner Top Bottom | AC31: {=_xlfn.TEXTJOIN("-",TRUE,IF(TRIM(U31:AA31)="","",TRIM(U31:AA31)))} -> Front-Bottom-Corner-Top-Bottom | AD31: {=_xlfn.TEXTJOIN("",TRUE,LEFT(U31:AA31,1))} -> FBCTB | AE31: {=_xlfn.TEXTJOIN("/",TRUE,LEFT(U31:AA31,1))&"/"} -> F/B/C/T/B/ | AF31: {=_xlfn.TEXTJOIN("-",TRUE,LEFT(U31:AA31,1))&"-"} -> F-B-C-T-B-
A32: PT31 | B32: Cycling Shorts | C32: PT31 | D32: 250 | E32: 70 | F32: 320 | G32: Royal Mail Small Parcel | H32: Estimated | T32: F31 | U32: Front | W32: Bottom | X32: Corner | Z32: Top | AA32: Bottom | AB32: {=_xlfn.TEXTJOIN(" ",TRUE,IF(TRIM(U32:AA32)="","",TRIM(U32:AA32)))} -> Front Bottom Corner Top Bottom | AC32: {=_xlfn.TEXTJOIN("-",TRUE,IF(TRIM(U32:AA32)="","",TRIM(U32:AA32)))} -> Front-Bottom-Corner-Top-Bottom | AD32: {=_xlfn.TEXTJOIN("",TRUE,LEFT(U32:AA32,1))} -> FBCTB | AE32: {=_xlfn.TEXTJOIN("/",TRUE,LEFT(U32:AA32,1))&"/"} -> F/B/C/T/B/ | AF32: {=_xlfn.TEXTJOIN("-",TRUE,LEFT(U32:AA32,1))&"-"} -> F-B-C-T-B-
A33: PT32 | B33: ACTIVEWEAR | C33: PT32 | T33: F32 | U33: Front | W33: Bottom | X33: Middle | Z33: Top | AA33: Bottom | AB33: {=_xlfn.TEXTJOIN(" ",TRUE,IF(TRIM(U33:AA33)="","",TRIM(U33:AA33)))} -> Front Bottom Middle Top Bottom | AC33: {=_xlfn.TEXTJOIN("-",TRUE,IF(TRIM(U33:AA33)="","",TRIM(U33:AA33)))} -> Front-Bottom-Middle-Top-Bottom | AD33: {=_xlfn.TEXTJOIN("",TRUE,LEFT(U33:AA33,1))} -> FBMTB | AE33: {=_xlfn.TEXTJOIN("/",TRUE,LEFT(U33:AA33,1))&"/"} -> F/B/M/T/B/ | AF33: {=_xlfn.TEXTJOIN("-",TRUE,LEFT(U33:AA33,1))&"-"} -> F-B-M-T-B-
A34: PT33 | B34: Sports Jersey | C34: PT33 | T34: F33 | U34: Front | W34: Top | X34: Left | Y34: Corner | Z34: Top | AA34: Right | AB34: {=_xlfn.TEXTJOIN(" ",TRUE,IF(TRIM(U34:AA34)="","",TRIM(U34:AA34)))} -> Front Top Left Corner Top Right | AC34: {=_xlfn.TEXTJOIN("-",TRUE,IF(TRIM(U34:AA34)="","",TRIM(U34:AA34)))} -> Front-Top-Left-Corner-Top-Right | AD34: {=_xlfn.TEXTJOIN("",TRUE,LEFT(U34:AA34,1))} -> FTLCTR | AE34: {=_xlfn.TEXTJOIN("/",TRUE,LEFT(U34:AA34,1))&"/"} -> F/T/L/C/T/R/ | AF34: {=_xlfn.TEXTJOIN("-",TRUE,LEFT(U34:AA34,1))&"-"} -> F-T-L-C-T-R-
A35: PT34 | B35: Compression Shirt | C35: PT34 | T35: F34 | U35: Front | W35: Top | X35: Right | Y35: Corner | Z35: Top | AA35: Left | AB35: {=_xlfn.TEXTJOIN(" ",TRUE,IF(TRIM(U35:AA35)="","",TRIM(U35:AA35)))} -> Front Top Right Corner Top Left | AC35: {=_xlfn.TEXTJOIN("-",TRUE,IF(TRIM(U35:AA35)="","",TRIM(U35:AA35)))} -> Front-Top-Right-Corner-Top-Left | AD35: {=_xlfn.TEXTJOIN("",TRUE,LEFT(U35:AA35,1))} -> FTRCTL | AE35: {=_xlfn.TEXTJOIN("/",TRUE,LEFT(U35:AA35,1))&"/"} -> F/T/R/C/T/L/ | AF35: {=_xlfn.TEXTJOIN("-",TRUE,LEFT(U35:AA35,1))&"-"} -> F-T-R-C-T-L-
A36: PT35 | B36: Men’s Gym Vest | C36: PT35 | D36: 180 | E36: 60 | F36: 240 | G36: Large Letter / Small Parcel | H36: Estimated | T36: F35 | U36: Front | W36: Top | AB36: {=_xlfn.TEXTJOIN(" ",TRUE,IF(TRIM(U36:AA36)="","",TRIM(U36:AA36)))} -> Front Top | AC36: {=_xlfn.TEXTJOIN("-",TRUE,IF(TRIM(U36:AA36)="","",TRIM(U36:AA36)))} -> Front-Top | AD36: {=_xlfn.TEXTJOIN("",TRUE,LEFT(U36:AA36,1))} -> FT | AE36: {=_xlfn.TEXTJOIN("/",TRUE,LEFT(U36:AA36,1))&"/"} -> F/T/ | AF36: {=_xlfn.TEXTJOIN("-",TRUE,LEFT(U36:AA36,1))&"-"} -> F-T-
A37: PT36 | B37: Sports Leggings | C37: PT36 | D37: 220 | E37: 70 | F37: 290 | G37: Royal Mail Small Parcel | H37: Estimated | T37: F36 | U37: Front | AB37: {=_xlfn.TEXTJOIN(" ",TRUE,IF(TRIM(U37:AA37)="","",TRIM(U37:AA37)))} -> Front | AC37: {=_xlfn.TEXTJOIN("-",TRUE,IF(TRIM(U37:AA37)="","",TRIM(U37:AA37)))} -> Front | AD37: {=_xlfn.TEXTJOIN("",TRUE,LEFT(U37:AA37,1))} -> F | AE37: {=_xlfn.TEXTJOIN("/",TRUE,LEFT(U37:AA37,1))&"/"} -> F/ | AF37: {=_xlfn.TEXTJOIN("-",TRUE,LEFT(U37:AA37,1))&"-"} -> F-
A38: PT37 | B38: BABY & KIDS APPAREL | C38: PT37 | T38: F37 | U38: Front | AB38: {=_xlfn.TEXTJOIN(" ",TRUE,IF(TRIM(U38:AA38)="","",TRIM(U38:AA38)))} -> Front | AC38: {=_xlfn.TEXTJOIN("-",TRUE,IF(TRIM(U38:AA38)="","",TRIM(U38:AA38)))} -> Front | AD38: {=_xlfn.TEXTJOIN("",TRUE,LEFT(U38:AA38,1))} -> F | AE38: {=_xlfn.TEXTJOIN("/",TRUE,LEFT(U38:AA38,1))&"/"} -> F/ | AF38: {=_xlfn.TEXTJOIN("-",TRUE,LEFT(U38:AA38,1))&"-"} -> F-
A39: PT38 | B39: Baby Bodysuit | C39: PT38 | T39: F38 | U39: Front | AB39: {=_xlfn.TEXTJOIN(" ",TRUE,IF(TRIM(U39:AA39)="","",TRIM(U39:AA39)))} -> Front | AC39: {=_xlfn.TEXTJOIN("-",TRUE,IF(TRIM(U39:AA39)="","",TRIM(U39:AA39)))} -> Front | AD39: {=_xlfn.TEXTJOIN("",TRUE,LEFT(U39:AA39,1))} -> F | AE39: {=_xlfn.TEXTJOIN("/",TRUE,LEFT(U39:AA39,1))&"/"} -> F/ | AF39: {=_xlfn.TEXTJOIN("-",TRUE,LEFT(U39:AA39,1))&"-"} -> F-
A40: PT39 | B40: Baby Bib | C40: PT39 | T40: F39 | U40: Front | AB40: {=_xlfn.TEXTJOIN(" ",TRUE,IF(TRIM(U40:AA40)="","",TRIM(U40:AA40)))} -> Front | AC40: {=_xlfn.TEXTJOIN("-",TRUE,IF(TRIM(U40:AA40)="","",TRIM(U40:AA40)))} -> Front | AD40: {=_xlfn.TEXTJOIN("",TRUE,LEFT(U40:AA40,1))} -> F | AE40: {=_xlfn.TEXTJOIN("/",TRUE,LEFT(U40:AA40,1))&"/"} -> F/ | AF40: {=_xlfn.TEXTJOIN("-",TRUE,LEFT(U40:AA40,1))&"-"} -> F-
A41: PT40 | B41: Kids T-shirt | C41: PT40 | D41: 140 | E41: 50 | F41: 190 | G41: Large Letter / Small Parcel | H41: Estimated | T41: F40 | U41: Front | AB41: {=_xlfn.TEXTJOIN(" ",TRUE,IF(TRIM(U41:AA41)="","",TRIM(U41:AA41)))} -> Front | AC41: {=_xlfn.TEXTJOIN("-",TRUE,IF(TRIM(U41:AA41)="","",TRIM(U41:AA41)))} -> Front | AD41: {=_xlfn.TEXTJOIN("",TRUE,LEFT(U41:AA41,1))} -> F | AE41: {=_xlfn.TEXTJOIN("/",TRUE,LEFT(U41:AA41,1))&"/"} -> F/ | AF41: {=_xlfn.TEXTJOIN("-",TRUE,LEFT(U41:AA41,1))&"-"} -> F-
A42: PT42 | B42: Kids Pajamas | C42: PT42 | T42: B1 | U42: Back | W42: Left | Y42: Top | Z42: Bottom | AB42: {=_xlfn.TEXTJOIN(" ",TRUE,IF(TRIM(U42:AA42)="","",TRIM(U42:AA42)))} -> Back Left Top Bottom | AC42: {=_xlfn.TEXTJOIN("-",TRUE,IF(TRIM(U42:AA42)="","",TRIM(U42:AA42)))} -> Back-Left-Top-Bottom | AD42: {=_xlfn.TEXTJOIN("",TRUE,LEFT(U42:AA42,1))} -> BLTB | AE42: {=_xlfn.TEXTJOIN("/",TRUE,LEFT(U42:AA42,1))&"/"} -> B/L/T/B/ | AF42: {=_xlfn.TEXTJOIN("-",TRUE,LEFT(U42:AA42,1))&"-"} -> B-L-T-B-
A43: PT43 | B43: 🟧 2. POD DRINKWARE | C43: PT43 | T43: B2 | U43: Back | W43: Right | Y43: Top | Z43: Bottom | AB43: {=_xlfn.TEXTJOIN(" ",TRUE,IF(TRIM(U43:AA43)="","",TRIM(U43:AA43)))} -> Back Right Top Bottom | AC43: {=_xlfn.TEXTJOIN("-",TRUE,IF(TRIM(U43:AA43)="","",TRIM(U43:AA43)))} -> Back-Right-Top-Bottom | AD43: {=_xlfn.TEXTJOIN("",TRUE,LEFT(U43:AA43,1))} -> BRTB | AE43: {=_xlfn.TEXTJOIN("/",TRUE,LEFT(U43:AA43,1))&"/"} -> B/R/T/B/ | AF43: {=_xlfn.TEXTJOIN("-",TRUE,LEFT(U43:AA43,1))&"-"} -> B-R-T-B-
A44: PT44 | B44: Product Type: Custom Drinkware | C44: PT44 | T44: B3 | U44: Back | W44: Middle | Y44: Top | Z44: Bottom | AB44: {=_xlfn.TEXTJOIN(" ",TRUE,IF(TRIM(U44:AA44)="","",TRIM(U44:AA44)))} -> Back Middle Top Bottom | AC44: {=_xlfn.TEXTJOIN("-",TRUE,IF(TRIM(U44:AA44)="","",TRIM(U44:AA44)))} -> Back-Middle-Top-Bottom | AD44: {=_xlfn.TEXTJOIN("",TRUE,LEFT(U44:AA44,1))} -> BMTB | AE44: {=_xlfn.TEXTJOIN("/",TRUE,LEFT(U44:AA44,1))&"/"} -> B/M/T/B/ | AF44: {=_xlfn.TEXTJOIN("-",TRUE,LEFT(U44:AA44,1))&"-"} -> B-M-T-B-
A45: PT45 | B45: 11oz Ceramic Mug | C45: PT45 | D45: 350 | E45: 150 | F45: 500 | G45: Royal Mail Small Parcel | H45: Estimated | T45: B4 | U45: Back | W45: Top | X45: Centre | AB45: {=_xlfn.TEXTJOIN(" ",TRUE,IF(TRIM(U45:AA45)="","",TRIM(U45:AA45)))} -> Back Top Centre | AC45: {=_xlfn.TEXTJOIN("-",TRUE,IF(TRIM(U45:AA45)="","",TRIM(U45:AA45)))} -> Back-Top-Centre | AD45: {=_xlfn.TEXTJOIN("",TRUE,LEFT(U45:AA45,1))} -> BTC | AE45: {=_xlfn.TEXTJOIN("/",TRUE,LEFT(U45:AA45,1))&"/"} -> B/T/C/ | AF45: {=_xlfn.TEXTJOIN("-",TRUE,LEFT(U45:AA45,1))&"-"} -> B-T-C- | AG45: A4 | AH45: A3 | AI45: A2/80
A46: PT46 | B46: 15oz Mug | C46: PT46 | D46: 440 | E46: 160 | F46: 600 | G46: Royal Mail Small Parcel | H46: Estimated | T46: B5 | U46: Back | W46: Left | X46: Middle | Y46: Top | Z46: Bottom | AB46: {=_xlfn.TEXTJOIN(" ",TRUE,IF(TRIM(U46:AA46)="","",TRIM(U46:AA46)))} -> Back Left Middle Top Bottom | AC46: {=_xlfn.TEXTJOIN("-",TRUE,IF(TRIM(U46:AA46)="","",TRIM(U46:AA46)))} -> Back-Left-Middle-Top-Bottom | AD46: {=_xlfn.TEXTJOIN("",TRUE,LEFT(U46:AA46,1))} -> BLMTB | AE46: {=_xlfn.TEXTJOIN("/",TRUE,LEFT(U46:AA46,1))&"/"} -> B/L/M/T/B/ | AF46: {=_xlfn.TEXTJOIN("-",TRUE,LEFT(U46:AA46,1))&"-"} -> B-L-M-T-B-
A47: PT47 | B47: Two-Tone Mug | C47: PT47 | D47: 370 | E47: 150 | F47: 520 | G47: Royal Mail Small Parcel | H47: Estimated | T47: B6 | U47: Back | W47: Right | X47: Middle | Y47: Top | Z47: Bottom | AB47: {=_xlfn.TEXTJOIN(" ",TRUE,IF(TRIM(U47:AA47)="","",TRIM(U47:AA47)))} -> Back Right Middle Top Bottom | AC47: {=_xlfn.TEXTJOIN("-",TRUE,IF(TRIM(U47:AA47)="","",TRIM(U47:AA47)))} -> Back-Right-Middle-Top-Bottom | AD47: {=_xlfn.TEXTJOIN("",TRUE,LEFT(U47:AA47,1))} -> BRMTB | AE47: {=_xlfn.TEXTJOIN("/",TRUE,LEFT(U47:AA47,1))&"/"} -> B/R/M/T/B/ | AF47: {=_xlfn.TEXTJOIN("-",TRUE,LEFT(U47:AA47,1))&"-"} -> B-R-M-T-B-
A48: PT48 | B48: Rim & Handle Colour Mug | C48: PT48 | D48: 360 | E48: 150 | F48: 510 | G48: Royal Mail Small Parcel | H48: Estimated | T48: B7 | U48: Back | W48: Middle | X48: Centre | Y48: Top | Z48: Bottom | AB48: {=_xlfn.TEXTJOIN(" ",TRUE,IF(TRIM(U48:AA48)="","",TRIM(U48:AA48)))} -> Back Middle Centre Top Bottom | AC48: {=_xlfn.TEXTJOIN("-",TRUE,IF(TRIM(U48:AA48)="","",TRIM(U48:AA48)))} -> Back-Middle-Centre-Top-Bottom | AD48: {=_xlfn.TEXTJOIN("",TRUE,LEFT(U48:AA48,1))} -> BMCTB | AE48: {=_xlfn.TEXTJOIN("/",TRUE,LEFT(U48:AA48,1))&"/"} -> B/M/C/T/B/ | AF48: {=_xlfn.TEXTJOIN("-",TRUE,LEFT(U48:AA48,1))&"-"} -> B-M-C-T-B-
A49: PT49 | B49: Magic Heat-Changing Mug | C49: PT49 | D49: 360 | E49: 150 | F49: 510 | G49: Royal Mail Small Parcel | H49: Estimated | T49: B8 | U49: Back | W49: Left | AB49: {=_xlfn.TEXTJOIN(" ",TRUE,IF(TRIM(U49:AA49)="","",TRIM(U49:AA49)))} -> Back Left | AC49: {=_xlfn.TEXTJOIN("-",TRUE,IF(TRIM(U49:AA49)="","",TRIM(U49:AA49)))} -> Back-Left | AD49: {=_xlfn.TEXTJOIN("",TRUE,LEFT(U49:AA49,1))} -> BL | AE49: {=_xlfn.TEXTJOIN("/",TRUE,LEFT(U49:AA49,1))&"/"} -> B/L/ | AF49: {=_xlfn.TEXTJOIN("-",TRUE,LEFT(U49:AA49,1))&"-"} -> B-L- | AG49: A9 | AH49: A8 | AI49: A7
A50: PT50 | B50: Enamel Camping Mug | C50: PT50 | D50: 300 | E50: 140 | F50: 440 | G50: Royal Mail Small Parcel | H50: Estimated | T50: B9 | U50: Back | W50: Right | AB50: {=_xlfn.TEXTJOIN(" ",TRUE,IF(TRIM(U50:AA50)="","",TRIM(U50:AA50)))} -> Back Right | AC50: {=_xlfn.TEXTJOIN("-",TRUE,IF(TRIM(U50:AA50)="","",TRIM(U50:AA50)))} -> Back-Right | AD50: {=_xlfn.TEXTJOIN("",TRUE,LEFT(U50:AA50,1))} -> BR | AE50: {=_xlfn.TEXTJOIN("/",TRUE,LEFT(U50:AA50,1))&"/"} -> B/R/ | AF50: {=_xlfn.TEXTJOIN("-",TRUE,LEFT(U50:AA50,1))&"-"} -> B-R-
A51: PT51 | B51: Travel Mug | C51: PT51 | D51: 460 | E51: 170 | F51: 630 | G51: Royal Mail Small Parcel | H51: Estimated | T51: B10 | U51: Back | W51: Bottom | X51: Left | Y51: Corner | AB51: {=_xlfn.TEXTJOIN(" ",TRUE,IF(TRIM(U51:AA51)="","",TRIM(U51:AA51)))} -> Back Bottom Left Corner | AC51: {=_xlfn.TEXTJOIN("-",TRUE,IF(TRIM(U51:AA51)="","",TRIM(U51:AA51)))} -> Back-Bottom-Left-Corner | AD51: {=_xlfn.TEXTJOIN("",TRUE,LEFT(U51:AA51,1))} -> BBLC | AE51: {=_xlfn.TEXTJOIN("/",TRUE,LEFT(U51:AA51,1))&"/"} -> B/B/L/C/ | AF51: {=_xlfn.TEXTJOIN("-",TRUE,LEFT(U51:AA51,1))&"-"} -> B-B-L-C-
A52: PT52 | B52: Insulated Tumbler | C52: PT52 | T52: B11 | U52: Back | W52: Bottom | X52: Right | Y52: Corner | AB52: {=_xlfn.TEXTJOIN(" ",TRUE,IF(TRIM(U52:AA52)="","",TRIM(U52:AA52)))} -> Back Bottom Right Corner | AC52: {=_xlfn.TEXTJOIN("-",TRUE,IF(TRIM(U52:AA52)="","",TRIM(U52:AA52)))} -> Back-Bottom-Right-Corner | AD52: {=_xlfn.TEXTJOIN("",TRUE,LEFT(U52:AA52,1))} -> BBRC | AE52: {=_xlfn.TEXTJOIN("/",TRUE,LEFT(U52:AA52,1))&"/"} -> B/B/R/C/ | AF52: {=_xlfn.TEXTJOIN("-",TRUE,LEFT(U52:AA52,1))&"-"} -> B-B-R-C-
A53: PT53 | B53: Stainless Steel Water Bottle | C53: PT53 | D53: 200 | E53: 60 | F53: 260 | G53: Large Letter / Small Parcel | H53: Estimated | T53: B12 | U53: Back | W53: Top | X53: Left | Y53: Corner | Z53: Top | AA53: Left | AB53: {=_xlfn.TEXTJOIN(" ",TRUE,IF(TRIM(U53:AA53)="","",TRIM(U53:AA53)))} -> Back Top Left Corner Top Left | AC53: {=_xlfn.TEXTJOIN("-",TRUE,IF(TRIM(U53:AA53)="","",TRIM(U53:AA53)))} -> Back-Top-Left-Corner-Top-Left | AD53: {=_xlfn.TEXTJOIN("",TRUE,LEFT(U53:AA53,1))} -> BTLCTL | AE53: {=_xlfn.TEXTJOIN("/",TRUE,LEFT(U53:AA53,1))&"/"} -> B/T/L/C/T/L/ | AF53: {=_xlfn.TEXTJOIN("-",TRUE,LEFT(U53:AA53,1))&"-"} -> B-T-L-C-T-L-
A54: PT54 | B54: Aluminium Bottle | C54: PT54 | T54: B13 | U54: Back | W54: Top | X54: Right | Y54: Corner | Z54: Top | AA54: Right | AB54: {=_xlfn.TEXTJOIN(" ",TRUE,IF(TRIM(U54:AA54)="","",TRIM(U54:AA54)))} -> Back Top Right Corner Top Right | AC54: {=_xlfn.TEXTJOIN("-",TRUE,IF(TRIM(U54:AA54)="","",TRIM(U54:AA54)))} -> Back-Top-Right-Corner-Top-Right | AD54: {=_xlfn.TEXTJOIN("",TRUE,LEFT(U54:AA54,1))} -> BTRCTR | AE54: {=_xlfn.TEXTJOIN("/",TRUE,LEFT(U54:AA54,1))&"/"} -> B/T/R/C/T/R/ | AF54: {=_xlfn.TEXTJOIN("-",TRUE,LEFT(U54:AA54,1))&"-"} -> B-T-R-C-T-R-
A55: PT55 | B55: Wine Glass (Printed) | C55: PT55 | D55: 70 | E55: 50 | F55: 120 | G55: Royal Mail Large Letter | H55: Estimated | T55: B14 | U55: Back | W55: Top | X55: Left | Y55: Corner | AB55: {=_xlfn.TEXTJOIN(" ",TRUE,IF(TRIM(U55:AA55)="","",TRIM(U55:AA55)))} -> Back Top Left Corner | AC55: {=_xlfn.TEXTJOIN("-",TRUE,IF(TRIM(U55:AA55)="","",TRIM(U55:AA55)))} -> Back-Top-Left-Corner | AD55: {=_xlfn.TEXTJOIN("",TRUE,LEFT(U55:AA55,1))} -> BTLC | AE55: {=_xlfn.TEXTJOIN("/",TRUE,LEFT(U55:AA55,1))&"/"} -> B/T/L/C/ | AF55: {=_xlfn.TEXTJOIN("-",TRUE,LEFT(U55:AA55,1))&"-"} -> B-T-L-C-
A56: PT56 | B56: Beer Glass | C56: PT56 | D56: 1100 | E56: 300 | F56: 1400 | G56: Royal Mail Small Parcel | H56: Estimated | T56: B15 | U56: Back | W56: Top | X56: Right | Y56: Corner | AB56: {=_xlfn.TEXTJOIN(" ",TRUE,IF(TRIM(U56:AA56)="","",TRIM(U56:AA56)))} -> Back Top Right Corner | AC56: {=_xlfn.TEXTJOIN("-",TRUE,IF(TRIM(U56:AA56)="","",TRIM(U56:AA56)))} -> Back-Top-Right-Corner | AD56: {=_xlfn.TEXTJOIN("",TRUE,LEFT(U56:AA56,1))} -> BTRC | AE56: {=_xlfn.TEXTJOIN("/",TRUE,LEFT(U56:AA56,1))&"/"} -> B/T/R/C/ | AF56: {=_xlfn.TEXTJOIN("-",TRUE,LEFT(U56:AA56,1))&"-"} -> B-T-R-C-
A57: PT57 | B57: Frosted Glass Mug | C57: PT57 | D57: 360 | E57: 150 | F57: 510 | G57: Royal Mail Small Parcel | H57: Estimated | T57: B16 | U57: Back | W57: Top | X57: Left | Y57: Bottom | Z57: Right | AA57: Corner | AB57: {=_xlfn.TEXTJOIN(" ",TRUE,IF(TRIM(U57:AA57)="","",TRIM(U57:AA57)))} -> Back Top Left Bottom Right Corner | AC57: {=_xlfn.TEXTJOIN("-",TRUE,IF(TRIM(U57:AA57)="","",TRIM(U57:AA57)))} -> Back-Top-Left-Bottom-Right-Corner | AD57: {=_xlfn.TEXTJOIN("",TRUE,LEFT(U57:AA57,1))} -> BTLBRC | AE57: {=_xlfn.TEXTJOIN("/",TRUE,LEFT(U57:AA57,1))&"/"} -> B/T/L/B/R/C/ | AF57: {=_xlfn.TEXTJOIN("-",TRUE,LEFT(U57:AA57,1))&"-"} -> B-T-L-B-R-C-
A58: PT58 | B58: Shot Glass | C58: PT58 | D58: 1100 | E58: 300 | F58: 1400 | G58: Royal Mail Small Parcel | H58: Estimated | T58: B17 | U58: Back | W58: Top | X58: Right | Y58: Corner | Z58: Left | AA58: Corner | AB58: {=_xlfn.TEXTJOIN(" ",TRUE,IF(TRIM(U58:AA58)="","",TRIM(U58:AA58)))} -> Back Top Right Corner Left Corner | AC58: {=_xlfn.TEXTJOIN("-",TRUE,IF(TRIM(U58:AA58)="","",TRIM(U58:AA58)))} -> Back-Top-Right-Corner-Left-Corner | AD58: {=_xlfn.TEXTJOIN("",TRUE,LEFT(U58:AA58,1))} -> BTRCLC | AE58: {=_xlfn.TEXTJOIN("/",TRUE,LEFT(U58:AA58,1))&"/"} -> B/T/R/C/L/C/ | AF58: {=_xlfn.TEXTJOIN("-",TRUE,LEFT(U58:AA58,1))&"-"} -> B-T-R-C-L-C-
A59: PT59 | B59: Latte Mug | C59: PT59 | D59: 360 | E59: 150 | F59: 510 | G59: Royal Mail Small Parcel | H59: Estimated | T59: B18 | U59: Back | W59: Bottom | X59: Left | Y59: Corner | Z59: Top | AA59: Left | AB59: {=_xlfn.TEXTJOIN(" ",TRUE,IF(TRIM(U59:AA59)="","",TRIM(U59:AA59)))} -> Back Bottom Left Corner Top Left | AC59: {=_xlfn.TEXTJOIN("-",TRUE,IF(TRIM(U59:AA59)="","",TRIM(U59:AA59)))} -> Back-Bottom-Left-Corner-Top-Left | AD59: {=_xlfn.TEXTJOIN("",TRUE,LEFT(U59:AA59,1))} -> BBLCTL | AE59: {=_xlfn.TEXTJOIN("/",TRUE,LEFT(U59:AA59,1))&"/"} -> B/B/L/C/T/L/ | AF59: {=_xlfn.TEXTJOIN("-",TRUE,LEFT(U59:AA59,1))&"-"} -> B-B-L-C-T-L-
A60: PT60 | B60: Mason Jar Mug (Printed) | C60: PT60 | D60: 70 | E60: 50 | F60: 120 | G60: Royal Mail Large Letter | H60: Estimated | T60: B19 | U60: Back | W60: Bottom | X60: Right | Y60: Corner | Z60: Top | AA60: Left | AB60: {=_xlfn.TEXTJOIN(" ",TRUE,IF(TRIM(U60:AA60)="","",TRIM(U60:AA60)))} -> Back Bottom Right Corner Top Left | AC60: {=_xlfn.TEXTJOIN("-",TRUE,IF(TRIM(U60:AA60)="","",TRIM(U60:AA60)))} -> Back-Bottom-Right-Corner-Top-Left | AD60: {=_xlfn.TEXTJOIN("",TRUE,LEFT(U60:AA60,1))} -> BBRCTL | AE60: {=_xlfn.TEXTJOIN("/",TRUE,LEFT(U60:AA60,1))&"/"} -> B/B/R/C/T/L/ | AF60: {=_xlfn.TEXTJOIN("-",TRUE,LEFT(U60:AA60,1))&"-"} -> B-B-R-C-T-L-
A61: PT61 | B61: 🟩 3. POD HOME & LIVING | C61: PT61 | T61: B20 | U61: Back | W61: Bottom | X61: Left | Y61: Corner | Z61: Top | AA61: Right | AB61: {=_xlfn.TEXTJOIN(" ",TRUE,IF(TRIM(U61:AA61)="","",TRIM(U61:AA61)))} -> Back Bottom Left Corner Top Right | AC61: {=_xlfn.TEXTJOIN("-",TRUE,IF(TRIM(U61:AA61)="","",TRIM(U61:AA61)))} -> Back-Bottom-Left-Corner-Top-Right | AD61: {=_xlfn.TEXTJOIN("",TRUE,LEFT(U61:AA61,1))} -> BBLCTR | AE61: {=_xlfn.TEXTJOIN("/",TRUE,LEFT(U61:AA61,1))&"/"} -> B/B/L/C/T/R/ | AF61: {=_xlfn.TEXTJOIN("-",TRUE,LEFT(U61:AA61,1))&"-"} -> B-B-L-C-T-R-
A62: PT62 | B62: Product Type: Personalised Home Decor | C62: PT62 | T62: B21 | U62: Back | W62: Bottom | X62: Right | Y62: Corner | Z62: Top | AA62: Right | AB62: {=_xlfn.TEXTJOIN(" ",TRUE,IF(TRIM(U62:AA62)="","",TRIM(U62:AA62)))} -> Back Bottom Right Corner Top Right | AC62: {=_xlfn.TEXTJOIN("-",TRUE,IF(TRIM(U62:AA62)="","",TRIM(U62:AA62)))} -> Back-Bottom-Right-Corner-Top-Right | AD62: {=_xlfn.TEXTJOIN("",TRUE,LEFT(U62:AA62,1))} -> BBRCTR | AE62: {=_xlfn.TEXTJOIN("/",TRUE,LEFT(U62:AA62,1))&"/"} -> B/B/R/C/T/R/ | AF62: {=_xlfn.TEXTJOIN("-",TRUE,LEFT(U62:AA62,1))&"-"} -> B-B-R-C-T-R-
A63: PT63 | B63: CUSHIONS / PILLOWS | C63: PT63 | T63: B22 | U63: Back | W63: Left | X63: Middle | Z63: Top | AA63: Left | AB63: {=_xlfn.TEXTJOIN(" ",TRUE,IF(TRIM(U63:AA63)="","",TRIM(U63:AA63)))} -> Back Left Middle Top Left | AC63: {=_xlfn.TEXTJOIN("-",TRUE,IF(TRIM(U63:AA63)="","",TRIM(U63:AA63)))} -> Back-Left-Middle-Top-Left | AD63: {=_xlfn.TEXTJOIN("",TRUE,LEFT(U63:AA63,1))} -> BLMTL | AE63: {=_xlfn.TEXTJOIN("/",TRUE,LEFT(U63:AA63,1))&"/"} -> B/L/M/T/L/ | AF63: {=_xlfn.TEXTJOIN("-",TRUE,LEFT(U63:AA63,1))&"-"} -> B-L-M-T-L-
A64: PT64 | B64: Throw Pillow (Square) | C64: PT64 | T64: B23 | U64: Back | W64: Right | X64: Middle | Z64: Top | AA64: Left | AB64: {=_xlfn.TEXTJOIN(" ",TRUE,IF(TRIM(U64:AA64)="","",TRIM(U64:AA64)))} -> Back Right Middle Top Left | AC64: {=_xlfn.TEXTJOIN("-",TRUE,IF(TRIM(U64:AA64)="","",TRIM(U64:AA64)))} -> Back-Right-Middle-Top-Left | AD64: {=_xlfn.TEXTJOIN("",TRUE,LEFT(U64:AA64,1))} -> BRMTL | AE64: {=_xlfn.TEXTJOIN("/",TRUE,LEFT(U64:AA64,1))&"/"} -> B/R/M/T/L/ | AF64: {=_xlfn.TEXTJOIN("-",TRUE,LEFT(U64:AA64,1))&"-"} -> B-R-M-T-L-
A65: PT65 | B65: Lumbar Pillow | C65: PT65 | T65: B24 | U65: Back | W65: Middle | X65: Centre | Z65: Top | AA65: Left | AB65: {=_xlfn.TEXTJOIN(" ",TRUE,IF(TRIM(U65:AA65)="","",TRIM(U65:AA65)))} -> Back Middle Centre Top Left | AC65: {=_xlfn.TEXTJOIN("-",TRUE,IF(TRIM(U65:AA65)="","",TRIM(U65:AA65)))} -> Back-Middle-Centre-Top-Left | AD65: {=_xlfn.TEXTJOIN("",TRUE,LEFT(U65:AA65,1))} -> BMCTL | AE65: {=_xlfn.TEXTJOIN("/",TRUE,LEFT(U65:AA65,1))&"/"} -> B/M/C/T/L/ | AF65: {=_xlfn.TEXTJOIN("-",TRUE,LEFT(U65:AA65,1))&"-"} -> B-M-C-T-L-
A66: PT66 | B66: Sequin Pillow | C66: PT66 | T66: B25 | U66: Back | W66: Left | X66: Middle | Z66: Top | AA66: Right | AB66: {=_xlfn.TEXTJOIN(" ",TRUE,IF(TRIM(U66:AA66)="","",TRIM(U66:AA66)))} -> Back Left Middle Top Right | AC66: {=_xlfn.TEXTJOIN("-",TRUE,IF(TRIM(U66:AA66)="","",TRIM(U66:AA66)))} -> Back-Left-Middle-Top-Right | AD66: {=_xlfn.TEXTJOIN("",TRUE,LEFT(U66:AA66,1))} -> BLMTR | AE66: {=_xlfn.TEXTJOIN("/",TRUE,LEFT(U66:AA66,1))&"/"} -> B/L/M/T/R/ | AF66: {=_xlfn.TEXTJOIN("-",TRUE,LEFT(U66:AA66,1))&"-"} -> B-L-M-T-R-
A67: PT67 | B67: Photo Cushion Cover | C67: PT67 | D67: 150 | E67: 60 | F67: 210 | G67: Royal Mail Large Letter | H67: Estimated | T67: B26 | U67: Back | W67: Right | X67: Middle | Z67: Top | AA67: Right | AB67: {=_xlfn.TEXTJOIN(" ",TRUE,IF(TRIM(U67:AA67)="","",TRIM(U67:AA67)))} -> Back Right Middle Top Right | AC67: {=_xlfn.TEXTJOIN("-",TRUE,IF(TRIM(U67:AA67)="","",TRIM(U67:AA67)))} -> Back-Right-Middle-Top-Right | AD67: {=_xlfn.TEXTJOIN("",TRUE,LEFT(U67:AA67,1))} -> BRMTR | AE67: {=_xlfn.TEXTJOIN("/",TRUE,LEFT(U67:AA67,1))&"/"} -> B/R/M/T/R/ | AF67: {=_xlfn.TEXTJOIN("-",TRUE,LEFT(U67:AA67,1))&"-"} -> B-R-M-T-R-
A68: PT68 | B68: BLANKETS | C68: PT68 | T68: B27 | U68: Back | W68: Middle | X68: Centre | Z68: Top | AA68: Right | AB68: {=_xlfn.TEXTJOIN(" ",TRUE,IF(TRIM(U68:AA68)="","",TRIM(U68:AA68)))} -> Back Middle Centre Top Right | AC68: {=_xlfn.TEXTJOIN("-",TRUE,IF(TRIM(U68:AA68)="","",TRIM(U68:AA68)))} -> Back-Middle-Centre-Top-Right | AD68: {=_xlfn.TEXTJOIN("",TRUE,LEFT(U68:AA68,1))} -> BMCTR | AE68: {=_xlfn.TEXTJOIN("/",TRUE,LEFT(U68:AA68,1))&"/"} -> B/M/C/T/R/ | AF68: {=_xlfn.TEXTJOIN("-",TRUE,LEFT(U68:AA68,1))&"-"} -> B-M-C-T-R-
A69: PT69 | B69: Sherpa Blanket | C69: PT69 | T69: B28 | U69: Back | W69: Bottom | X69: Left | Y69: Right | AB69: {=_xlfn.TEXTJOIN(" ",TRUE,IF(TRIM(U69:AA69)="","",TRIM(U69:AA69)))} -> Back Bottom Left Right | AC69: {=_xlfn.TEXTJOIN("-",TRUE,IF(TRIM(U69:AA69)="","",TRIM(U69:AA69)))} -> Back-Bottom-Left-Right | AD69: {=_xlfn.TEXTJOIN("",TRUE,LEFT(U69:AA69,1))} -> BBLR | AE69: {=_xlfn.TEXTJOIN("/",TRUE,LEFT(U69:AA69,1))&"/"} -> B/B/L/R/ | AF69: {=_xlfn.TEXTJOIN("-",TRUE,LEFT(U69:AA69,1))&"-"} -> B-B-L-R-
A70: PT70 | B70: Fleece Blanket | C70: PT70 | T70: B29 | U70: Back | W70: Centre | X70: Left | Y70: Right | AB70: {=_xlfn.TEXTJOIN(" ",TRUE,IF(TRIM(U70:AA70)="","",TRIM(U70:AA70)))} -> Back Centre Left Right | AC70: {=_xlfn.TEXTJOIN("-",TRUE,IF(TRIM(U70:AA70)="","",TRIM(U70:AA70)))} -> Back-Centre-Left-Right | AD70: {=_xlfn.TEXTJOIN("",TRUE,LEFT(U70:AA70,1))} -> BCLR | AE70: {=_xlfn.TEXTJOIN("/",TRUE,LEFT(U70:AA70,1))&"/"} -> B/C/L/R/ | AF70: {=_xlfn.TEXTJOIN("-",TRUE,LEFT(U70:AA70,1))&"-"} -> B-C-L-R-
A71: PT71 | B71: Woven Blanket | C71: PT71 | T71: B30 | U71: Back | W71: Bottom | X71: Corner | Z71: Top | AA71: Bottom | AB71: {=_xlfn.TEXTJOIN(" ",TRUE,IF(TRIM(U71:AA71)="","",TRIM(U71:AA71)))} -> Back Bottom Corner Top Bottom | AC71: {=_xlfn.TEXTJOIN("-",TRUE,IF(TRIM(U71:AA71)="","",TRIM(U71:AA71)))} -> Back-Bottom-Corner-Top-Bottom | AD71: {=_xlfn.TEXTJOIN("",TRUE,LEFT(U71:AA71,1))} -> BBCTB | AE71: {=_xlfn.TEXTJOIN("/",TRUE,LEFT(U71:AA71,1))&"/"} -> B/B/C/T/B/ | AF71: {=_xlfn.TEXTJOIN("-",TRUE,LEFT(U71:AA71,1))&"-"} -> B-B-C-T-B-
A72: PT72 | B72: Photo Collage Blanket | C72: PT72 | T72: B31 | U72: Back | W72: Bottom | X72: Corner | Z72: Top | AA72: Bottom | AB72: {=_xlfn.TEXTJOIN(" ",TRUE,IF(TRIM(U72:AA72)="","",TRIM(U72:AA72)))} -> Back Bottom Corner Top Bottom | AC72: {=_xlfn.TEXTJOIN("-",TRUE,IF(TRIM(U72:AA72)="","",TRIM(U72:AA72)))} -> Back-Bottom-Corner-Top-Bottom | AD72: {=_xlfn.TEXTJOIN("",TRUE,LEFT(U72:AA72,1))} -> BBCTB | AE72: {=_xlfn.TEXTJOIN("/",TRUE,LEFT(U72:AA72,1))&"/"} -> B/B/C/T/B/ | AF72: {=_xlfn.TEXTJOIN("-",TRUE,LEFT(U72:AA72,1))&"-"} -> B-B-C-T-B-
A73: PT73 | B73: TOWELS | C73: PT73 | T73: B32 | U73: Back | W73: Bottom | X73: Middle | Z73: Top | AA73: Bottom | AB73: {=_xlfn.TEXTJOIN(" ",TRUE,IF(TRIM(U73:AA73)="","",TRIM(U73:AA73)))} -> Back Bottom Middle Top Bottom | AC73: {=_xlfn.TEXTJOIN("-",TRUE,IF(TRIM(U73:AA73)="","",TRIM(U73:AA73)))} -> Back-Bottom-Middle-Top-Bottom | AD73: {=_xlfn.TEXTJOIN("",TRUE,LEFT(U73:AA73,1))} -> BBMTB | AE73: {=_xlfn.TEXTJOIN("/",TRUE,LEFT(U73:AA73,1))&"/"} -> B/B/M/T/B/ | AF73: {=_xlfn.TEXTJOIN("-",TRUE,LEFT(U73:AA73,1))&"-"} -> B-B-M-T-B-
A74: PT74 | B74: Bath Towel | C74: PT74 | D74: 180 | E74: 60 | F74: 240 | G74: Royal Mail Large Letter | H74: Estimated | T74: B33 | U74: Back | W74: Top | X74: Left | Y74: Corner | Z74: Top | AA74: Right | AB74: {=_xlfn.TEXTJOIN(" ",TRUE,IF(TRIM(U74:AA74)="","",TRIM(U74:AA74)))} -> Back Top Left Corner Top Right | AC74: {=_xlfn.TEXTJOIN("-",TRUE,IF(TRIM(U74:AA74)="","",TRIM(U74:AA74)))} -> Back-Top-Left-Corner-Top-Right | AD74: {=_xlfn.TEXTJOIN("",TRUE,LEFT(U74:AA74,1))} -> BTLCTR | AE74: {=_xlfn.TEXTJOIN("/",TRUE,LEFT(U74:AA74,1))&"/"} -> B/T/L/C/T/R/ | AF74: {=_xlfn.TEXTJOIN("-",TRUE,LEFT(U74:AA74,1))&"-"} -> B-T-L-C-T-R-
A75: PT75 | B75: Beach Towel | C75: PT75 | D75: 180 | E75: 60 | F75: 240 | G75: Royal Mail Large Letter | H75: Estimated | T75: B34 | U75: Back | W75: Top | X75: Right | Y75: Corner | Z75: Top | AA75: Left | AB75: {=_xlfn.TEXTJOIN(" ",TRUE,IF(TRIM(U75:AA75)="","",TRIM(U75:AA75)))} -> Back Top Right Corner Top Left | AC75: {=_xlfn.TEXTJOIN("-",TRUE,IF(TRIM(U75:AA75)="","",TRIM(U75:AA75)))} -> Back-Top-Right-Corner-Top-Left | AD75: {=_xlfn.TEXTJOIN("",TRUE,LEFT(U75:AA75,1))} -> BTRCTL | AE75: {=_xlfn.TEXTJOIN("/",TRUE,LEFT(U75:AA75,1))&"/"} -> B/T/R/C/T/L/ | AF75: {=_xlfn.TEXTJOIN("-",TRUE,LEFT(U75:AA75,1))&"-"} -> B-T-R-C-T-L-
A76: PT76 | B76: Sports Towel | C76: PT76 | D76: 180 | E76: 60 | F76: 240 | G76: Royal Mail Large Letter | H76: Estimated | T76: B35 | U76: Back | W76: Top | AB76: {=_xlfn.TEXTJOIN(" ",TRUE,IF(TRIM(U76:AA76)="","",TRIM(U76:AA76)))} -> Back Top | AC76: {=_xlfn.TEXTJOIN("-",TRUE,IF(TRIM(U76:AA76)="","",TRIM(U76:AA76)))} -> Back-Top | AD76: {=_xlfn.TEXTJOIN("",TRUE,LEFT(U76:AA76,1))} -> BT | AE76: {=_xlfn.TEXTJOIN("/",TRUE,LEFT(U76:AA76,1))&"/"} -> B/T/ | AF76: {=_xlfn.TEXTJOIN("-",TRUE,LEFT(U76:AA76,1))&"-"} -> B-T-
A77: PT77 | B77: MATS | C77: PT77 | T77: B36 | U77: Back | AB77: {=_xlfn.TEXTJOIN(" ",TRUE,IF(TRIM(U77:AA77)="","",TRIM(U77:AA77)))} -> Back | AC77: {=_xlfn.TEXTJOIN("-",TRUE,IF(TRIM(U77:AA77)="","",TRIM(U77:AA77)))} -> Back | AD77: {=_xlfn.TEXTJOIN("",TRUE,LEFT(U77:AA77,1))} -> B | AE77: {=_xlfn.TEXTJOIN("/",TRUE,LEFT(U77:AA77,1))&"/"} -> B/ | AF77: {=_xlfn.TEXTJOIN("-",TRUE,LEFT(U77:AA77,1))&"-"} -> B-
A78: PT78 | B78: Doormat | C78: PT78 | T78: B37 | U78: Back | AB78: {=_xlfn.TEXTJOIN(" ",TRUE,IF(TRIM(U78:AA78)="","",TRIM(U78:AA78)))} -> Back | AC78: {=_xlfn.TEXTJOIN("-",TRUE,IF(TRIM(U78:AA78)="","",TRIM(U78:AA78)))} -> Back | AD78: {=_xlfn.TEXTJOIN("",TRUE,LEFT(U78:AA78,1))} -> B | AE78: {=_xlfn.TEXTJOIN("/",TRUE,LEFT(U78:AA78,1))&"/"} -> B/ | AF78: {=_xlfn.TEXTJOIN("-",TRUE,LEFT(U78:AA78,1))&"-"} -> B-
A79: PT79 | B79: Kitchen Mat | C79: PT79 | T79: B38 | U79: Back | AB79: {=_xlfn.TEXTJOIN(" ",TRUE,IF(TRIM(U79:AA79)="","",TRIM(U79:AA79)))} -> Back | AC79: {=_xlfn.TEXTJOIN("-",TRUE,IF(TRIM(U79:AA79)="","",TRIM(U79:AA79)))} -> Back | AD79: {=_xlfn.TEXTJOIN("",TRUE,LEFT(U79:AA79,1))} -> B | AE79: {=_xlfn.TEXTJOIN("/",TRUE,LEFT(U79:AA79,1))&"/"} -> B/ | AF79: {=_xlfn.TEXTJOIN("-",TRUE,LEFT(U79:AA79,1))&"-"} -> B-
A80: PT80 | B80: Bath Mat | C80: PT80 | T80: B39 | U80: Back | AB80: {=_xlfn.TEXTJOIN(" ",TRUE,IF(TRIM(U80:AA80)="","",TRIM(U80:AA80)))} -> Back | AC80: {=_xlfn.TEXTJOIN("-",TRUE,IF(TRIM(U80:AA80)="","",TRIM(U80:AA80)))} -> Back | AD80: {=_xlfn.TEXTJOIN("",TRUE,LEFT(U80:AA80,1))} -> B | AE80: {=_xlfn.TEXTJOIN("/",TRUE,LEFT(U80:AA80,1))&"/"} -> B/ | AF80: {=_xlfn.TEXTJOIN("-",TRUE,LEFT(U80:AA80,1))&"-"} -> B-
A81: PT81 | B81: KITCHEN & DINING | C81: PT81 | T81: B40 | U81: Back | AB81: {=_xlfn.TEXTJOIN(" ",TRUE,IF(TRIM(U81:AA81)="","",TRIM(U81:AA81)))} -> Back | AC81: {=_xlfn.TEXTJOIN("-",TRUE,IF(TRIM(U81:AA81)="","",TRIM(U81:AA81)))} -> Back | AD81: {=_xlfn.TEXTJOIN("",TRUE,LEFT(U81:AA81,1))} -> B | AE81: {=_xlfn.TEXTJOIN("/",TRUE,LEFT(U81:AA81,1))&"/"} -> B/ | AF81: {=_xlfn.TEXTJOIN("-",TRUE,LEFT(U81:AA81,1))&"-"} -> B-
A82: PT82 | B82: Apron | C82: PT82 | D82: 230 | E82: 70 | F82: 300 | G82: Royal Mail Large Letter | H82: Estimated | T82: L1 | U82: Left | V82: Sleeve | W82: Left | Y82: Top | Z82: Bottom | AB82: {=_xlfn.TEXTJOIN(" ",TRUE,IF(TRIM(U82:AA82)="","",TRIM(U82:AA82)))} -> Left Sleeve Left Top Bottom | AC82: {=_xlfn.TEXTJOIN("-",TRUE,IF(TRIM(U82:AA82)="","",TRIM(U82:AA82)))} -> Left-Sleeve-Left-Top-Bottom | AD82: {=_xlfn.TEXTJOIN("",TRUE,LEFT(U82:AA82,1))} -> LSLTB | AE82: {=_xlfn.TEXTJOIN("/",TRUE,LEFT(U82:AA82,1))&"/"} -> L/S/L/T/B/ | AF82: {=_xlfn.TEXTJOIN("-",TRUE,LEFT(U82:AA82,1))&"-"} -> L-S-L-T-B- | AG82: A3-1
A83: PT83 | B83: Tea Towel | C83: PT83 | D83: 180 | E83: 60 | F83: 240 | G83: Royal Mail Large Letter | H83: Estimated | T83: L2 | U83: Left | V83: Sleeve | W83: Right | Y83: Top | Z83: Bottom | AB83: {=_xlfn.TEXTJOIN(" ",TRUE,IF(TRIM(U83:AA83)="","",TRIM(U83:AA83)))} -> Left Sleeve Right Top Bottom | AC83: {=_xlfn.TEXTJOIN("-",TRUE,IF(TRIM(U83:AA83)="","",TRIM(U83:AA83)))} -> Left-Sleeve-Right-Top-Bottom | AD83: {=_xlfn.TEXTJOIN("",TRUE,LEFT(U83:AA83,1))} -> LSRTB | AE83: {=_xlfn.TEXTJOIN("/",TRUE,LEFT(U83:AA83,1))&"/"} -> L/S/R/T/B/ | AF83: {=_xlfn.TEXTJOIN("-",TRUE,LEFT(U83:AA83,1))&"-"} -> L-S-R-T-B- | AG83: A3-1
A84: PT84 | B84: Oven Mitt | C84: PT84 | T84: L3 | U84: Left | V84: Sleeve | W84: Middle | Y84: Top | Z84: Bottom | AB84: {=_xlfn.TEXTJOIN(" ",TRUE,IF(TRIM(U84:AA84)="","",TRIM(U84:AA84)))} -> Left Sleeve Middle Top Bottom | AC84: {=_xlfn.TEXTJOIN("-",TRUE,IF(TRIM(U84:AA84)="","",TRIM(U84:AA84)))} -> Left-Sleeve-Middle-Top-Bottom | AD84: {=_xlfn.TEXTJOIN("",TRUE,LEFT(U84:AA84,1))} -> LSMTB | AE84: {=_xlfn.TEXTJOIN("/",TRUE,LEFT(U84:AA84,1))&"/"} -> L/S/M/T/B/ | AF84: {=_xlfn.TEXTJOIN("-",TRUE,LEFT(U84:AA84,1))&"-"} -> L-S-M-T-B- | AG84: A3-1
A85: PT85 | B85: Pot Holder | C85: PT85 | T85: L4 | U85: Left | V85: Sleeve | W85: Top | X85: Centre | AB85: {=_xlfn.TEXTJOIN(" ",TRUE,IF(TRIM(U85:AA85)="","",TRIM(U85:AA85)))} -> Left Sleeve Top Centre | AC85: {=_xlfn.TEXTJOIN("-",TRUE,IF(TRIM(U85:AA85)="","",TRIM(U85:AA85)))} -> Left-Sleeve-Top-Centre | AD85: {=_xlfn.TEXTJOIN("",TRUE,LEFT(U85:AA85,1))} -> LSTC | AE85: {=_xlfn.TEXTJOIN("/",TRUE,LEFT(U85:AA85,1))&"/"} -> L/S/T/C/ | AF85: {=_xlfn.TEXTJOIN("-",TRUE,LEFT(U85:AA85,1))&"-"} -> L-S-T-C- | AG85: A9 | AH85: A8
A86: PT86 | B86: Cutting Board (Glass) | C86: PT86 | D86: 1100 | E86: 300 | F86: 1400 | G86: Royal Mail Small Parcel | H86: Estimated | T86: L5 | U86: Left | V86: Sleeve | W86: Left | X86: Middle | Y86: Top | Z86: Bottom | AB86: {=_xlfn.TEXTJOIN(" ",TRUE,IF(TRIM(U86:AA86)="","",TRIM(U86:AA86)))} -> Left Sleeve Left Middle Top Bottom | AC86: {=_xlfn.TEXTJOIN("-",TRUE,IF(TRIM(U86:AA86)="","",TRIM(U86:AA86)))} -> Left-Sleeve-Left-Middle-Top-Bottom | AD86: {=_xlfn.TEXTJOIN("",TRUE,LEFT(U86:AA86,1))} -> LSLMTB | AE86: {=_xlfn.TEXTJOIN("/",TRUE,LEFT(U86:AA86,1))&"/"} -> L/S/L/M/T/B/ | AF86: {=_xlfn.TEXTJOIN("-",TRUE,LEFT(U86:AA86,1))&"-"} -> L-S-L-M-T-B- | AG86: A3-1
A87: PT87 | B87: BEDDING | C87: PT87 | T87: L6 | U87: Left | V87: Sleeve | W87: Right | X87: Middle | Y87: Top | Z87: Bottom | AB87: {=_xlfn.TEXTJOIN(" ",TRUE,IF(TRIM(U87:AA87)="","",TRIM(U87:AA87)))} -> Left Sleeve Right Middle Top Bottom | AC87: {=_xlfn.TEXTJOIN("-",TRUE,IF(TRIM(U87:AA87)="","",TRIM(U87:AA87)))} -> Left-Sleeve-Right-Middle-Top-Bottom | AD87: {=_xlfn.TEXTJOIN("",TRUE,LEFT(U87:AA87,1))} -> LSRMTB | AE87: {=_xlfn.TEXTJOIN("/",TRUE,LEFT(U87:AA87,1))&"/"} -> L/S/R/M/T/B/ | AF87: {=_xlfn.TEXTJOIN("-",TRUE,LEFT(U87:AA87,1))&"-"} -> L-S-R-M-T-B- | AG87: A3-1
A88: PT88 | B88: Duvet Cover | C88: PT88 | T88: L7 | U88: Left | V88: Sleeve | W88: Middle | X88: Centre | Y88: Top | Z88: Bottom | AB88: {=_xlfn.TEXTJOIN(" ",TRUE,IF(TRIM(U88:AA88)="","",TRIM(U88:AA88)))} -> Left Sleeve Middle Centre Top Bottom | AC88: {=_xlfn.TEXTJOIN("-",TRUE,IF(TRIM(U88:AA88)="","",TRIM(U88:AA88)))} -> Left-Sleeve-Middle-Centre-Top-Bottom | AD88: {=_xlfn.TEXTJOIN("",TRUE,LEFT(U88:AA88,1))} -> LSMCTB | AE88: {=_xlfn.TEXTJOIN("/",TRUE,LEFT(U88:AA88,1))&"/"} -> L/S/M/C/T/B/ | AF88: {=_xlfn.TEXTJOIN("-",TRUE,LEFT(U88:AA88,1))&"-"} -> L-S-M-C-T-B- | AG88: A3-1
A89: PT89 | B89: Pillowcase | C89: PT89 | T89: L8 | U89: Left | V89: Sleeve | W89: Left | AB89: {=_xlfn.TEXTJOIN(" ",TRUE,IF(TRIM(U89:AA89)="","",TRIM(U89:AA89)))} -> Left Sleeve Left | AC89: {=_xlfn.TEXTJOIN("-",TRUE,IF(TRIM(U89:AA89)="","",TRIM(U89:AA89)))} -> Left-Sleeve-Left | AD89: {=_xlfn.TEXTJOIN("",TRUE,LEFT(U89:AA89,1))} -> LSL | AE89: {=_xlfn.TEXTJOIN("/",TRUE,LEFT(U89:AA89,1))&"/"} -> L/S/L/ | AF89: {=_xlfn.TEXTJOIN("-",TRUE,LEFT(U89:AA89,1))&"-"} -> L-S-L-
A90: PT90 | B90: Bedsheet Prints | C90: PT90 | D90: 70 | E90: 50 | F90: 120 | G90: Royal Mail Large Letter | H90: Estimated | T90: L9 | U90: Left | V90: Sleeve | W90: Right | AB90: {=_xlfn.TEXTJOIN(" ",TRUE,IF(TRIM(U90:AA90)="","",TRIM(U90:AA90)))} -> Left Sleeve Right | AC90: {=_xlfn.TEXTJOIN("-",TRUE,IF(TRIM(U90:AA90)="","",TRIM(U90:AA90)))} -> Left-Sleeve-Right | AD90: {=_xlfn.TEXTJOIN("",TRUE,LEFT(U90:AA90,1))} -> LSR | AE90: {=_xlfn.TEXTJOIN("/",TRUE,LEFT(U90:AA90,1))&"/"} -> L/S/R/ | AF90: {=_xlfn.TEXTJOIN("-",TRUE,LEFT(U90:AA90,1))&"-"} -> L-S-R-
A91: PT91 | B91: 🟪 4. POD ACCESSORIES | C91: PT91 | T91: L10 | U91: Left | V91: Sleeve | W91: Bottom | X91: Left | Y91: Corner | AB91: {=_xlfn.TEXTJOIN(" ",TRUE,IF(TRIM(U91:AA91)="","",TRIM(U91:AA91)))} -> Left Sleeve Bottom Left Corner | AC91: {=_xlfn.TEXTJOIN("-",TRUE,IF(TRIM(U91:AA91)="","",TRIM(U91:AA91)))} -> Left-Sleeve-Bottom-Left-Corner | AD91: {=_xlfn.TEXTJOIN("",TRUE,LEFT(U91:AA91,1))} -> LSBLC | AE91: {=_xlfn.TEXTJOIN("/",TRUE,LEFT(U91:AA91,1))&"/"} -> L/S/B/L/C/ | AF91: {=_xlfn.TEXTJOIN("-",TRUE,LEFT(U91:AA91,1))&"-"} -> L-S-B-L-C-
A92: PT92 | B92: Product Type: Everyday Personal Gifts | C92: PT92 | T92: L11 | U92: Left | V92: Sleeve | W92: Bottom | X92: Right | Y92: Corner | AB92: {=_xlfn.TEXTJOIN(" ",TRUE,IF(TRIM(U92:AA92)="","",TRIM(U92:AA92)))} -> Left Sleeve Bottom Right Corner | AC92: {=_xlfn.TEXTJOIN("-",TRUE,IF(TRIM(U92:AA92)="","",TRIM(U92:AA92)))} -> Left-Sleeve-Bottom-Right-Corner | AD92: {=_xlfn.TEXTJOIN("",TRUE,LEFT(U92:AA92,1))} -> LSBRC | AE92: {=_xlfn.TEXTJOIN("/",TRUE,LEFT(U92:AA92,1))&"/"} -> L/S/B/R/C/ | AF92: {=_xlfn.TEXTJOIN("-",TRUE,LEFT(U92:AA92,1))&"-"} -> L-S-B-R-C-
A93: PT93 | B93: BAGS | C93: PT93 | T93: L12 | U93: Left | V93: Sleeve | W93: Top | X93: Left | Y93: Corner | Z93: Top | AA93: Left | AB93: {=_xlfn.TEXTJOIN(" ",TRUE,IF(TRIM(U93:AA93)="","",TRIM(U93:AA93)))} -> Left Sleeve Top Left Corner Top Left | AC93: {=_xlfn.TEXTJOIN("-",TRUE,IF(TRIM(U93:AA93)="","",TRIM(U93:AA93)))} -> Left-Sleeve-Top-Left-Corner-Top-Left | AD93: {=_xlfn.TEXTJOIN("",TRUE,LEFT(U93:AA93,1))} -> LSTLCTL | AE93: {=_xlfn.TEXTJOIN("/",TRUE,LEFT(U93:AA93,1))&"/"} -> L/S/T/L/C/T/L/ | AF93: {=_xlfn.TEXTJOIN("-",TRUE,LEFT(U93:AA93,1))&"-"} -> L-S-T-L-C-T-L-
A94: PT94 | B94: Tote Bag | C94: PT94 | D94: 200 | E94: 60 | F94: 260 | G94: Royal Mail Large Letter | H94: Estimated | T94: L13 | U94: Left | V94: Sleeve | W94: Top | X94: Right | Y94: Corner | Z94: Top | AA94: Right | AB94: {=_xlfn.TEXTJOIN(" ",TRUE,IF(TRIM(U94:AA94)="","",TRIM(U94:AA94)))} -> Left Sleeve Top Right Corner Top Right | AC94: {=_xlfn.TEXTJOIN("-",TRUE,IF(TRIM(U94:AA94)="","",TRIM(U94:AA94)))} -> Left-Sleeve-Top-Right-Corner-Top-Right | AD94: {=_xlfn.TEXTJOIN("",TRUE,LEFT(U94:AA94,1))} -> LSTRCTR | AE94: {=_xlfn.TEXTJOIN("/",TRUE,LEFT(U94:AA94,1))&"/"} -> L/S/T/R/C/T/R/ | AF94: {=_xlfn.TEXTJOIN("-",TRUE,LEFT(U94:AA94,1))&"-"} -> L-S-T-R-C-T-R-
A95: PT95 | B95: Organic Cotton Tote | C95: PT95 | T95: L14 | U95: Left | V95: Sleeve | W95: Top | X95: Left | Y95: Corner | AB95: {=_xlfn.TEXTJOIN(" ",TRUE,IF(TRIM(U95:AA95)="","",TRIM(U95:AA95)))} -> Left Sleeve Top Left Corner | AC95: {=_xlfn.TEXTJOIN("-",TRUE,IF(TRIM(U95:AA95)="","",TRIM(U95:AA95)))} -> Left-Sleeve-Top-Left-Corner | AD95: {=_xlfn.TEXTJOIN("",TRUE,LEFT(U95:AA95,1))} -> LSTLC | AE95: {=_xlfn.TEXTJOIN("/",TRUE,LEFT(U95:AA95,1))&"/"} -> L/S/T/L/C/ | AF95: {=_xlfn.TEXTJOIN("-",TRUE,LEFT(U95:AA95,1))&"-"} -> L-S-T-L-C-
A96: PT96 | B96: Drawstring Bag | C96: PT96 | T96: L15 | U96: Left | V96: Sleeve | W96: Top | X96: Right | Y96: Corner | AB96: {=_xlfn.TEXTJOIN(" ",TRUE,IF(TRIM(U96:AA96)="","",TRIM(U96:AA96)))} -> Left Sleeve Top Right Corner | AC96: {=_xlfn.TEXTJOIN("-",TRUE,IF(TRIM(U96:AA96)="","",TRIM(U96:AA96)))} -> Left-Sleeve-Top-Right-Corner | AD96: {=_xlfn.TEXTJOIN("",TRUE,LEFT(U96:AA96,1))} -> LSTRC | AE96: {=_xlfn.TEXTJOIN("/",TRUE,LEFT(U96:AA96,1))&"/"} -> L/S/T/R/C/ | AF96: {=_xlfn.TEXTJOIN("-",TRUE,LEFT(U96:AA96,1))&"-"} -> L-S-T-R-C-
A97: PT97 | B97: Backpacks | C97: PT97 | T97: L16 | U97: Left | V97: Sleeve | W97: Top | X97: Left | Y97: Bottom | Z97: Right | AA97: Corner | AB97: {=_xlfn.TEXTJOIN(" ",TRUE,IF(TRIM(U97:AA97)="","",TRIM(U97:AA97)))} -> Left Sleeve Top Left Bottom Right Corner | AC97: {=_xlfn.TEXTJOIN("-",TRUE,IF(TRIM(U97:AA97)="","",TRIM(U97:AA97)))} -> Left-Sleeve-Top-Left-Bottom-Right-Corner | AD97: {=_xlfn.TEXTJOIN("",TRUE,LEFT(U97:AA97,1))} -> LSTLBRC | AE97: {=_xlfn.TEXTJOIN("/",TRUE,LEFT(U97:AA97,1))&"/"} -> L/S/T/L/B/R/C/ | AF97: {=_xlfn.TEXTJOIN("-",TRUE,LEFT(U97:AA97,1))&"-"} -> L-S-T-L-B-R-C-
A98: PT98 | B98: Duffle Bag | C98: PT98 | T98: L17 | U98: Left | V98: Sleeve | W98: Top | X98: Right | Y98: Corner | Z98: Left | AA98: Corner | AB98: {=_xlfn.TEXTJOIN(" ",TRUE,IF(TRIM(U98:AA98)="","",TRIM(U98:AA98)))} -> Left Sleeve Top Right Corner Left Corner | AC98: {=_xlfn.TEXTJOIN("-",TRUE,IF(TRIM(U98:AA98)="","",TRIM(U98:AA98)))} -> Left-Sleeve-Top-Right-Corner-Left-Corner | AD98: {=_xlfn.TEXTJOIN("",TRUE,LEFT(U98:AA98,1))} -> LSTRCLC | AE98: {=_xlfn.TEXTJOIN("/",TRUE,LEFT(U98:AA98,1))&"/"} -> L/S/T/R/C/L/C/ | AF98: {=_xlfn.TEXTJOIN("-",TRUE,LEFT(U98:AA98,1))&"-"} -> L-S-T-R-C-L-C-
A99: PT99 | B99: Fanny Pack | C99: PT99 | T99: L18 | U99: Left | V99: Sleeve | W99: Bottom | X99: Left | Y99: Corner | Z99: Top | AA99: Left | AB99: {=_xlfn.TEXTJOIN(" ",TRUE,IF(TRIM(U99:AA99)="","",TRIM(U99:AA99)))} -> Left Sleeve Bottom Left Corner Top Left | AC99: {=_xlfn.TEXTJOIN("-",TRUE,IF(TRIM(U99:AA99)="","",TRIM(U99:AA99)))} -> Left-Sleeve-Bottom-Left-Corner-Top-Left | AD99: {=_xlfn.TEXTJOIN("",TRUE,LEFT(U99:AA99,1))} -> LSBLCTL | AE99: {=_xlfn.TEXTJOIN("/",TRUE,LEFT(U99:AA99,1))&"/"} -> L/S/B/L/C/T/L/ | AF99: {=_xlfn.TEXTJOIN("-",TRUE,LEFT(U99:AA99,1))&"-"} -> L-S-B-L-C-T-L-
A100: PT100 | B100: Lunch Bag | C100: PT100 | T100: L19 | U100: Left | V100: Sleeve | W100: Bottom | X100: Right | Y100: Corner | Z100: Top | AA100: Left | AB100: {=_xlfn.TEXTJOIN(" ",TRUE,IF(TRIM(U100:AA100)="","",TRIM(U100:AA100)))} -> Left Sleeve Bottom Right Corner Top Left | AC100: {=_xlfn.TEXTJOIN("-",TRUE,IF(TRIM(U100:AA100)="","",TRIM(U100:AA100)))} -> Left-Sleeve-Bottom-Right-Corner-Top-Left | AD100: {=_xlfn.TEXTJOIN("",TRUE,LEFT(U100:AA100,1))} -> LSBRCTL | AE100: {=_xlfn.TEXTJOIN("/",TRUE,LEFT(U100:AA100,1))&"/"} -> L/S/B/R/C/T/L/ | AF100: {=_xlfn.TEXTJOIN("-",TRUE,LEFT(U100:AA100,1))&"-"} -> L-S-B-R-C-T-L-
...

Sheet Guide1
A1: Supplier | B1: Brand | C1: Combined-Brand | D1: Department | E1: Sub-Department | F1: Brand-Code | G1: Product Name | H1: Daatadirect-Code | I1: china-code | J1: prodcuts Category | L1: prodcuts Category2 | M1: prodcuts Category3 | N1: prodcuts Category4 | O1: Amazon UK | P1: eBay UK | Q1: Etsy | R1: TikTok Shop UK | S1: Pinterest Shopping Categories | T1: Wix Stores | U1: Wix | V1: Category | W1: Google_Shopping | X1: Instagram | Y1: Pinterest | Z1: UNIVERSAL CATEGORY | AG1: Category | AO1: Tags
A3: BTC Activewear | B3: DaataaDirect | C3: Fruit Of The Loom/Gildan | D3: T-Shirts | E3: Unisex T-shirt | F3: 5000B | G3: TSHIRT | H3: DAT001 | I3: CH001 | J3: Apparel & Fashion | K3: Dropshipping | L3: Apparel | M3: T-Shirts | N3: Apparel & Accessories > Clothing > Shirts & Tops | O3: Books | P3: Antiques | Q3: Accessories | R3: Apparel & Accessories | S3: Home Decor | T3: Fashion | U3: Fashion | V3: Clothing & Accessories | W3: Apparel & Accessories | X3: Apparel & Accessories | Y3: Home Decor | Z3: Fashion & Apparel | AA3: Ready Made | AB3: Newborn | AC3: S1 | AD3: Newborn | AE3: INF-NB | AF3: 0-3 months | AO3: print on demand, personalised, custom, gift, apparel, t-shirts, #printondemand, #customgift, #customclothing
A4: Ralawise | B4: Giftvolt | C4: Daataa Direct | D4: T-Shirts | E4: Premium T-shirt | F4: 5000L | G4: TSHIRT | H4: DAT002 | I4: CH002 | J4: Beauty & Cosmetics | K4: Print-on-Demand | L4: Other | M4: Baby & Kids Apparel | N4: Apparel & Accessories > Clothing | O4: Business, Industry & Science | P4: Art | Q4: Art & Collectibles | R4: Beauty & Personal Care | S4: Fashion (Women / Men) | T4: Beauty & Wellness | U4: Beauty & Wellness | V4: Jewelry | W4: Media | X4: Beauty | Y4: Fashion | Z4: T-shirts | AA4: Your Photo/Image | AB4: 3 Months | AC4: S2 | AD4: 3 Months | AE4: INF-3M | AF4: 3-6 months | AO4: print on demand, personalised, custom, gift, apparel, t-shirts, #printondemand, #customgift, #customclothing
A5: Pencarrie | B5: Printvolt | C5: Gofasiondirect | D5: T-Shirts | E5: Heavy Cotton T-shirt | F5: 5100P | G5: BBWEAR | H5: DAT003 | I5: CH003 | J5: Electronics & Gadgets | K5: Print-on-Demand/Apparel & Fashion | L5: Drinkware | M5: Unclassified | N5: Apparel & Accessories | O5: Car & Motorbike | P5: Baby | Q5: Bags & Purses | R5: Home & Living | S5: Beauty | T5: Home & Decor | U5: Home & Decor | V5: Beauty & Personal Care | W5: Home & Garden | X5: Home | Y5: Beauty | Z5: Hoodies | AA5: Your Text | AB5: 6 Months | AC5: S3 | AD5: 6 Months | AE5: INF-6M | AF5: 6-9 months | AG5: Apparel & Fashion | AO5: print on demand, personalised, custom, gift, apparel, t-shirts, #printondemand, #customgift, #customclothing
A6: Uneek Clothing | B6: Foodvolt | C6: Printvolt | D6: T-Shirts | E6: Oversized T-shirt | F6: 64000 | G6: TSHIRT | H6: DAT004 | I6: CH004 | J6: Jewelry & Accessories | L6: Home & Living | M6: Hoodies & Sweatshirts | N6: Apparel & Accessories > Clothing > Pants | O6: Clothing | P6: Books, Comics & Magazines | Q6: Bath & Beauty | R6: Kitchenware | S6: DIY & Crafts | T6: Electronics | U6: Electronics | V6: Home & Garden | W6: Beauty | X6: Electronics | Y6: DIY & Crafts | Z6: Sweatshirts | AA6: Your Photo/Image & Your Text | AB6: 9 Months | AC6: S4 | AD6: 9 Months | AE6: INF-9M | AF6: 9-12 months | AG6: Beauty & Cosmetics | AO6: print on demand, personalised, custom, gift, apparel, t-shirts, #printondemand, #customgift, #customclothing
A7: Absolute Apparel | B7: B&C Collection | D7: T-Shirts | E7: Women’s Fitted T-shirt | F7: 64000B | G7: TSHIRT | H7: DAT005 | I7: CH005 | J7: Home & Kitchen Products | L7: Accessories | M7: Tanks & Vests | N7: Apparel & Accessories > Clothing > Activewear | O7: Computers & Accessories | P7: Business, Office & Industrial | Q7: Books, Films & Music | R7: Electronics | S7: Gifts | T7: Art | U7: Art | V7: Electronics | W7: Health | X7: Art | Y7: Gifts | Z7: Joggers | AA7: Your Photo/Image with Design Text | AB7: 12 Months | AC7: S5 | AD7: 12 Months | AE7: INF-12M | AF7: 12-18 months | AG7: Electronics & Gadgets | AO7: print on demand, personalised, custom, gift, apparel, t-shirts, #printondemand, #customgift, #customclothing
A8: MDP Supplies | B8: Babybugz | D8: T-Shirts | E8: Long Sleeve T-shirt | F8: 64000CVC | G8: TSHIRT | H8: DAT006 | I8: CH006 | J8: Digital Products (eBooks, Courses) | L8: Stationery | M8: Polos | N8: Apparel & Accessories > Clothing > Sleepwear & Loungewear | O8: DIY & Tools | P8: Cameras & Photography | Q8: Clothing | R8: Collectibles | S8: Art / Wall Art | T8: Jewellery | U8: Jewellery | V8: Art | W8: Toys & Games | X8: Jewelry | Y8: Art | Z8: Dresses | AA8: Your Text with Design Image | AB8: 18 Months | AC8: S6 | AD8: 18 Months | AE8: INF-18M | AF8: 18-24 months | AG8: Jewelry & Accessories | AO8: print on demand, personalised, custom, gift, apparel, t-shirts, #printondemand, #customgift, #customclothing
A9: Temu | B9: Bagbase | D9: T-Shirts | E9: V-neck T-shirt | F9: 64000L | G9: TSHIRT | H9: DAT007 | I9: CH007 | J9: Food & Beverages | L9: Digital Products | M9: Sports Jerseys | N9: Home & Garden > Kitchen & Dining > Drinkware > Mugs | O9: Electronics & Photo | P9: Cars, Motorcycles & Vehicles | Q9: Craft Supplies & Tools | R9: Toys & Hobbies | S9: Weddings | T9: Toys & Kids | U9: Toys & Kids | V9: Toys & Games | W9: Sporting Goods | X9: Sporting Goods | Y9: Weddings | Z9: Jackets | AA9: Your Text & Photo with Design | AB9: 2-3 Years | AC9: S7 | AD9: 2-3 Years | AE9: KID-2T | AF9: Toddler | AG9: Home & Kitchen Products | AO9: print on demand, personalised, custom, gift, apparel, t-shirts, #printondemand, #customgift, #customclothing
A10: Amazon | B10: Beechfield | D10: T-Shirts | E10: Ringer T-shirt | F10: 64001LCVC | G10: TSHIRT | H10: DAT008 | I10: CH008 | J10: Subscription Boxes | L10: Wall Art | M10: Leggings | N10: Home & Garden > Kitchen & Dining > Drinkware > Tumblers | O10: Garden & Outdoors | P10: Clothes, Shoes & Accessories | Q10: Electronics & Accessories | R10: Pet Supplies | S10: Party Ideas | T10: Pets | U10: Pets | V10: Baby & Kids | W10: Electronics | X10: Toys | Y10: Party Ideas | Z10: Co-ords | AA10: standard | AB10: 3-4 Years | AC10: S8 | AD10: 3-4 Years | AE10: KID-3T | AF10: Toddler | AG10: Digital Products (eBooks, Courses) | AO10: print on demand, personalised, custom, gift, apparel, t-shirts, #printondemand, #customgift, #customclothing
A11: eBay | B11: Bella+Canvas | D11: T-Shirts | E11: Pocket T-shirt | F11: 64200 | G11: TSHIRT | H11: DAT009 | I11: CH009 | L11: Photo Gifts | M11: Pants & Joggers | N11: Home & Garden > Kitchen & Dining > Drinkware > Water Bottles | O11: Grocery | P11: Collectables | Q11: Home & Living | R11: Food & Beverage | S11: Kids & Baby | T11: Digital Products | U11: Digital Products | V11: Sports | W11: Office Supplies | X11: Pet Supplies | Y11: Kids & Baby | Z11: Socks & Underwear | AA11: Photo Only | AB11: 4-5 Years | AC11: S9 | AD11: 4-5 Years | AE11: KID-4T | AF11: Toddler | AG11: Food & Beverages | AO11: print on demand, personalised, custom, gift, apparel, t-shirts, #printondemand, #customgift, #customclothing
A12: Alibaba | B12: Clique (NEW EXCLUSIVE) | D12: T-Shirts | E12: Kids T-shirt | F12: 64200L | G12: TSHIRT | H12: DAT010 | I12: CH010 | L12: Packaging & Branding | M12: Shorts | N12: Home & Garden > Kitchen & Dining > Drinkware > Drinking Glasses | O12: Health & Personal Care | P12: Computers, Tablets & Network Hardware | Q12: Jewellery | R12: Health | S12: Food & Recipes | T12: Gifts | U12: Gifts | V12: Food & Drink | W12: Pet Supplies | X12: Bags | Y12: Food & Recipes | Z12: Shoes | AA12: Name Only | AB12: 5-6 Years | AC12: S10 | AD12: 5-6 Years | AE12: KID-5T | AF12: Toddler | AG12: Subscription Boxes | AO12: print on demand, personalised, custom, gift, apparel, t-shirts, #printondemand, #customgift, #customclothing
A13: AliExpress | B13: Craft Sportswear (EXCLUSIVE) | D13: Baby & Kids Apparel | E13: Baby Bodysuit | F13: 64400 | G13: TSHIRT | H13: DAT011 | I13: CH011 | L13: Seasonal Gifts | M13: Sleepwear | N13: Home & Garden > Linens & Bedding > Decorative Pillows | O13: Home & Kitchen | P13: Crafts | Q13: Paper & Party Supplies | S13: Holidays & Events | T13: Food & Drink | U13: Food & Drink | V13: Gifts | W13: Luggage & Bags | X13: Shoes | Y13: Holidays | Z13: Bags | AA13: text Only | AB13: 6-7 Years | AC13: S11 | AD13: 6-7 Years | AE13: KID-6 | AF13: Kids | AG13: Dropshipping | AO13: print on demand, personalised, custom, gift, apparel, baby & kids apparel, #printondemand, #customgift, #customclothing
A14: Etsy | B14: Craghoppers Expert | D14: Unclassified | E14: Baby Bib | F14: 64800 | G14: PSHIRT | H14: DAT012 | I14: CH012 | L14: Pet Products | M14: Mugs | N14: Home & Garden > Linens & Bedding > Blankets | O14: Jewellery & Watches | P14: Dolls & Bears | Q14: Pet Supplies | S14: Pets | T14: DIY & Crafts | U14: DIY & Crafts | V14: Pet Supplies | W14: Baby & Toddler | X14: Furniture | Y14: Pets | Z14: B. Jewelry & Accessories | AA14: Photo + Text | AB14: 7-8 Years | AC14: S12 | AD14: 7-8 Years | AE14: KID-7 | AF14: Kids | AG14: Print-on-Demand | AO14: print on demand, personalised, custom, gift, other, unclassified, #printondemand, #customgift
A15: 1688 | B15: Delta Plus | D15: Hoodies & Sweatshirts | E15: Unisex Hoodie | F15: 64800L | G15: PSHIRT | H15: DAT013 | I15: CH013 | L15: Jewellery | M15: Tumblers | N15: Home & Garden > Linens & Bedding > Towels | O15: Pet Supplies | P15: Garden & Patio | Q15: Shoes | S15: Technology | T15: Socks & Underwear | W15: Vehicles & Parts | X15: Collectibles | Y15: Technology | Z15: Necklaces | AA15: Template with custom Date | AB15: 8-9 Years | AC15: S13 | AD15: 8-9 Years | AE15: KID-8 | AF15: Kids | AO15: print on demand, personalised, custom, gift, apparel, hoodies & sweatshirts, #printondemand, #customgift, #customclothing
A16: B&Q | B16: Dennys | D16: Hoodies & Sweatshirts | E16: Pullover Hoodie | F16: 64V00 | G16: TSHIRT | H16: DAT014 | I16: CH014 | M16: Bottles & Flasks | N16: Home & Garden > Kitchen & Dining > Kitchen Linens | O16: Sports & Outdoors | P16: Health & Beauty | Q16: Toys & Games | S16: Garden & Outdoor | T16: Shoes | W16: Arts & Entertainment | X16: Gifts | Y16: Garden & Outdoor | Z16: Bracelets | AA16: Template with custom Name | AB16: 9-10 Years | AC16: S14 | AD16: 9-10 Years | AE16: KID-9 | AF16: Kids | AO16: print on demand, personalised, custom, gift, apparel, hoodies & sweatshirts, #printondemand, #customgift, #customclothing
A17: Wickes | B17: Derby of Sweden (EXCLUSIVE) | D17: Hoodies & Sweatshirts | E17: Zip Hoodie | F17: 64V00L | G17: TSHIRT | H17: DAT015 | I17: CH015 | M17: Glassware & Barware | N17: Home & Garden > Rugs | O17: Toys & Games | P17: Home, Furniture & DIY | Q17: Weddings | S17: Travel | T17: Bags | W17: Hardware | Y17: Travel | Z17: Rings | AA17: Template with custom Text | AB17: 10-12 Years | AC17: S15 | AD17: 10-12 Years | AE17: KID-10 | AF17: Pre-Teen | AO17: print on demand, personalised, custom, gift, apparel, hoodies & sweatshirts, #printondemand, #customgift, #customclothing
A18: Screwfix | B18: ECOTote (EXCLUSIVE) | D18: Hoodies & Sweatshirts | E18: Crewneck Sweatshirt | F18: 65000 | G18: TSHIRT | H18: DAT016 | I18: CH016 | M18: Cushions & Pillows | N18: Luggage & Bags | O18: Video Games | P18: Jewellery & Watches | S18: Photography | W18: Furniture | Y18: Photography | Z18: Earrings | AA18: Template with custom photo | AB18: Extra Small | AC18: S16 | AD18: Extra Small | AE18: WM-XS | AF18: Size 6 (UK) / 2 (US) | AO18: print on demand, personalised, custom, gift, apparel, hoodies & sweatshirts, #printondemand, #customgift, #customclothing
A19: Toolstation | B19: Flexfit | D19: Hoodies & Sweatshirts | E19: Oversized Hoodie | F19: 65000B | G19: TSHIRT | H19: DAT017 | I19: CH017 | M19: Blankets & Bedding | N19: Electronics > Electronics Accessories > Bags, Cases & Sleeves | P19: Mobile Phones & Communication | Z19: Watches | AB19: Small | AC19: S17 | AD19: Small | AE19: WM-S | AF19: Size 8 (UK) / 4 (US) | AO19: print on demand, personalised, custom, gift, apparel, hoodies & sweatshirts, #printondemand, #customgift, #customclothing
A20: Amari Plastics | B20: Fruit of the Loom | D20: Hoodies & Sweatshirts | E20: Kids Hoodie | F20: 65000L | G20: TSHIRT | H20: DAT018 | I20: CH018 | M20: Towels | N20: Apparel & Accessories > Jewelry > Charms & Pendants | P20: Music | Z20: Hair Accessories | AB20: Medium | AC20: S18 | AD20: Medium | AE20: WM-M | AF20: Size 10 (UK) / 6 (US) | AO20: print on demand, personalised, custom, gift, apparel, hoodies & sweatshirts, #printondemand, #customgift, #customclothing
A21: China Suppliers | B21: Gildan | D21: Tanks & Vests | E21: Unisex Tank Top | F21: 8000 | G21: TSHIRT | H21: DAT019 | I21: CH019 | M21: Kitchen Textiles | N21: Apparel & Accessories > Handbags, Wallets & Cases | P21: Musical Instruments & DJ Equipment | Z21: Scarves & Gloves | AB21: Large | AC21: S19 | AD21: Large | AE21: WM-L | AF21: Size 12 (UK) / 8 (US) | AO21: print on demand, personalised, custom, gift, apparel, tanks & vests, #printondemand, #customgift, #customclothing
A22: Tilgear | B22: Gildan Hammer | D22: Tanks & Vests | E22: Women’s Racerback Tank | F22: 85800 | G22: PSHIRT | H22: DAT020 | I22: CH020 | M22: Rugs & Mats | N22: Office Supplies > General Office Supplies > Notebooks | P22: Pet Supplies | Z22: C. Beauty & Personal Care | AB22: X-Large | AC22: S20 | AD22: X-Large | AE22: WM-XL | AF22: Size 14 (UK) / 10 (US) | AO22: print on demand, personalised, custom, gift, apparel, tanks & vests, #printondemand, #customgift, #customclothing
A23: Indian | B23: Helly Hansen | D23: Polos | E23: Polo Shirt | F23: 85800L | G23: PSHIRT | H23: DAT021 | I23: CH021 | M23: Tote & Shopping Bags | N23: Office Supplies > General Office Supplies > Labels & Stickers | P23: Pottery, Porcelain & Glass | Z23: Skincare | AB23: 2X-Large | AC23: S21 | AD23: 2X-Large | AE23: WM-2XL | AF23: Size 16 (UK) / 12 (US) | AO23: print on demand, personalised, custom, gift, apparel, polos, #printondemand, #customgift, #customclothing
A24: Pakistan | B24: James Harvest (EXCLUSIVE) | D24: Sports Jerseys | E24: Sports Jersey | F24: 8800 | G24: PSHIRT | H24: DAT022 | I24: CH022 | M24: General Accessories | N24: Office Supplies > General Office Supplies > Calendars | P24: Sound & Vision | Z24: Bath & Body | AB24: 3X-Large | AC24: S22 | AD24: 3X-Large | AE24: WM-3XL | AF24: Size 18 (UK) / 14 (US) | AO24: print on demand, personalised, custom, gift, apparel, sports jerseys, #printondemand, #customgift, #customclothing
A25: Ikea | B25: James Harvest Outdoor (EXCLUSIVE) | D25: Leggings | E25: Leggings | F25: 8800B | G25: PSHIRT | H25: DAT023 | I25: CH023 | M25: Backpacks | N25: Office Supplies | P25: Sporting Goods | Z25: Haircare | AB25: Extra Small | AC25: S23 | AD25: Extra Small | AE25: MN-XS | AF25: 30-32 | AO25: print on demand, personalised, custom, gift, apparel, leggings, #printondemand, #customgift, #customclothing
A26: China + Amari Plastics | B26: Jerzees | D26: Pants & Joggers | E26: Joggers | F26: 980 | G26: TSHIRT | H26: DAT024 | I26: CH024 | M26: Travel & Gym Bags | N26: Software > Digital Goods & Currency | P26: Stamps | Z26: Perfume | AB26: Small | AC26: S24 | AD26: Small | AE26: MN-S | AF26: 34-36 | AO26: print on demand, personalised, custom, gift, apparel, pants & joggers, #printondemand, #customgift, #customclothing
B27: Jobman Workwear (EXCLUSIVE) | D27: Pants & Joggers | E27: Sweatpants | F27: SF000 | G27: SSHIRT | H27: DAT025 | I27: CH025 | M27: Keychains | N27: Home & Garden > Decor > Artwork > Posters, Prints, & Visual Artwork | P27: Toys & Games | Z27: Makeup | AB27: Medium | AC27: S25 | AD27: Medium | AE27: MN-M | AF27: 38-40 | AO27: print on demand, personalised, custom, gift, apparel, pants & joggers, #printondemand, #customgift, #customclothing
B28: Kustom Kit | D28: Shorts | E28: Shorts | F28: SF008 | G28: SSHIRT | H28: DAT026 | I28: CH026 | M28: Luggage Accessories | N28: Home & Garden > Decor | P28: Video Games & Consoles | Z28: D. Home & Living | AB28: Large | AC28: S26 | AD28: Large | AE28: MN-L | AF28: 42-44 | AO28: print on demand, personalised, custom, gift, apparel, shorts, #printondemand, #customgift, #customclothing
B29: Madeira | D29: Sleepwear | E29: Pyjama Set | F29: SF100 | G29: TROUSR | H29: DAT027 | I29: CH027 | M29: Wallets & Card Holders | N29: Home & Garden > Decor > Picture Frames | Z29: Wall Art | AB29: X-Large | AC29: S27 | AD29: X-Large | AE29: MN-XL | AF29: 46-48 | AO29: print on demand, personalised, custom, gift, apparel, sleepwear, #printondemand, #customgift, #customclothing
B30: Magic Touch | D30: Mugs | E30: 11oz Ceramic Mug | F30: SF500 | G30: SSHIRT | H30: DAT028 | I30: CH028 | M30: Notebooks & Journals | N30: Home & Garden > Kitchen & Dining > Drinkware | Z30: Posters | AB30: 2X-Large | AC30: S28 | AD30: 2X-Large | AE30: MN-2XL | AF30: 50-52 | AO30: print on demand, personalised, custom, gift, drinkware, mugs, #printondemand, #customgift, #custommug
B31: Mantis | D31: Mugs | E31: 15oz Ceramic Mug | F31: SF500B | G31: SSHIRT | H31: DAT029 | I31: CH029 | M31: Stickers & Labels | N31: Home & Garden > Window Treatments > Curtains & Drapes | Z31: Cushions | AB31: 3X-Large | AC31: S29 | AD31: 3X-Large | AE31: MN-3XL | AF31: 54-56 | AO31: print on demand, personalised, custom, gift, drinkware, mugs, #printondemand, #customgift, #custommug
B32: Nike | D32: Mugs | E32: Two-Tone Mug | F32: SF600 | G32: SSHIRT | H32: DAT030 | I32: CH030 | M32: Calendars | N32: Business & Industrial > Advertising & Marketing > Business Cards | Z32: Bedding | AB32: 4XL | AC32: S30 | AD32: 4XL | AE32: MN-4XL | AF32: 58-60 | AO32: print on demand, personalised, custom, gift, drinkware, mugs, #printondemand, #customgift, #custommug
B33: Printer Essentials (EXCLUSIVE) | D33: Mugs | E33: Magic Heat-Changing Mug | F33: H000 | G33: TSHIRT | H33: DAT031 | I33: CH031 | M33: Stationery | N33: Business & Industrial > Packing & Shipping Supplies | Z33: Kitchen Items | AB33: 5XL | AC33: S31 | AD33: 5XL | AE33: MN-5XL | AF33: 62-64 | AO33: print on demand, personalised, custom, gift, drinkware, mugs, #printondemand, #customgift, #custommug
B34: Printer Prime (EXCLUSIVE) | D34: Mugs | E34: Enamel Camp Mug | F34: H400 | G34: TSHIRT | H34: DAT032 | I34: CH032 | M34: Templates / Printables | N34: Home & Garden > Decor > Artwork | Z34: Candles | AB34: 6XL | AC34: S32 | AD34: 6XL | AE34: MN-6XL | AF34: 66-68 | AO34: print on demand, personalised, custom, gift, drinkware, mugs, #printondemand, #customgift, #custommug
B35: Printer Red (EXCLUSIVE) | D35: Mugs | E35: Travel Mug | F35: HF000 | G35: SSHIRT | H35: DAT033 | I35: CH033 | M35: Posters | N35: Home & Garden > Decor > Seasonal & Holiday Decorations | Z35: Decor | AB35: 7XL | AC35: S33 | AD35: 7XL | AE35: MN-7XL | AF35: 70-72 | AO35: print on demand, personalised, custom, gift, drinkware, mugs, #printondemand, #customgift, #custommug
B36: Puma Safety | D36: T-Shirts | E36: Stainless Steel Tumbler | F36: SS800 | G36: OUTERW | H36: DAT034 | I36: CH034 | M36: Art Prints | N36: Animals & Pet Supplies > Pet Supplies | Z36: Furniture | AB36: 8XL | AC36: S34 | AD36: 8XL | AE36: MN8XL | AF36: 74-76 | AO36: print on demand, personalised, custom, gift, apparel, t-shirts, #printondemand, #customgift, #customclothing
B37: Pure Earth by Stormtech | D37: Tumblers | E37: Insulated Tumbler | F37: SS800L | G37: OUTERW | H37: DAT035 | I37: CH035 | M37: Photo Personalised Gifts | N37: Apparel & Accessories > Clothing > Dresses | Z37: E. Art & Collectibles | AB37: A2 | AC37: S35 | AD37: A2 | AE37: 420.5*594mm | AO37: print on demand, personalised, custom, gift, drinkware, tumblers, #printondemand, #customgift, #custommug
B38: Quadra | D38: Bottles & Flasks | E38: Water Bottle Metal | F38: 70180 | G38: WKWEAR | H38: DAT036 | I38: CH036 | M38: Drinkware | N38: Apparel & Accessories > Clothing > Skirts | Z38: Prints | AB38: A2-1 | AC38: S36 | AD38: A2-1 | AE38: 140.166*594mm | AO38: print on demand, personalised, custom, gift, drinkware, bottles & flasks, #printondemand, #customgift, #custommug
B39: Regatta Professional | D39: Mugs | E39: Latte Mug | F39: 70480 | G39: WKWEAR | H39: DAT037 | I39: CH037 | M39: Table Linens | N39: Apparel & Accessories > Jewelry | Z39: Digital Art | AB39: A2-2 | AC39: S37 | AD39: A2-2 | AE39: 420.5*420.5mm | AO39: print on demand, personalised, custom, gift, drinkware, mugs, #printondemand, #customgift, #custommug
B40: Regatta High Visibility | D40: Glassware & Barware | E40: Beer Glass | F40: 71043 | G40: WKWEAR | H40: DAT038 | I40: CH038 | M40: Curtains & Drapes | N40: Home & Garden > Kitchen & Dining > Drinkware > Drinking Glasses | Z40: Paintings | AB40: A2-3 | AC40: S38 | AD40: A2-3 | AE40: 420.5*210.25mm | AO40: print on demand, personalised, custom, gift, drinkware, glassware & barware, #printondemand, #customgift, #custommug
B41: Regatta Honestly Made | D41: Glassware & Barware | E41: Wine Glass | F41: 71080 | G41: OUTERW | H41: DAT039 | I41: CH039 | M41: Home Textiles | N41: Home & Garden > Kitchen & Dining > Drinkware > Drinking Glasses | Z41: Photography | AB41: A2-4 | AC41: S39 | AD41: A2-4 | AE41: 420.5*148.5mm | AO41: print on demand, personalised, custom, gift, drinkware, glassware & barware, #printondemand, #customgift, #custommug
B42: Regatta Junior | D42: Glassware & Barware | E42: Shot Glass | F42: 71261 | G42: WKWEAR | H42: DAT040 | I42: CH040 | M42: Cosmetic Bags | N42: Home & Garden > Kitchen & Dining > Drinkware > Drinking Glasses | Z42: Handmade Crafts | AB42: A2-5 | AC42: S40 | AD42: A2-5 | AE42: 140.166*210.25mm | AO42: print on demand, personalised, custom, gift, drinkware, glassware & barware, #printondemand, #customgift, #custommug
B43: Regatta Safety Footwear | D43: Mugs | E43: Glass Mug Frosted | F43: 71262 | G43: WKWEAR | H43: DAT041 | I43: CH041 | M43: Pencil & Pen Cases | N43: Home & Garden > Kitchen & Dining > Drinkware > Mugs | Z43: F. Gifts (Your main category for GiftsVolt) | AB43: A2-6 | AC43: S41 | AD43: A2-6 | AE43: 210.25*210.25mm | AO43: print on demand, personalised, custom, gift, drinkware, mugs, #printondemand, #customgift, #custommug
B44: Result | D44: Cushions & Pillows | E44: Throw Pillow | F44: 71342 | G44: OUTERW | H44: DAT042 | I44: CH042 | M44: Business Cards | N44: Home & Garden > Linens & Bedding > Decorative Pillows | Z44: Personalised Mugs | AB44: A2-7 | AC44: S42 | AD44: A2-7 | AE44: 420.5*534mm | AO44: print on demand, personalised, custom, gift, home & living, cushions & pillows, #printondemand, #customgift, #homedecor
B45: Result Core | D45: Cushions & Pillows | E45: Cushion Cover | F45: 71351 | G45: WKWEAR | H45: DAT043 | I45: CH043 | M45: Labels & Stickers | N45: Home & Garden > Linens & Bedding > Decorative Pillows | Z45: Photo Frames | AB45: A2-8 | AC45: S43 | AD45: A2-8 | AE45: 140.166*554mm | AO45: print on demand, personalised, custom, gift, home & living, cushions & pillows, #printondemand, #customgift, #homedecor
B46: Result Headwear | D46: Cushions & Pillows | E46: Photo Cushion | F46: 72026 | G46: OUTERW | H46: DAT044 | I46: CH044 | M46: Bookmarks | N46: Home & Garden > Linens & Bedding > Decorative Pillows | Z46: Acrylic Signs | AB46: A2-9 | AC46: S44 | AD46: A2-9 | AE46: 140.166*534mm | AO46: print on demand, personalised, custom, gift, home & living, cushions & pillows, #printondemand, #customgift, #homedecor
B47: Result Recycled | D47: Cushions & Pillows | E47: Sequin Pillow | F47: 72096 | G47: OUTERW | H47: DAT045 | I47: CH045 | M47: Map & City Prints | N47: Home & Garden > Linens & Bedding > Decorative Pillows | Z47: Custom Name Gifts | AB47: A2-10 | AC47: S45 | AD47: A2-10 | AE47: 420.5*554mm | AO47: print on demand, personalised, custom, gift, home & living, cushions & pillows, #printondemand, #customgift, #homedecor
B48: Result Safe-Guard | D48: Blankets & Bedding | E48: Fleece Blanket | F48: 72251 | G48: OUTERW | H48: DAT046 | I48: CH046 | M48: Occasion Gifts | N48: Home & Garden > Linens & Bedding > Blankets | Z48: Wedding Gifts | AB48: A2-11 | AC48: S46 | AD48: A2-11 | AE48: *mm | AO48: print on demand, personalised, custom, gift, home & living, blankets & bedding, #printondemand, #customgift, #homedecor
... B65: Yoko | D65: General Accessories | E65: Phone Case Samsung | F65: 77408 | G65: WKWEAR | H65: DAT063 | I65: CH063 | M65: Printable Quote Set | N65: Electronics > Electronics Accessories > Bags, Cases & Sleeves | Z65: Pet Clothing | AB65: A3-13 | AC65: S63 | AD65: A3-13 | AE65: *mm | AO65: print on demand, personalised, custom, gift, accessories, general accessories, #printondemand, #customgift
B66: 2786 | D66: General Accessories | E66: Clear Phone Case | F66: 77521 | G66: TROUSR | H66: DAT064 | I66: CH064 | M66: Led base | N66: Electronics > Electronics Accessories > Bags, Cases & Sleeves | Z66: Pet Accessories | AB66: A3-14 | AC66: S64 | AD66: A3-14 | AE66: *mm | AO66: print on demand, personalised, custom, gift, accessories, general accessories, #printondemand, #customgift
B67: Add It On | D67: General Accessories | E67: Tough Phone Case | F67: 77525 | G67: TROUSR | H67: DAT065 | I67: CH065 | M67: Acrylic sheet | N67: Electronics > Electronics Accessories > Bags, Cases & Sleeves | Z67: Pet Toys | AB67: A4 | AC67: S65 | AD67: A4 | AE67: 210*297mm | AO67: print on demand, personalised, custom, gift, accessories, general accessories, #printondemand, #customgift
B68: Adidas | D68: Keychains | E68: Keychain | F68: 77543 | G68: TROUSR | H68: DAT066 | I68: CH066 | M68: MDF | N68: Apparel & Accessories > Jewelry > Charms & Pendants | Z68: Pet Bowls | AB68: A4-1 | AC68: S66 | AD68: A4-1 | AE68: 70*297mm | AO68: print on demand, personalised, custom, gift, accessories, keychains, #printondemand, #customgift
B69: Anthem | D69: Unclassified | E69: Passport Holder | F69: 77578 | G69: TROUSR | H69: DAT067 | I69: CH067 | M69: Flexi-Ply | N69: Apparel & Accessories | Z69: J. Paper & Party | AB69: A4-2 | AC69: S67 | AD69: A4-2 | AE69: 210*210mm | AO69: print on demand, personalised, custom, gift, other, unclassified, #printondemand, #customgift
B70: Asquith & Fox | D70: Luggage Accessories | E70: Luggage Tag | F70: 78422 | G70: WKWEAR | H70: DAT068 | I70: CH068 | M70: Poplar Laser Ply | N70: Apparel & Accessories | Z70: Invitations | AB70: A4-3 | AC70: S68 | AD70: A4-3 | AE70: 210*105mm | AO70: print on demand, personalised, custom, gift, accessories, luggage accessories, #printondemand, #customgift
B71: AWDis | D71: Wallets & Card Holders | E71: Wallet | F71: 79161 | G71: TSHIRT | H71: DAT069 | I71: CH069 | M71: Aluminium | N71: Apparel & Accessories > Handbags, Wallets & Cases | Z71: Stickers | AB71: A4-4 | AC71: S69 | AD71: A4-4 | AE71: 210*74.25mm | AO71: print on demand, personalised, custom, gift, accessories, wallets & card holders, #printondemand, #customgift
B72: AWDis Academy | D72: Notebooks & Journals | E72: Spiral Notebook | F72: 79167 | G72: PSHIRT | H72: DAT070 | I72: CH070 | M72: Steel | N72: Office Supplies > General Office Supplies > Notebooks | Z72: Banners | AB72: A4-5 | AC72: S70 | AD72: A4-5 | AE72: 70*105mm | AO72: print on demand, personalised, custom, gift, stationery, notebooks & journals, #printondemand, #customgift
B73: AWDis Ecologie | D73: Notebooks & Journals | E73: Hardcover Notebook | F73: 79208 | G73: SSHIRT | H73: DAT071 | I73: CH071 | M73: Brass | N73: Office Supplies > General Office Supplies > Notebooks | Z73: Party Decorations | AB73: A4-6 | AC73: S71 | AD73: A4-6 | AE73: 105*105mm | AO73: print on demand, personalised, custom, gift, stationery, notebooks & journals, #printondemand, #customgift
B74: AWDis Just Cool | D74: Notebooks & Journals | E74: Journal | F74: 79210 | G74: SSHIRT | H74: DAT072 | I74: CH072 | M74: Copper | N74: Office Supplies > General Office Supplies > Notebooks | Z74: K. Weddings & Events | AB74: A4-7 | AC74: S72 | AD74: A4-7 | AE74: 210*237mm | AO74: print on demand, personalised, custom, gift, stationery, notebooks & journals, #printondemand, #customgift
B75: AWDis Just Hoods | D75: Notebooks & Journals | E75: Diary | F75: 79241 | G75: PSHIRT | H75: DAT073 | I75: CH073 | M75: Ground Flat Stock | N75: Office Supplies > General Office Supplies > Notebooks | Z75: Bridal Party Gifts | AB75: A4-8 | AC75: S73 | AD75: A4-8 | AE75: 70*257mm | AO75: print on demand, personalised, custom, gift, stationery, notebooks & journals, #printondemand, #customgift
B76: AWDis Just Polos | D76: Unclassified | E76: Greeting Card | F76: 79241N | G76: PSHIRT | H76: DAT074 | I76: CH074 | M76: Pewter | N76: Apparel & Accessories | Z76: Engagement Gifts | AB76: A4-9 | AC76: S74 | AD76: A4-9 | AE76: 70*237mm | AO76: print on demand, personalised, custom, gift, other, unclassified, #printondemand, #customgift
B77: AWDis So Denim | D77: Stickers & Labels | E77: Sticker Sheet | F77: 79248 | G77: PSHIRT | H77: DAT075 | I77: CH075 | M77: Silver Steel | N77: Office Supplies > General Office Supplies > Labels & Stickers | Z77: Wedding Decor | AB77: A4-10 | AC77: S75 | AD77: A4-10 | AE77: 210*257mm | AO77: print on demand, personalised, custom, gift, stationery, stickers & labels, #printondemand, #customgift
B78: AWDis Just Ts | D78: Stickers & Labels | E78: Die Cut Stickers | F78: 79327 | G78: SSHIRT | H78: DAT076 | I78: CH076 | M78: Ball Bearings | N78: Office Supplies > General Office Supplies > Labels & Stickers | Z78: Hen Party Items | AB78: A4-11 | AC78: S76 | AD78: A4-11 | AE78: *mm | AO78: print on demand, personalised, custom, gift, stationery, stickers & labels, #printondemand, #customgift
... B84: Build Your Brand | D84: Posters | E84: Framed Poster | F84: 79572 | G84: WKWEAR | H84: DAT082 | I84: CH082 | M84: Clear Rigid PVC Roll | N84: Home & Garden > Decor > Artwork > Posters, Prints, & Visual Artwork | Z84: Shakes & Juices | AB84: A5-2 | AC84: S82 | AD84: A5-2 | AE84: 148.5*148.5mm | AO84: print on demand, personalised, custom, gift, wall art, posters, #printondemand, #customgift
B85: Build Your Brand Basic | D85: Posters | E85: Poster Print | F85: 79646 | G85: FTWEAR | H85: DAT083 | I85: CH083 | M85: Plastazote Sheets | N85: Home & Garden > Decor > Artwork > Posters, Prints, & Visual Artwork | AB85: A5-3 | AC85: S83 | AD85: A5-3 | AE85: 148.5*74.25mm | AO85: print on demand, personalised, custom, gift, wall art, posters, #printondemand, #customgift
B86: Build Your Brandit | D86: Art Prints | E86: Metal Print | F86: 79811 | G86: CAPHA | H86: DAT084 | I86: CH084 | M86: PETg Clear Sheet | N86: Home & Garden > Decor > Artwork > Posters, Prints, & Visual Artwork | AB86: A5-4 | AC86: S84 | AD86: A5-4 | AE86: 148.5*52.5mm | AO86: print on demand, personalised, custom, gift, wall art, art prints, #printondemand, #customgift
B87: Callaway | D87: Unclassified | E87: Acrylic Wall Panel | F87: HAR2111031 | G87: OUTERW | H87: DAT085 | I87: CH085 | M87: Modelling Foam | N87: Apparel & Accessories | AB87: A5-5 | AC87: S85 | AD87: A5-5 | AE87: 49.5*74.25mm | AO87: print on demand, personalised, custom, gift, other, unclassified, #printondemand, #customgift
B88: Colortone | D88: Photo Personalised Gifts | E88: Photo Tiles | F88: HAR2111032 | G88: OUTERW | H88: DAT086 | I88: CH086 | M88: High Impact Polystyrene | N88: Home & Garden > Decor | AB88: A5-6 | AC88: S86 | AD88: A5-6 | AE88: 74.25*74.25mm | AO88: print on demand, personalised, custom, gift, photo gifts, photo personalised gifts, #printondemand, #customgift, #photogift
B89: Comfort Colors | D89: Photo Personalised Gifts | E89: Acrylic Photo Block | F89: HAR2111033 | G89: SSHIRT | H89: DAT087 | I89: CH087 | M89: Engraving Laminate | N89: Home & Garden > Decor > Picture Frames | AB89: A5-7 | AC89: S87 | AD89: A5-7 | AE89: 148.5*150mm | AO89: print on demand, personalised, custom, gift, photo gifts, photo personalised gifts, #printondemand, #customgift, #photogift
B90: Craghoppers Expert | D90: Photo Personalised Gifts | E90: Spotify Music Plaque | F90: HAR2111037 | G90: OUTERW | H90: DAT088 | I90: CH088 | M90: Correx | N90: Home & Garden > Decor > Picture Frames | AB90: A5-8 | AC90: S88 | AD90: A5-8 | AE90: 49.5*170mm | AO90: print on demand, personalised, custom, gift, photo gifts, photo personalised gifts, #printondemand, #customgift, #photogift
B91: Everyday Essentials | D91: Photo Personalised Gifts | E91: Photo Crystal | F91: HAR2111038 | G91: OUTERW | H91: DAT089 | I91: CH089 | M91: Brushed Aluminium | N91: Home & Garden > Decor | AB91: A5-9 | AC91: S89 | AD91: A5-9 | AE91: 49.5*150mm | AO91: print on demand, personalised, custom, gift, photo gifts, photo personalised gifts, #printondemand, #customgift, #photogift
B92: Finden & Hales | D92: Photo Personalised Gifts | E92: Photo Clock | F92: HAR2111039 | G92: OUTERW | H92: DAT090 | I92: CH090 | M92: Acrylic Tube | N92: Home & Garden > Decor | AB92: A5-10 | AC92: S90 | AD92: A5-10 | AE92: 148.5*170mm | AO92: print on demand, personalised, custom, gift, photo gifts, photo personalised gifts, #printondemand, #customgift, #photogift
B93: Flexfit by Yupoong | D93: Photo Personalised Gifts | E93: Photo Coaster | F93: HAR2111040 | G93: OUTERW | H93: DAT091 | I93: CH091 | M93: Acrylic Rod | N93: Home & Garden > Decor | AB93: A5-11 | AC93: S91 | AD93: A5-11 | AE93: *mm | AO93: print on demand, personalised, custom, gift, photo gifts, photo personalised gifts, #printondemand, #customgift, #photogift
B94: Front Row | D94: Calendars | E94: Photo Calendar | F94: HAR2111041 | G94: OUTERW | H94: DAT092 | I94: CH092 | M94: Acrylic Sheets | N94: Office Supplies > General Office Supplies > Calendars | AB94: A5-12 | AC94: S92 | AD94: A5-12 | AE94: *mm | AO94: print on demand, personalised, custom, gift, stationery, calendars, #printondemand, #customgift
B95: Fruit of the Loom | D95: Keychains | E95: Photo Keyring | F95: HAR2111042 | G95: OUTERW | H95: DAT093 | I95: CH093 | M95: Acrylic Components | N95: Apparel & Accessories > Jewelry > Charms & Pendants | AB95: A5-13 | AC95: S93 | AD95: A5-13 | AE95: *mm | AO95: print on demand, personalised, custom, gift, accessories, keychains, #printondemand, #customgift
B96: Gamegear | D96: T-Shirts | E96: All-Over Print T-shirt | F96: HAR2111043 | G96: OUTERW | H96: DAT094 | I96: CH094 | M96: Vinyl | N96: Apparel & Accessories > Clothing > Shirts & Tops | AB96: A5-14 | AC96: S94 | AD96: A5-14 | AE96: *mm | AO96: print on demand, personalised, custom, gift, apparel, t-shirts, #printondemand, #customgift, #customclothing
... B126: Result Winter Essentials | D126: Glassware & Barware | E126: Beer Stein | F126: HAR2121026 | G126: OUTERW | H126: DAT124 | I126: CH124 | M126: Other Speciality Vinyl | N126: Home & Garden > Kitchen & Dining > Drinkware > Drinking Glasses | AB126: A7-14 | AC126: S124 | AD126: A7-14 | AE126: *mm | AO126: print on demand, personalised, custom, gift, drinkware, glassware & barware, #printondemand, #customgift, #custommug
B127: Result Urban Outdoor | D127: Tumblers | E127: Wine Tumbler Metal | F127: HAR2121030 | G127: OUTERW | H127: DAT125 | I127: CH125 | M127: Application Tape | N127: Home & Garden > Kitchen & Dining > Drinkware > Tumblers | AB127: Letter | AC127: S125 | AD127: Letter | AE127: 8.5 × 11 | AF127: LTR | AO127: print on demand, personalised, custom, gift, drinkware, tumblers, #printondemand, #customgift, #custommug
B128: Rhino | D128: Glassware & Barware | E128: Frosted Glass Can | F128: HAR2121031 | G128: OUTERW | H128: DAT126 | I128: CH126 | M128: Automotive Films | N128: Home & Garden > Kitchen & Dining > Drinkware > Drinking Glasses | AB128: Legal | AC128: S126 | AD128: Legal | AE128: 8.5 × 14 | AF128: LGL | AO128: print on demand, personalised, custom, gift, drinkware, glassware & barware, #printondemand, #customgift, #custommug
B129: Ribbon | D129: Bottles & Flasks | E129: Protein Shaker Bottle | F129: HAR2121032 | G129: OUTERW | H129: DAT127 | I129: CH127 | M129: Paint / Sandblast Films | N129: Home & Garden > Kitchen & Dining > Drinkware > Water Bottles | AB129: Tabloid | AC129: S127 | AD129: Tabloid | AE129: 11 × 17 | AF129: TAB | AO129: print on demand, personalised, custom, gift, drinkware, bottles & flasks, #printondemand, #customgift, #custommug
B130: Scruffs | D130: Cushions & Pillows | E130: Round Cushion | F130: HAR2121037 | G130: OUTERW | H130: DAT128 | I130: CH128 | M130: Clothing Vinyl / HTV | N130: Home & Garden > Linens & Bedding > Decorative Pillows | AB130: Ledger | AC130: S128 | AD130: Ledger | AE130: 17 × 11 | AF130: LED | AO130: print on demand, personalised, custom, gift, home & living, cushions & pillows, #printondemand, #customgift, #homedecor
B131: SF Clothing | D131: Cushions & Pillows | E131: Body Pillow | F131: HAR2121038 | G131: OUTERW | H131: DAT129 | I131: CH129 | M131: Clothing Range | N131: Home & Garden > Linens & Bedding > Decorative Pillows | AB131: Executive | AC131: S129 | AD131: Executive | AE131: 7.25 × 10.5 | AF131: EXE | AO131: print on demand, personalised, custom, gift, home & living, cushions & pillows, #printondemand, #customgift, #homedecor
B132: Spiro Recycled | D132: Cushions & Pillows | E132: Floor Pillow | F132: HAR2121039 | G132: OUTERW | H132: DAT130 | I132: CH130 | M132: Dye Sub Equipment | N132: Home & Garden > Linens & Bedding > Decorative Pillows | AC132: S130 | AE132: 500*500 | AF132: RB1 | AO132: print on demand, personalised, custom, gift, home & living, cushions & pillows, #printondemand, #customgift, #homedecor
B133: Splashmacs | D133: Rugs & Mats | E133: Baby Play Mat | F133: HAR2121040 | G133: OUTERW | H133: DAT131 | I133: CH131 | M133: Dye Sub Inks / Paper | N133: Home & Garden > Rugs | AC133: S131 | AE133: 760*500 | AF133: RB2 | AO133: print on demand, personalised, custom, gift, home & living, rugs & mats, #printondemand, #customgift, #homedecor
B134: Stanley / Stella | D134: Table Linens | E134: Table Runner | F134: HAR2121041 | G134: OUTERW | H134: DAT132 | I134: CH132 | M134: Dye Sub Blanks | N134: Home & Garden > Kitchen & Dining > Kitchen Linens | AC134: S132 | AE134: 1370*500 | AF134: RB3 | AO134: print on demand, personalised, custom, gift, home & living, table linens, #printondemand, #customgift, #homedecor
B135: Stanley Workwear | D135: Table Linens | E135: Table Cloth | F135: HAR2121042 | G135: OUTERW | H135: DAT133 | I135: CH133 | M135: Vinyl Cutters | N135: Home & Garden > Kitchen & Dining > Kitchen Linens | AC135: S133 | AE135: 1520*500 | AF135: RB4 | AO135: print on demand, personalised, custom, gift, home & living, table linens, #printondemand, #customgift, #homedecor
B136: The Christmas Shop | D136: Rugs & Mats | E136: Placemat Set | F136: HAR2121043 | G136: OUTERW | H136: DAT134 | I136: CH134 | M136: Heat Presses | N136: Home & Garden > Rugs | AC136: S134 | AE136: 1600*500 | AF136: RB5 | AO136: print on demand, personalised, custom, gift, home & living, rugs & mats, #printondemand, #customgift, #homedecor
B137: TheMagicTouch | D137: Curtains & Drapes | E137: Shower Curtain | F137: HAR2121044 | G137: OUTERW | H137: DAT135 | I137: CH135 | M137: Sign Tools & Mats | N137: Home & Garden > Window Treatments > Curtains & Drapes | AC137: S135 | AE137: =AC74&#REF!&AF131 -> #REF! | AF137: RB6 | AO137: print on demand, personalised, custom, gift, home & living, curtains & drapes, #printondemand, #customgift, #homedecor
B138: Tombo | D138: Home Textiles | E138: Wall Tapestry | F138: HAR2121045 | G138: OUTERW | H138: DAT136 | I138: CH136 | M138: Substrates / Signs | N138: Home & Garden > Decor | AC138: S136 | AE138: =AC75&#REF!&AF132 -> #REF! | AF138: RB7 | AO138: print on demand, personalised, custom, gift, home & living, home textiles, #printondemand, #customgift, #homedecor
B139: Towel City | D139: Blankets & Bedding | E139: Throw Rug | F139: HAR2121046 | G139: OUTERW | H139: DAT137 | I139: CH137 | M139: Cut Letter / Fabrication | N139: Home & Garden > Linens & Bedding > Blankets | AC139: S137 | AE139: =AC76&#REF!&AF133 -> #REF! | AF139: RB8 | AO139: print on demand, personalised, custom, gift, home & living, blankets & bedding, #printondemand, #customgift, #homedecor
B140: TriDri® | D140: Towels | E140: Kitchen Towel | F140: HAR2121049 | G140: OUTERW | H140: DAT138 | I140: CH138 | M140: Silhouette Cameo | N140: Home & Garden > Linens & Bedding > Towels | AC140: S138 | AE140: 500*710 | AF140: RB9 | AO140: print on demand, personalised, custom, gift, home & living, towels, #printondemand, #customgift, #homedecor
B141: Under Armour | D141: Kitchen Textiles | E141: Oven Mitt and Pot Holder Set | F141: HAR2121050 | G141: OUTERW | H141: DAT139 | I141: CH139 | M141: Silhouette Portrait | N141: Home & Garden > Kitchen & Dining > Kitchen Linens | AC141: S139 | AE141: 760*1079.2 | AF141: RB10 | AO141: print on demand, personalised, custom, gift, home & living, kitchen textiles, #printondemand, #customgift, #homedecor
B142: Under Armour Golf | D142: Travel & Gym Bags | E142: Weekender Bag | F142: HAR2121051 | G142: OUTERW | H142: DAT140 | I142: CH140 | M142: Cricut | N142: Luggage & Bags | AC142: S140 | AE142: 1370*1945.4 | AF142: RB11 | AO142: print on demand, personalised, custom, gift, accessories, travel & gym bags, #printondemand, #customgift
B143: Wombat | D143: Travel & Gym Bags | E143: Gym Bag | F143: HAR2121052 | G143: OUTERW | H143: DAT141 | I143: CH141 | M143: Etching | N143: Luggage & Bags | AC143: S141 | AE143: 1520*2158.4 | AF143: RB12 | AO143: print on demand, personalised, custom, gift, accessories, travel & gym bags, #printondemand, #customgift
B144: ADC | D144: Cosmetic Bags | E144: Makeup Bag | F144: HAR2121053 | G144: OUTERW | H144: DAT142 | I144: CH142 | M144: Doming | N144: Luggage & Bags | AC144: S142 | AE144: 1600*2272 | AF144: RB13 | AO144: print on demand, personalised, custom, gift, accessories, cosmetic bags, #printondemand, #customgift
B145: Brand Lab (Exclusive) | D145: Pencil & Pen Cases | E145: Pencil Case | F145: HAR2121054 | G145: OUTERW | H145: DAT143 | I145: CH143 | M145: Swatches | N145: Electronics > Electronics Accessories > Bags, Cases & Sleeves | AC145: S143 | AE145: 500*500 | AF145: RB14 | AO145: print on demand, personalised, custom, gift, accessories, pencil & pen cases, #printondemand, #customgift
B146: Brook Taverner (Exclusive) | D146: Backpacks | E146: Drawstring Backpack | F146: HAR2121055 | G146: OUTERW | H146: DAT144 | I146: CH144 | M146: White Ceramic | N146: Luggage & Bags | AC146: S144 | AE146: 760*760 | AF146: RB15 | AO146: print on demand, personalised, custom, gift, accessories, backpacks, #printondemand, #customgift
B147: Canterbury (Exclusive) | D147: General Accessories | E147: Laptop Bag | F147: HAR2121056 | G147: OUTERW | H147: DAT145 | I147: CH145 | M147: Bone China | N147: Luggage & Bags | AC147: S145 | AE147: 1370*1370 | AF147: RB16 | AO147: print on demand, personalised, custom, gift, accessories, general accessories, #printondemand, #customgift
B148: Comfort Grip | D148: General Accessories | E148: Tech Pouch | F148: HAR2121057 | G148: OUTERW | H148: DAT146 | I148: CH146 | M148: Coloured Mugs | N148: Apparel & Accessories | AC148: S146 | AE148: 1520*1520 | AF148: RB17 | AO148: print on demand, personalised, custom, gift, accessories, general accessories, #printondemand, #customgift
B149: Craghoppers | D149: Unclassified | E149: Phone Grip | F149: HAR2121500 | G149: OUTERW | H149: DAT147 | I149: CH147 | M149: Glass And Metal | N149: Apparel & Accessories | AC149: S147 | AE149: 1600*1600 | AF149: RB18 | AO149: print on demand, personalised, custom, gift, other, unclassified, #printondemand, #customgift
B150: Dennys | D150: Stickers & Labels | E150: Phone Wallet Back Sticker | F150: HAR2121501 | G150: OUTERW | H150: DAT148 | I150: CH148 | M150: Water Bottles | N150: Office Supplies > General Office Supplies > Labels & Stickers | AC150: S148 | AE150: 500*750 | AF150: RB19 | AO150: print on demand, personalised, custom, gift, stationery, stickers & labels, #printondemand, #customgift
B151: Ecologie | D151: Stationery | E151: Notepad | F151: HAR2121502 | G151: OUTERW | H151: DAT149 | I151: CH149 | M151: Other Drinkware | N151: Office Supplies | AC151: S149 | AE151: 760*1140 | AF151: RB20 | AO151: print on demand, personalised, custom, gift, stationery, #printondemand, #customgift
...

Sheet Guide2
A1: Sr | B1: Title | C1: Note | J1: Used By Base62 | K1: 0 | M1: A | O1: =M1&$K1 -> A0 | Q1: AA | S1: =K1&Q1 -> 0AA | U1: AB | X1: MC | Y1: Machine | AB1: A0 | AD1: =K$1&M$12&M1 -> 0LA | AF1: =M$16&M1 -> PA | AH1: =M$19&M$5&M1 -> SEA | AP1: Used By Base62 | AQ1: 0 | AS1: A | AU1: =AS1&$K1 -> A0 | AW1: AA | AY1: =AQ1&AW1 -> 0AA | BA1: AB | BD1: MC | BE1: Machine | BH1: A0 | BJ1: =AQ$1&AS$12&AS1 -> 0LA | BL1: =AS$16&AS1 -> PA | BN1: =AS$19&AS$5&AS1 -> SEA
A2: 1 | B2: A To Z | C2: BASE SKU | J2: Used By Base62 And Linking SKU Code | K2: 1 | M2: B | O2: =M2&$K2 -> B1 | Q2: BA | S2: =K2&Q2 -> 1BA | U2: BB | X2: MC | AB2: B1 | AD2: =K$1&M$12&M2 -> 0LB | AF2: =M$16&M2 -> PB | AH2: =M$19&M$5&M2 -> SEB | AP2: Used By Base62 And Linking SKU Code | AQ2: 1 | AS2: B | AU2: =AS2&$K2 -> B1 | AW2: BA | AY2: =AQ2&AW2 -> 1BA | BA2: BB | BD2: MC | BH2: B1 | BJ2: =AQ$1&AS$12&AS2 -> 0LB | BL2: =AS$16&AS2 -> PB | BN2: =AS$19&AS$5&AS2 -> SEB
A3: 2 | B3: 1 to unlimited | C3: btcactivewear | J3: Used By Linking SKU Code | K3: 2 | M3: C | O3: =M3&$K3 -> C2 | Q3: CA | S3: =K3&Q3 -> 2CA | U3: CB | X3: CT | AB3: C2 | AD3: =K$1&M$12&M3 -> 0LC | AF3: =M$16&M3 -> PC | AH3: =M$19&M$5&M3 -> SEC | AP3: Used By Linking SKU Code | AQ3: 2 | AS3: C | AU3: =AS3&$K3 -> C2 | AW3: CA | AY3: =AQ3&AW3 -> 2CA | BA3: CB | BD3: CT | BH3: C2 | BJ3: =AQ$1&AS$12&AS3 -> 0LC | BL3: =AS$16&AS3 -> PC | BN3: =AS$19&AS$5&AS3 -> SEC
A4: 3 | B4: 1-A | C4: ralawise | J4: Used For Designs | K4: 3 | M4: D | O4: =M4&$K4 -> D3 | Q4: DA | S4: =K4&Q4 -> 3DA | U4: DB | X4: CL | AB4: D3 | AD4: =K$1&M$12&M4 -> 0LD | AF4: =M$16&M4 -> PD | AH4: =M$19&M$5&M4 -> SED | AP4: Used For Designs | AQ4: 3 | AS4: D | AU4: =AS4&$K4 -> D3 | AW4: DA | AY4: =AQ4&AW4 -> 3DA | BA4: DB | BD4: CL | BH4: D3 | BJ4: =AQ$1&AS$12&AS4 -> 0LD | BL4: =AS$16&AS4 -> PD | BN4: =AS$19&AS$5&AS4 -> SED
A5: 4 | C5: PenCarrie | J5: Used For SET Listing | K5: 4 | M5: E | O5: =M5&$K5 -> E4 | Q5: EA | S5: =K5&Q5 -> 4EA | U5: EB | X5: PT | AB5: E4 | AD5: =K$1&M$12&M5 -> 0LE | AF5: =M$16&M5 -> PE | AH5: =M$19&M$5&M5 -> SEE | AP5: Used For SET Listing | AQ5: 4 | AS5: E | AT5: EVENT | AU5: =AS5&$K5 -> E4 | AW5: EA | AY5: =AQ5&AW5 -> 4EA | BA5: EB | BD5: PT | BH5: E4 | BJ5: =AQ$1&AS$12&AS5 -> 0LE | BL5: =AS$16&AS5 -> PE | BN5: =AS$19&AS$5&AS5 -> SEE
A6: 5 | C6: uneekclothing | K6: 5 | M6: F | O6: =M6&$K6 -> F5 | Q6: FA | S6: =K6&Q6 -> 5FA | U6: FB | X6: PG | AB6: F5 | AD6: =K$1&M$12&M6 -> 0LF | AF6: =M$16&M6 -> PF | AH6: =M$19&M$5&M6 -> SEF | AQ6: 5 | AS6: F | AU6: =AS6&$K6 -> F5 | AW6: FA | AY6: =AQ6&AW6 -> 5FA | BA6: FB | BD6: PG | BH6: F5 | BJ6: =AQ$1&AS$12&AS6 -> 0LF | BL6: =AS$16&AS6 -> PF | BN6: =AS$19&AS$5&AS6 -> SEF
A7: 6 | C7: absoluteapparel | K7: 6 | M7: G | O7: =M7&$K7 -> G6 | Q7: GA | S7: =K7&Q7 -> 6GA | U7: GB | X7: PRT | AB7: G6 | AD7: =K$1&M$12&M7 -> 0LG | AF7: =M$16&M7 -> PG | AH7: =M$19&M$5&M7 -> SEG | AQ7: 6 | AS7: G | AU7: =AS7&$K7 -> G6 | AW7: GA | AY7: =AQ7&AW7 -> 6GA | BA7: GB | BD7: PRT | BH7: G6 | BJ7: =AQ$1&AS$12&AS7 -> 0LG | BL7: =AS$16&AS7 -> PG | BN7: =AS$19&AS$5&AS7 -> SEG
A8: 7 | B8: DS1001S | C8: mdpsupplies | E8: M5 | I8: NOTE | K8: 7 | M8: H | O8: =M8&$K8 -> H7 | Q8: HA | S8: =K8&Q8 -> 7HA | U8: HB | X8: CG | AB8: H7 | AD8: =K$1&M$12&M8 -> 0LH | AF8: =M$16&M8 -> PH | AH8: =M$19&M$5&M8 -> SEH | AQ8: 7 | AS8: H | AU8: =AS8&$K8 -> H7 | AW8: HA | AY8: =AQ8&AW8 -> 7HA | BA8: HB | BD8: CG | BH8: H7 | BJ8: =AQ$1&AS$12&AS8 -> 0LH | BL8: =AS$16&AS8 -> PH | BN8: =AS$19&AS$5&AS8 -> SEH
A9: 8 | E9: LG | I9: 46002 | J9: B64 BEFORE NO LOW CASE | K9: 8 | M9: I | O9: =M9&$K9 -> I8 | Q9: IA | S9: =K9&Q9 -> 8IA | U9: IB | X9: MCG | AB9: I8 | AD9: =K$1&M$12&M9 -> 0LI | AF9: =M$16&M9 -> PI | AH9: =M$19&M$5&M9 -> SEI | AQ9: 8 | AS9: I | AU9: =AS9&$K9 -> I8 | AW9: IA | AY9: =AQ9&AW9 -> 8IA | BA9: IB | BD9: MCG | BH9: I8 | BJ9: =AQ$1&AS$12&AS9 -> 0LI | BL9: =AS$16&AS9 -> PI | BN9: =AS$19&AS$5&AS9 -> SEI
A10: 9 | E10: BTC | J10: B32 AFTER | K10: 9 | M10: J | O10: =M10&$K10 -> J9 | Q10: JA | S10: =K10&Q10 -> 9JA | U10: JB | X10: SS | AB10: J9 | AD10: =K$1&M$12&M10 -> 0LJ | AF10: =M$16&M10 -> PJ | AH10: =M$19&M$5&M10 -> SEJ | AQ10: 9 | AS10: J | AU10: =AS10&$K10 -> J9 | AW10: JA | AY10: =AQ10&AW10 -> 9JA | BA10: JB | BD10: SS | BH10: J9 | BJ10: =AQ$1&AS$12&AS10 -> 0LJ | BL10: =AS$16&AS10 -> PJ | BN10: =AS$19&AS$5&AS10 -> SEJ
A11: 10 | E11: FIVE SHEETS | K11: 10 | M11: K | O11: =M11&$K11 -> K10 | Q11: KA | S11: =K11&Q11 -> 10KA | U11: KB | X11: PC | AB11: K10 | AD11: =K$1&M$12&M11 -> 0LK | AF11: =M$16&M11 -> PK | AH11: =M$19&M$5&M11 -> SEK | AQ11: 10 | AS11: K | AU11: =AS11&$K11 -> K10 | AW11: KA | AY11: =AQ11&AW11 -> 10KA | BA11: KB | BD11: PC | BH11: K10 | BJ11: =AQ$1&AS$12&AS11 -> 0LK | BL11: =AS$16&AS11 -> PK | BN11: =AS$19&AS$5&AS11 -> SEK
A12: 11 | I12: SKU | J12: A1 | K12: 11 | M12: L | O12: =M12&$K12 -> L11 | Q12: LA | S12: =K12&Q12 -> 11LA | U12: LB | X12: V | AB12: L11 | AD12: =K$1&M$12&M12 -> 0LL | AF12: =M$16&M12 -> PL | AH12: =M$19&M$5&M12 -> SEL | AQ12: 11 | AS12: L | AU12: =AS12&$K12 -> L11 | AW12: LA | AY12: =AQ12&AW12 -> 11LA | BA12: LB | BD12: V | BH12: L11 | BJ12: =AQ$1&AS$12&AS12 -> 0LL | BL12: =AS$16&AS12 -> PL | BN12: =AS$19&AS$5&AS12 -> SEL
A13: 12 | I13: TILE | J13: A1 | K13: 12 | M13: M | O13: =I3&$K13 -> 12 | Q13: MA | S13: =K13&Q13 -> 12MA | U13: MB | X13: W | AB13: M12 | AD13: =K$1&M$12&M13 -> 0LM | AF13: =M$16&M13 -> PM | AH13: =M$19&M$5&M13 -> SEM | AQ13: 12 | AS13: M | AU13: =AO3&$K13 -> 12 | AW13: MA | AY13: =AQ13&AW13 -> 12MA | BA13: MB | BD13: W | BH13: M12 | BJ13: =AQ$1&AS$12&AS13 -> 0LM | BL13: =AS$16&AS13 -> PM | BN13: =AS$19&AS$5&AS13 -> SEM
A14: 13 | I14: DES | K14: 13 | M14: N | O14: =M14&$K14 -> N13 | Q14: NA | S14: =K14&Q14 -> 13NA | U14: NB | AB14: N13 | AD14: =K$1&M$12&M14 -> 0LN | AF14: =M$16&M14 -> PN | AH14: =M$19&M$5&M14 -> SEN | AQ14: 13 | AS14: N | AU14: =AS14&$K14 -> N13 | AW14: NA | AY14: =AQ14&AW14 -> 13NA | BA14: NB | BH14: N13 | BJ14: =AQ$1&AS$12&AS14 -> 0LN | BL14: =AS$16&AS14 -> PN | BN14: =AS$19&AS$5&AS14 -> SEN
A15: 14 | E15: 100LG-M-T-BLK-D | I15: TAGS | K15: 14 | M15: O | O15: =M15&$K15 -> O14 | Q15: OA | S15: =K15&Q15 -> 14OA | U15: OB | AB15: O14 | AD15: =K$1&M$12&M15 -> 0LO | AF15: =M$16&M15 -> PO | AH15: =M$19&M$5&M15 -> SEO | AQ15: 14 | AS15: O | AU15: =AS15&$K15 -> O14 | AW15: OA | AY15: =AQ15&AW15 -> 14OA | BA15: OB | BH15: O14 | BJ15: =AQ$1&AS$12&AS15 -> 0LO | BL15: =AS$16&AS15 -> PO | BN15: =AS$19&AS$5&AS15 -> SEO
A16: 15 | I16: PIONTS | K16: 15 | M16: P | O16: =M16&$K16 -> P15 | Q16: PA | S16: =K16&Q16 -> 15PA | U16: PB | AB16: P15 | AD16: =K$1&M$12&M16 -> 0LP | AF16: =M$16&M16 -> PP | AH16: =M$19&M$5&M16 -> SEP | AQ16: 15 | AS16: P | AU16: =AS16&$K16 -> P15 | AW16: PA | AY16: =AQ16&AW16 -> 15PA | BA16: PB | BH16: P15 | BJ16: =AQ$1&AS$12&AS16 -> 0LP | BL16: =AS$16&AS16 -> PP | BN16: =AS$19&AS$5&AS16 -> SEP
A17: 16 | I17: MOCK | J17: M | K17: 16 | M17: Q | O17: =M17&$K17 -> Q16 | Q17: QA | S17: =K17&Q17 -> 16QA | U17: QB | AB17: Q16 | AD17: =K$1&M$12&M17 -> 0LQ | AF17: =M$16&M17 -> PQ | AH17: =M$19&M$5&M17 -> SEQ | AQ17: 16 | AS17: Q | AU17: =AS17&$K17 -> Q16 | AW17: QA | AY17: =AQ17&AW17 -> 16QA | BA17: QB | BH17: Q16 | BJ17: =AQ$1&AS$12&AS17 -> 0LQ | BL17: =AS$16&AS17 -> PQ | BN17: =AS$19&AS$5&AS17 -> SEQ
A18: 17 | I18: PASTING | J18: P | K18: 17 | M18: R | O18: =M18&$K18 -> R17 | Q18: RA | S18: =K18&Q18 -> 17RA | U18: RB | AB18: R17 | AD18: =K$1&M$12&M18 -> 0LR | AF18: =M$16&M18 -> PR | AH18: =M$19&M$5&M18 -> SER | AQ18: 17 | AS18: R | AU18: =AS18&$K18 -> R17 | AW18: RA | AY18: =AQ18&AW18 -> 17RA | BA18: RB | BH18: R17 | BJ18: =AQ$1&AS$12&AS18 -> 0LR | BL18: =AS$16&AS18 -> PR | BN18: =AS$19&AS$5&AS18 -> SER
A19: 18 | K19: 18 | M19: S | O19: =M19&$K19 -> S18 | Q19: SA | S19: =K19&Q19 -> 18SA | U19: SB | AB19: S18 | AD19: =K$1&M$12&M19 -> 0LS | AF19: =M$16&M19 -> PS | AH19: =M$19&M$5&M19 -> SES | AQ19: 18 | AS19: S | AU19: =AS19&$K19 -> S18 | AW19: SA | AY19: =AQ19&AW19 -> 18SA | BA19: SB | BH19: S18 | BJ19: =AQ$1&AS$12&AS19 -> 0LS | BL19: =AS$16&AS19 -> PS | BN19: =AS$19&AS$5&AS19 -> SES
A20: 19 | K20: 19 | M20: T | O20: =M20&$K20 -> T19 | Q20: TA | S20: =K20&Q20 -> 19TA | U20: TB | AB20: T19 | AD20: =K$1&M$12&M20 -> 0LT | AF20: =M$16&M20 -> PT | AH20: =M$19&M$5&M20 -> SET | AQ20: 19 | AS20: T | AU20: =AS20&$K20 -> T19 | AW20: TA | AY20: =AQ20&AW20 -> 19TA | BA20: TB | BH20: T19 | BJ20: =AQ$1&AS$12&AS20 -> 0LT | BL20: =AS$16&AS20 -> PT | BN20: =AS$19&AS$5&AS20 -> SET
A21: 20 | K21: 20 | M21: U | O21: =M21&$K21 -> U20 | Q21: UA | S21: =K21&Q21 -> 20UA | U21: UB | AB21: U20 | AD21: =K$1&M$12&M21 -> 0LU | AF21: =M$16&M21 -> PU | AH21: =M$19&M$5&M21 -> SEU | AQ21: 20 | AS21: U | AU21: =AS21&$K21 -> U20 | AW21: UA | AY21: =AQ21&AW21 -> 20UA | BA21: UB | BH21: U20 | BJ21: =AQ$1&AS$12&AS21 -> 0LU | BL21: =AS$16&AS21 -> PU | BN21: =AS$19&AS$5&AS21 -> SEU
A22: 21 | K22: 21 | M22: V | O22: =M22&$K22 -> V21 | Q22: VA | S22: =K22&Q22 -> 21VA | U22: VB | AB22: V21 | AD22: =K$1&M$12&M22 -> 0LV | AF22: =M$16&M22 -> PV | AH22: =M$19&M$5&M22 -> SEV | AQ22: 21 | AS22: V | AU22: =AS22&$K22 -> V21 | AW22: VA | AY22: =AQ22&AW22 -> 21VA | BA22: VB | BH22: V21 | BJ22: =AQ$1&AS$12&AS22 -> 0LV | BL22: =AS$16&AS22 -> PV | BN22: =AS$19&AS$5&AS22 -> SEV
A23: 22 | K23: 22 | M23: W | O23: =M23&$K23 -> W22 | Q23: WA | S23: =K23&Q23 -> 22WA | U23: WB | AB23: W22 | AD23: =K$1&M$12&M23 -> 0LW | AF23: =M$16&M23 -> PW | AH23: =M$19&M$5&M23 -> SEW | AQ23: 22 | AS23: W | AU23: =AS23&$K23 -> W22 | AW23: WA | AY23: =AQ23&AW23 -> 22WA | BA23: WB | BH23: W22 | BJ23: =AQ$1&AS$12&AS23 -> 0LW | BL23: =AS$16&AS23 -> PW | BN23: =AS$19&AS$5&AS23 -> SEW
A24: 23 | I24: M-T | K24: 23 | M24: X | O24: =M24&$K24 -> X23 | Q24: XA | S24: =K24&Q24 -> 23XA | U24: XB | AB24: X23 | AD24: =K$1&M$12&M24 -> 0LX | AF24: =M$16&M24 -> PX | AH24: =M$19&M$5&M24 -> SEX | AQ24: 23 | AS24: X | AU24: =AS24&$K24 -> X23 | AW24: XA | AY24: =AQ24&AW24 -> 23XA | BA24: XB | BH24: X23 | BJ24: =AQ$1&AS$12&AS24 -> 0LX | BL24: =AS$16&AS24 -> PX | BN24: =AS$19&AS$5&AS24 -> SEX
A25: 24 | K25: 24 | M25: Y | O25: =M25&$K25 -> Y24 | Q25: YA | S25: =K25&Q25 -> 24YA | U25: YB | AB25: Y24 | AD25: =K$1&M$12&M25 -> 0LY | AF25: =M$16&M25 -> PY | AH25: =M$19&M$5&M25 -> SEY | AQ25: 24 | AS25: Y | AU25: =AS25&$K25 -> Y24 | AW25: YA | AY25: =AQ25&AW25 -> 24YA | BA25: YB | BH25: Y24 | BJ25: =AQ$1&AS$12&AS25 -> 0LY | BL25: =AS$16&AS25 -> PY | BN25: =AS$19&AS$5&AS25 -> SEY
A26: 25 | D26: OLD 2013 90% | F26: 62480LG-K-H-DHR-YL | K26: 25 | M26: Z | O26: =M26&$K26 -> Z25 | Q26: ZA | S26: =K26&Q26 -> 25ZA | U26: ZB | AB26: Z25 | AD26: =K$1&M$12&M26 -> 0LZ | AF26: =M$16&M26 -> PZ | AH26: =M$19&M$5&M26 -> SEZ | AQ26: 25 | AS26: Z | AU26: =AS26&$K26 -> Z25 | AW26: ZA | AY26: =AQ26&AW26 -> 25ZA | BA26: ZB | BH26: Z25 | BJ26: =AQ$1&AS$12&AS26 -> 0LZ | BL26: =AS$16&AS26 -> PZ | BN26: =AS$19&AS$5&AS26 -> SEZ
D27: OLD 2013 90% | E27: OLD 2021 | F27: 6081LG-DM-F/S-F4-M-H-WHI-XL 37798LG-DM-S1-M-H-WHI-XL | G27: DM-F/S-F4 | H27: DM-S1 | I27: M-H-WHI-XL | J27: 6081LG/37798LG -DM-F/S-F4-DM-S1-M-H-WHI-XL
D28: OLD 2013 90% | E28: OLD 2021 | F28: Plain-BG-BG125-MUD-O/S | G28: Plain-BG | I28: BG125-MUD-O/S
D29: OLD 2013 90% | F29: 112637LG-BG-QD457-BGNDY-O/S-YES
D30: OLD 2013 90% | F30: 129010LG-C8030T-BS-WHI-0-3M-Yes | G30: DG-DM | H30: DG-F/S-F4-W-T-BLK-XL | I30: DM-F/S-F4-K-T-BLK-YL 32360LG-DM-S1-K-T-BLK-YL
D31: OLD 2013 90% | E31: OLD 2021 | F31: 6081LG-DM-F/S-F4-M-H-WHI-XL 37798LG-DM-S1-M-H-WHI-XL
D32: OLD 2013 90% | E32: OLD 2022 | F32: 48813LG-DTF-IronOn-A4-YES
E34: 2025
F35: 62480LG-K-H-DHR-YL
F36: 6081LG-DM-F/S-F4-M-H-WHI-XL 37798LG-DM-S1-M-H-WHI-XL
F37: Plain-BG-BG125-MUD-O/S
F38: 112637LG-BG-QD457-BGNDY-O/S-YES
F39: 129010LG-C8030T-BS-WHI-0-3M-Yes
F40: 6081LG-DM-F/S-F4-M-H-WHI-XL 37798LG-DM-S1-M-H-WHI-XL
F41: 48813LG-DTF-IronOn-A4-YES
D43: 2025 | E43: BASE 64
D45: fix | E45: fix | F45: fix | G45: varation
D46: btc | E46: base 62 | F46: daataadirect | G46: store
F52: DATA1-PLAIN | G52: DATA2-CHOICE 4
F53: 64000
G54: BLACK
G55: RED
D59: ALG | E59: HASHIM | F59: 46029
D60: ZLG | E60: HASHIM | F60: 46030
D63: LG-F | E63: OLD USING
D64: LG-B | E64: OLD USING
D87: NEW 2026
C90: OLD DATA | D90: LG-B
D91: LG-F
F93: 1 | G93: 2
D94: LG-F1 SO ON | E94: M1 | F94: 64000 PLSU VARTION BY US | G94: POSTION +PRINTING | H94: FIX | I94: LG-M-P-BTC | J94: BACK+FRONT +FRONT +LEFT SLEEVE | K94: BTC SAME
D95: LG-B1 SO ON | E95: N1 | F95: NOT | G95: POSTION +PRINTING +SIZE | I95: LG-N-BTC | K95: FRONT ,BACK ,SLEEVEN ,LEFT
D96: LG-L1 SO ON
D97: LG-R1 SO ON | K97: BTC -F | L97: BTC-1
D98: LG-N1 SO ON | K98: BTC-B | L98: BTC-2
K99: BTC-LEFT | L99: BTC-3
K100: BTC-RIGHT | L100: BTC-4
I101: 1D | J101: SSYSTEM
B104: old | D104: NEW 2026
B105: Products | C105: M-T
B106: Products | C106: W-T
B107: Products | C107: K-T
B108: Design | C108: ALG TO ZLG
B109: Design | C109: LG-F
B110: Design | C110: LG-B
B111: COLOUR CODE | C111: BLK
B112: Material | D112: Material | E112: MAT011
D113: Computer | E113: PC01
D114: MCH | E114: MCH01
D115: N
D116: M
D117: P
D118: BTC /RALWA/UNIEEK/ABSOLUTE

Sheet Guide3
A1: Parent-Code-S | B1: child-Code-S | C1: Supplier | D1: Tile-Parent | E1: Tile-SKU | F1: =Guide!B1 -> Product Tile | G1: =A1 -> Parent-Code-S | H1: =B1 -> child-Code-S | I1: Product-code-D | J1: =Values!A1 -> Brand-code-D | K1: USING | L1: =AG1 -> Parent-SKU-D | M1: =AH1 -> CHILD-SKU-D | N1: barcode | O1: URL | P1: URL | Q1: URL | R1: COLOUR | S1: Size | T1: Selling Size | U1: Selling Size | V1: Min Weight | W1: max Weight | X1: postage | Y1: Shape | Z1: Material-ID | AA1: Material-1 | AB1: Material-2 | AC1: Thickness | AD1: Thinner | AE1: Light Source | AF1: Power supply | AG1: Parent-SKU-D | AH1: CHILD-SKU-D | AI1: Combined-Brand | AJ1: Printing | AK1: Printing | AL1: Printing | AM1: Printing | AN1: =BG1 -> Final Selling Price | AO1: size | AQ1: LG | AR1: Mock | AS1: Mock | AT1: design_type_code | AV1: =M1 -> CHILD-SKU-D | AW1: SKU | AX1: SKU | AY1: Tile | AZ1: Product | BA1: Material | BB1: UV Print | BC1: Royal Mail | BD1: Cost Before VAT | BE1: Selling Price (+20% Profit) | BF1: Selling Price + 20% VAT | BG1: Final Selling Price | BH1: Packed Weight | BI1: Best Service | BJ1: Market low | BK1: Market Middle | BL1: Market High | BM1: length_mm | BN1: width_mm | BO1: height_mm | BP1: weight_g | BQ1: package_type | BR1: dispatch_days | BS1: shipping_policy | BT1: 2 kg Small parecl OR Large Letter | BU1: Max Qty Fit BY DIMENSION | BV1: Max Qty Fit BY WEIGHT
B2: ds000660s | C2: mdpsupplies | D2: Two-Tone 11oz Mug – Coloured Handle & Inner | E2: Two-Tone 11oz Mug – Black | F2: =IFERROR(VLOOKUP(I2,Guide!A:B,2,FALSE),"") -> Two-Tone Mug | G2: =A2 -> 0 | H2: =B2 -> ds000660s | I2: PT47 | J2: =IFERROR(VLOOKUP(F2,Values!D:E,2,FALSE),"") -> DAT012 | L2: A3F | M2: 1D1 | N2: 1000000000001 | O2: https://www.mdpsupplies.co.uk/dye-sublimation/dye-sub-two-tone-11oz-mugs | R2: BZ2 | S2: 11oz | T2: 11oz | V2: =IFERROR(VLOOKUP(I2,Guide!A:D,3,FALSE),"") -> PT47 | W2: =IFERROR(VLOOKUP(I2,Guide!A:F,5,FALSE),"") -> 150 | X2: =IFERROR(VLOOKUP(I2,Guide!A:G,6,FALSE),"") -> 520 | AA2: Ceramics | AG2: =L2 -> A3F | AH2: =M2 -> 1D1 | AJ2: Sublimation | AK2: Sublimation | AN2: 1D1 | AO2: =T2 -> 11oz | AP2: CT-6 | AQ2: LG | AR2: N58 | AT2: P | AV2: =M2 -> 1D1 | AW2: =_xlfn.TEXTJOIN("-",TRUE,AQ2:AV2) -> LG-N58-P-1D1 | AX2: =_xlfn.TEXTJOIN("-",TRUE,AS2:AV2) -> P-1D1 | AY2: =E2 -> Two-Tone 11oz Mug – Black
B3: ds000661s | C3: mdpsupplies | D3: Two-Tone 11oz Mug – Coloured Handle & Inner | E3: Two-Tone 11oz Mug – Dark Blue | F3: =IFERROR(VLOOKUP(I3,Guide!A:B,2,FALSE),"") -> Two-Tone Mug | G3: =A3 -> 0 | H3: =B3 -> ds000661s | I3: PT47 | J3: =IFERROR(VLOOKUP(F3,Values!D:E,2,FALSE),"") -> DAT012 | L3: A3F | M3: 1D2 | N3: 1000000000002 | O3: https://www.mdpsupplies.co.uk/dye-sublimation/dye-sub-two-tone-11oz-mugs | R3: Dark BLUE | S3: 11oz | T3: 11oz | V3: =IFERROR(VLOOKUP(I3,Guide!A:D,3,FALSE),"") -> PT47 | W3: =IFERROR(VLOOKUP(I3,Guide!A:F,5,FALSE),"") -> 150 | X3: =IFERROR(VLOOKUP(I3,Guide!A:G,6,FALSE),"") -> 520 | AA3: Ceramics | AG3: =L3 -> A3F | AH3: =M3 -> 1D2 | AJ3: Sublimation | AK3: Sublimation | AN3: 1D2 | AO3: =T3 -> 11oz | AP3: CT-6 | AQ3: LG | AR3: N58 | AT3: P | AV3: =M3 -> 1D2 | AW3: =_xlfn.TEXTJOIN("-",TRUE,AQ3:AV3) -> LG-N58-P-1D2 | AX3: =_xlfn.TEXTJOIN("-",TRUE,AS3:AV3) -> P-1D2 | AY3: =E3 -> Two-Tone 11oz Mug – Dark Blue
B4: ds000662s | C4: mdpsupplies | D4: Two-Tone 11oz Mug – Coloured Handle & Inner | E4: Two-Tone 11oz Mug – Red | F4: =IFERROR(VLOOKUP(I4,Guide!A:B,2,FALSE),"") -> Two-Tone Mug | G4: =A4 -> 0 | H4: =B4 -> ds000662s | I4: PT47 | J4: =IFERROR(VLOOKUP(F4,Values!D:E,2,FALSE),"") -> DAT012 | L4: A3F | M4: 1D3 | N4: 1000000000003 | O4: https://www.mdpsupplies.co.uk/dye-sublimation/dye-sub-two-tone-11oz-mugs | R4: Red | S4: 11oz | T4: 11oz | V4: =IFERROR(VLOOKUP(I4,Guide!A:D,3,FALSE),"") -> PT47 | W4: =IFERROR(VLOOKUP(I4,Guide!A:F,5,FALSE),"") -> 150 | X4: =IFERROR(VLOOKUP(I4,Guide!A:G,6,FALSE),"") -> 520 | AA4: Ceramics | AG4: =L4 -> A3F | AH4: =M4 -> 1D3 | AJ4: Sublimation | AK4: Sublimation | AN4: 1D3 | AO4: =T4 -> 11oz | AP4: CT-6 | AQ4: LG | AR4: N58 | AT4: P | AV4: =M4 -> 1D3 | AW4: =_xlfn.TEXTJOIN("-",TRUE,AQ4:AV4) -> LG-N58-P-1D3 | AX4: =_xlfn.TEXTJOIN("-",TRUE,AS4:AV4) -> P-1D3 | AY4: =E4 -> Two-Tone 11oz Mug – Red
B5: ds000663s | C5: mdpsupplies | D5: Two-Tone 11oz Mug – Coloured Handle & Inner | E5: Two-Tone 11oz Mug – Pink | F5: =IFERROR(VLOOKUP(I5,Guide!A:B,2,FALSE),"") -> Two-Tone Mug | G5: =A5 -> 0 | H5: =B5 -> ds000663s | I5: PT47 | J5: =IFERROR(VLOOKUP(F5,Values!D:E,2,FALSE),"") -> DAT012 | L5: A3F | M5: 1D4 | N5: 1000000000004 | O5: https://www.mdpsupplies.co.uk/dye-sublimation/dye-sub-two-tone-11oz-mugs | R5: Pink | S5: 11oz | T5: 11oz | V5: =IFERROR(VLOOKUP(I5,Guide!A:D,3,FALSE),"") -> PT47 | W5: =IFERROR(VLOOKUP(I5,Guide!A:F,5,FALSE),"") -> 150 | X5: =IFERROR(VLOOKUP(I5,Guide!A:G,6,FALSE),"") -> 520 | AA5: Ceramics | AG5: =L5 -> A3F | AH5: =M5 -> 1D4 | AJ5: Sublimation | AK5: Sublimation | AN5: 1D4 | AO5: =T5 -> 11oz | AP5: CT-6 | AQ5: LG | AR5: N58 | AT5: P | AV5: =M5 -> 1D4 | AW5: =_xlfn.TEXTJOIN("-",TRUE,AQ5:AV5) -> LG-N58-P-1D4 | AX5: =_xlfn.TEXTJOIN("-",TRUE,AS5:AV5) -> P-1D4 | AY5: =E5 -> Two-Tone 11oz Mug – Pink
B6: ds000664s | C6: mdpsupplies | D6: Two-Tone 11oz Mug – Coloured Handle & Inner | E6: Two-Tone 11oz Mug – Yellow | F6: =IFERROR(VLOOKUP(I6,Guide!A:B,2,FALSE),"") -> Two-Tone Mug | G6: =A6 -> 0 | H6: =B6 -> ds000664s | I6: PT47 | J6: =IFERROR(VLOOKUP(F6,Values!D:E,2,FALSE),"") -> DAT012 | L6: A3F | M6: 1D5 | N6: 1000000000005 | O6: https://www.mdpsupplies.co.uk/dye-sublimation/dye-sub-two-tone-11oz-mugs | R6: Yellow | S6: 11oz | T6: 11oz | V6: =IFERROR(VLOOKUP(I6,Guide!A:D,3,FALSE),"") -> PT47 | W6: =IFERROR(VLOOKUP(I6,Guide!A:F,5,FALSE),"") -> 150 | X6: =IFERROR(VLOOKUP(I6,Guide!A:G,6,FALSE),"") -> 520 | AA6: Ceramics | AG6: =L6 -> A3F | AH6: =M6 -> 1D5 | AJ6: Sublimation | AK6: Sublimation | AN6: 1D5 | AO6: =T6 -> 11oz | AP6: CT-6 | AQ6: LG | AR6: N58 | AT6: P | AV6: =M6 -> 1D5 | AW6: =_xlfn.TEXTJOIN("-",TRUE,AQ6:AV6) -> LG-N58-P-1D5 | AX6: =_xlfn.TEXTJOIN("-",TRUE,AS6:AV6) -> P-1D5 | AY6: =E6 -> Two-Tone 11oz Mug – Yellow
B7: ds000665s | C7: mdpsupplies | D7: Two-Tone 11oz Mug – Coloured Handle & Inner | E7: Two-Tone 11oz Mug – Grey | F7: =IFERROR(VLOOKUP(I7,Guide!A:B,2,FALSE),"") -> Two-Tone Mug | G7: =A7 -> 0 | H7: =B7 -> ds000665s | I7: PT47 | J7: =IFERROR(VLOOKUP(F7,Values!D:E,2,FALSE),"") -> DAT012 | L7: A3F | M7: 1D6 | N7: 1000000000006 | O7: https://www.mdpsupplies.co.uk/dye-sublimation/dye-sub-two-tone-11oz-mugs | R7: Grey | S7: 11oz | T7: 11oz | V7: =IFERROR(VLOOKUP(I7,Guide!A:D,3,FALSE),"") -> PT47 | W7: =IFERROR(VLOOKUP(I7,Guide!A:F,5,FALSE),"") -> 150 | X7: =IFERROR(VLOOKUP(I7,Guide!A:G,6,FALSE),"") -> 520 | AA7: Ceramics | AG7: =L7 -> A3F | AH7: =M7 -> 1D6 | AJ7: Sublimation | AK7: Sublimation | AN7: 1D6 | AO7: =T7 -> 11oz | AP7: CT-6 | AQ7: LG | AR7: N58 | AT7: P | AV7: =M7 -> 1D6 | AW7: =_xlfn.TEXTJOIN("-",TRUE,AQ7:AV7) -> LG-N58-P-1D6 | AX7: =_xlfn.TEXTJOIN("-",TRUE,AS7:AV7) -> P-1D6 | AY7: =E7 -> Two-Tone 11oz Mug – Grey
B8: ds000666s | C8: mdpsupplies | D8: Two-Tone 11oz Mug – Coloured Handle & Inner | E8: Two-Tone 11oz Mug – Green | F8: =IFERROR(VLOOKUP(I8,Guide!A:B,2,FALSE),"") -> Two-Tone Mug | G8: =A8 -> 0 | H8: =B8 -> ds000666s | I8: PT47 | J8: =IFERROR(VLOOKUP(F8,Values!D:E,2,FALSE),"") -> DAT012 | L8: A3F | M8: 1D7 | N8: 1000000000007 | O8: https://www.mdpsupplies.co.uk/dye-sublimation/dye-sub-two-tone-11oz-mugs | R8: Green | S8: 11oz | T8: 11oz | V8: =IFERROR(VLOOKUP(I8,Guide!A:D,3,FALSE),"") -> PT47 | W8: =IFERROR(VLOOKUP(I8,Guide!A:F,5,FALSE),"") -> 150 | X8: =IFERROR(VLOOKUP(I8,Guide!A:G,6,FALSE),"") -> 520 | AA8: Ceramics | AG8: =L8 -> A3F | AH8: =M8 -> 1D7 | AJ8: Sublimation | AK8: Sublimation | AN8: 1D7 | AO8: =T8 -> 11oz | AP8: CT-6 | AQ8: LG | AR8: N58 | AT8: P | AV8: =M8 -> 1D7 | AW8: =_xlfn.TEXTJOIN("-",TRUE,AQ8:AV8) -> LG-N58-P-1D7 | AX8: =_xlfn.TEXTJOIN("-",TRUE,AS8:AV8) -> P-1D7 | AY8: =E8 -> Two-Tone 11oz Mug – Green
B9: ds000667s | C9: mdpsupplies | D9: Two-Tone 11oz Mug – Coloured Handle & Inner | E9: Two-Tone 11oz Mug – Orange | F9: =IFERROR(VLOOKUP(I9,Guide!A:B,2,FALSE),"") -> Two-Tone Mug | G9: =A9 -> 0 | H9: =B9 -> ds000667s | I9: PT47 | J9: =IFERROR(VLOOKUP(F9,Values!D:E,2,FALSE),"") -> DAT012 | L9: A3F | M9: 1D8 | N9: 1000000000008 | O9: https://www.mdpsupplies.co.uk/dye-sublimation/dye-sub-two-tone-11oz-mugs | R9: Orange | S9: 11oz | T9: 11oz | V9: =IFERROR(VLOOKUP(I9,Guide!A:D,3,FALSE),"") -> PT47 | W9: =IFERROR(VLOOKUP(I9,Guide!A:F,5,FALSE),"") -> 150 | X9: =IFERROR(VLOOKUP(I9,Guide!A:G,6,FALSE),"") -> 520 | AA9: Ceramics | AG9: =L9 -> A3F | AH9: =M9 -> 1D8 | AJ9: Sublimation | AK9: Sublimation | AN9: 1D8 | AO9: =T9 -> 11oz | AP9: CT-6 | AQ9: LG | AR9: N58 | AT9: P | AV9: =M9 -> 1D8 | AW9: =_xlfn.TEXTJOIN("-",TRUE,AQ9:AV9) -> LG-N58-P-1D8 | AX9: =_xlfn.TEXTJOIN("-",TRUE,AS9:AV9) -> P-1D8 | AY9: =E9 -> Two-Tone 11oz Mug – Orange
B10: ds000668s | C10: mdpsupplies | D10: Two-Tone 11oz Mug – Coloured Handle & Inner | E10: Two-Tone 11oz Mug – Medium Blue | F10: =IFERROR(VLOOKUP(I10,Guide!A:B,2,FALSE),"") -> Two-Tone Mug | G10: =A10 -> 0 | H10: =B10 -> ds000668s | I10: PT47 | J10: =IFERROR(VLOOKUP(F10,Values!D:E,2,FALSE),"") -> DAT012 | L10: A3F | M10: 1D9 | N10: 1000000000009 | O10: https://www.mdpsupplies.co.uk/dye-sublimation/dye-sub-two-tone-11oz-mugs | R10: Medium Blue | S10: 11oz | T10: 11oz | V10: =IFERROR(VLOOKUP(I10,Guide!A:D,3,FALSE),"") -> PT47 | W10: =IFERROR(VLOOKUP(I10,Guide!A:F,5,FALSE),"") -> 150 | X10: =IFERROR(VLOOKUP(I10,Guide!A:G,6,FALSE),"") -> 520 | AA10: Ceramics | AG10: =L10 -> A3F | AH10: =M10 -> 1D9 | AJ10: Sublimation | AK10: Sublimation | AN10: 1D9 | AO10: =T10 -> 11oz | AP10: CT-6 | AQ10: LG | AR10: N58 | AT10: P | AV10: =M10 -> 1D9 | AW10: =_xlfn.TEXTJOIN("-",TRUE,AQ10:AV10) -> LG-N58-P-1D9 | AX10: =_xlfn.TEXTJOIN("-",TRUE,AS10:AV10) -> P-1D9 | AY10: =E10 -> Two-Tone 11oz Mug – Medium Blue
B11: ds000671s | C11: mdpsupplies | D11: Two-Tone 11oz Mug – Coloured Handle & Inner | E11: Two-Tone 11oz Mug – Cream | F11: =IFERROR(VLOOKUP(I11,Guide!A:B,2,FALSE),"") -> Two-Tone Mug | G11: =A11 -> 0 | H11: =B11 -> ds000671s | I11: PT47 | J11: =IFERROR(VLOOKUP(F11,Values!D:E,2,FALSE),"") -> DAT012 | L11: A3F | M11: 1D10 | N11: 1000000000010 | O11: https://www.mdpsupplies.co.uk/dye-sublimation/dye-sub-two-tone-11oz-mugs | R11: Cream | S11: 11oz | T11: 11oz | V11: =IFERROR(VLOOKUP(I11,Guide!A:D,3,FALSE),"") -> PT47 | W11: =IFERROR(VLOOKUP(I11,Guide!A:F,5,FALSE),"") -> 150 | X11: =IFERROR(VLOOKUP(I11,Guide!A:G,6,FALSE),"") -> 520 | AA11: Ceramics | AG11: =L11 -> A3F | AH11: =M11 -> 1D10 | AJ11: Sublimation | AK11: Sublimation | AN11: 1D10 | AO11: =T11 -> 11oz | AP11: CT-6 | AQ11: LG | AR11: N58 | AT11: P | AV11: =M11 -> 1D10 | AW11: =_xlfn.TEXTJOIN("-",TRUE,AQ11:AV11) -> LG-N58-P-1D10 | AX11: =_xlfn.TEXTJOIN("-",TRUE,AS11:AV11) -> P-1D10 | AY11: =E11 -> Two-Tone 11oz Mug – Cream
B12: ds000672s | C12: mdpsupplies | D12: Two-Tone 11oz Mug – Coloured Handle & Inner | E12: Two-Tone 11oz Mug – Golden Yellow | F12: =IFERROR(VLOOKUP(I12,Guide!A:B,2,FALSE),"") -> Two-Tone Mug | G12: =A12 -> 0 | H12: =B12 -> ds000672s | I12: PT47 | J12: =IFERROR(VLOOKUP(F12,Values!D:E,2,FALSE),"") -> DAT012 | L12: A3F | M12: 1D11 | N12: 1000000000011 | O12: https://www.mdpsupplies.co.uk/dye-sublimation/dye-sub-two-tone-11oz-mugs | R12: Golden Yellow | S12: 11oz | T12: 11oz | V12: =IFERROR(VLOOKUP(I12,Guide!A:D,3,FALSE),"") -> PT47 | W12: =IFERROR(VLOOKUP(I12,Guide!A:F,5,FALSE),"") -> 150 | X12: =IFERROR(VLOOKUP(I12,Guide!A:G,6,FALSE),"") -> 520 | AA12: Ceramics | AG12: =L12 -> A3F | AH12: =M12 -> 1D11 | AJ12: Sublimation | AK12: Sublimation | AN12: 1D11 | AO12: =T12 -> 11oz | AP12: CT-6 | AQ12: LG | AR12: N58 | AT12: P | AV12: =M12 -> 1D11 | AW12: =_xlfn.TEXTJOIN("-",TRUE,AQ12:AV12) -> LG-N58-P-1D11 | AX12: =_xlfn.TEXTJOIN("-",TRUE,AS12:AV12) -> P-1D11 | AY12: =E12 -> Two-Tone 11oz Mug – Golden Yellow
B13: ds000673s | C13: mdpsupplies | D13: Two-Tone 11oz Mug – Coloured Handle & Inner | E13: Two-Tone 11oz Mug – Light Aqua | F13: =IFERROR(VLOOKUP(I13,Guide!A:B,2,FALSE),"") -> Two-Tone Mug | G13: =A13 -> 0 | H13: =B13 -> ds000673s | I13: PT47 | J13: =IFERROR(VLOOKUP(F13,Values!D:E,2,FALSE),"") -> DAT012 | L13: A3F | M13: 1D12 | N13: 1000000000012 | O13: https://www.mdpsupplies.co.uk/dye-sublimation/dye-sub-two-tone-11oz-mugs | R13: Light Aqua | S13: 11oz | T13: 11oz | V13: =IFERROR(VLOOKUP(I13,Guide!A:D,3,FALSE),"") -> PT47 | W13: =IFERROR(VLOOKUP(I13,Guide!A:F,5,FALSE),"") -> 150 | X13: =IFERROR(VLOOKUP(I13,Guide!A:G,6,FALSE),"") -> 520 | AA13: Ceramics | AG13: =L13 -> A3F | AH13: =M13 -> 1D12 | AJ13: Sublimation | AK13: Sublimation | AN13: 1D12 | AO13: =T13 -> 11oz | AP13: CT-6 | AQ13: LG | AR13: N58 | AT13: P | AV13: =M13 -> 1D12 | AW13: =_xlfn.TEXTJOIN("-",TRUE,AQ13:AV13) -> LG-N58-P-1D12 | AX13: =_xlfn.TEXTJOIN("-",TRUE,AS13:AV13) -> P-1D12 | AY13: =E13 -> Two-Tone 11oz Mug – Light Aqua
... B17: DS000315 | C17: mdpsupplies | D17: Two-Tone 11oz Mug – Coloured Handle & Inner | E17: Two-Tone 11oz Mug – White | F17: =IFERROR(VLOOKUP(I17,Guide!A:B,2,FALSE),"") -> Two-Tone Mug | G17: =A17 -> 0 | H17: =B17 -> DS000315 | I17: PT47 | J17: =IFERROR(VLOOKUP(F17,Values!D:E,2,FALSE),"") -> DAT012 | L17: A3F | M17: 1D41 | N17: 1000000000016 | O17: https://www.mdpsupplies.co.uk/dye-sublimation/dye_sublimation_mugs | R17: white | S17: 11oz | T17: 11oz | V17: =IFERROR(VLOOKUP(I17,Guide!A:D,3,FALSE),"") -> PT47 | W17: =IFERROR(VLOOKUP(I17,Guide!A:F,5,FALSE),"") -> 150 | X17: =IFERROR(VLOOKUP(I17,Guide!A:G,6,FALSE),"") -> 520 | AA17: Ceramics | AG17: =L17 -> A3F | AH17: =M17 -> 1D41 | AJ17: Sublimation | AK17: Sublimation | AN17: 1D41 | AO17: =T17 -> 11oz | AP17: CT-6 | AQ17: LG | AR17: N58 | AT17: P | AV17: =M17 -> 1D41 | AW17: =_xlfn.TEXTJOIN("-",TRUE,AQ17:AV17) -> LG-N58-P-1D41 | AX17: =_xlfn.TEXTJOIN("-",TRUE,AS17:AV17) -> P-1D41 | AY17: =E17 -> Two-Tone 11oz Mug – White
B18: Nil | C18: china suppliers | D18: Led lamb Base | E18: LED Lamp – S – 145mm – Acrylic Insert | F18: =IFERROR(VLOOKUP(I18,Guide!A:B,2,FALSE),"") -> LED Base | G18: =A18 -> 0 | H18: =B18 -> Nil | I18: PT251 | J18: =IFERROR(VLOOKUP(F18,Values!D:E,2,FALSE),"") -> DAT013 | L18: A29 | M18: 1D17 | N18: 1000000000017 | O18: https://www.alibaba.com/product-detail/Wholesale-Wooden-Lamp-Stand-Holder-Base_1600921737515.html?spm=a2700.details.you_may_like.1.1fe412d0y1kZlV | R18: Light Brown | S18: 145mm | T18: S | V18: =IFERROR(VLOOKUP(I18,Guide!A:D,3,FALSE),"") -> PT251 | W18: =IFERROR(VLOOKUP(I18,Guide!A:F,5,FALSE),"") -> 0 | X18: =IFERROR(VLOOKUP(I18,Guide!A:G,6,FALSE),"") -> 0 | Y18: Oval | AA18: Wooden | AE18: LED | AF18: 101 - 240V ~ 50/60Hz 0.4A | AG18: =L18 -> A29 | AH18: =M18 -> 1D17 | AJ18: UV | AK18: UV | AN18: 1D17 | AO18: =T18 -> S | AQ18: LG | AT18: P | AV18: =M18 -> 1D17 | AW18: =_xlfn.TEXTJOIN("-",TRUE,AQ18:AV18) -> LG-P-1D17 | AX18: =_xlfn.TEXTJOIN("-",TRUE,AS18:AV18) -> P-1D17 | AY18: =E18 -> LED Lamp – S – 145mm – Acrylic Insert
B19: Nil | C19: china suppliers | D19: Led lamb Base | E19: LED Lamp – M – 150mm – Acrylic Insert | F19: =IFERROR(VLOOKUP(I19,Guide!A:B,2,FALSE),"") -> LED Base | G19: =A19 -> 0 | H19: =B19 -> Nil | I19: PT251 | J19: =IFERROR(VLOOKUP(F19,Values!D:E,2,FALSE),"") -> DAT013 | L19: A29 | M19: 1D18 | N19: 1000000000018 | O19: https://www.alibaba.com/product-detail/Wholesale-Wooden-Lamp-Stand-Holder-Base_1600921737515.html?spm=a2700.details.you_may_like.1.1fe412d0y1kZlV | R19: Light Brown | S19: 150mm | T19: M | V19: =IFERROR(VLOOKUP(I19,Guide!A:D,3,FALSE),"") -> PT251 | W19: =IFERROR(VLOOKUP(I19,Guide!A:F,5,FALSE),"") -> 0 | X19: =IFERROR(VLOOKUP(I19,Guide!A:G,6,FALSE),"") -> 0 | Y19: Rectangle | AA19: Wooden | AE19: LED | AF19: 102 - 240V ~ 50/60Hz 0.4A | AG19: =L19 -> A29 | AH19: =M19 -> 1D18 | AJ19: UV | AK19: UV | AN19: 1D18 | AO19: =T19 -> M | AQ19: LG | AT19: P | AV19: =M19 -> 1D18 | AW19: =_xlfn.TEXTJOIN("-",TRUE,AQ19:AV19) -> LG-P-1D18 | AX19: =_xlfn.TEXTJOIN("-",TRUE,AS19:AV19) -> P-1D18 | AY19: =E19 -> LED Lamp – M – 150mm – Acrylic Insert
B20: Nil | C20: china suppliers | D20: Led lamb Base | E20: LED Lamp – XS – 98mm – Acrylic Insert | F20: =IFERROR(VLOOKUP(I20,Guide!A:B,2,FALSE),"") -> LED Base | G20: =A20 -> 0 | H20: =B20 -> Nil | I20: PT251 | J20: =IFERROR(VLOOKUP(F20,Values!D:E,2,FALSE),"") -> DAT013 | L20: A29 | M20: 1D16 | N20: 1000000000019 | O20: https://www.alibaba.com/product-detail/Wholesale-Wooden-Lamp-Stand-Holder-Base_1600921737515.html?spm=a2700.details.you_may_like.1.1fe412d0y1kZlV | R20: Light Brown | S20: 98mm | T20: XS | V20: =IFERROR(VLOOKUP(I20,Guide!A:D,3,FALSE),"") -> PT251 | W20: =IFERROR(VLOOKUP(I20,Guide!A:F,5,FALSE),"") -> 0 | X20: =IFERROR(VLOOKUP(I20,Guide!A:G,6,FALSE),"") -> 0 | Y20: Round | AA20: Wooden | AE20: LED | AF20: 100 - 240V ~ 50/60Hz 0.4A | AG20: =L20 -> A29 | AH20: =M20 -> 1D16 | AJ20: UV | AK20: UV | AN20: 1D16 | AO20: =T20 -> XS | AQ20: LG | AT20: P | AV20: =M20 -> 1D16 | AW20: =_xlfn.TEXTJOIN("-",TRUE,AQ20:AV20) -> LG-P-1D16 | AX20: =_xlfn.TEXTJOIN("-",TRUE,AS20:AV20) -> P-1D16 | AY20: =E20 -> LED Lamp – XS – 98mm – Acrylic Insert
B21: Nil | C21: china suppliers | D21: Led lamb Base | E21: LED Lamp – L – 200mm – Acrylic Insert | F21: =IFERROR(VLOOKUP(I21,Guide!A:B,2,FALSE),"") -> LED Base | G21: =A21 -> 0 | H21: =B21 -> Nil | I21: PT251 | J21: =IFERROR(VLOOKUP(F21,Values!D:E,2,FALSE),"") -> DAT013 | L21: A29 | M21: 1D19 | N21: 1000000000020 | O21: https://www.alibaba.com/product-detail/Wholesale-Wooden-Lamp-Stand-Holder-Base_1600921737515.html?spm=a2700.details.you_may_like.1.1fe412d0y1kZlV | R21: Light Brown | S21: 200mm | T21: L | V21: =IFERROR(VLOOKUP(I21,Guide!A:D,3,FALSE),"") -> PT251 | W21: =IFERROR(VLOOKUP(I21,Guide!A:F,5,FALSE),"") -> 0 | X21: =IFERROR(VLOOKUP(I21,Guide!A:G,6,FALSE),"") -> 0 | Y21: Rectangle | AA21: Wooden | AE21: LED | AF21: 103 - 240V ~ 50/60Hz 0.4A | AG21: =L21 -> A29 | AH21: =M21 -> 1D19 | AJ21: UV | AK21: UV | AN21: 1D19 | AO21: =T21 -> L | AQ21: LG | AT21: P | AV21: =M21 -> 1D19 | AW21: =_xlfn.TEXTJOIN("-",TRUE,AQ21:AV21) -> LG-P-1D19 | AX21: =_xlfn.TEXTJOIN("-",TRUE,AS21:AV21) -> P-1D19 | AY21: =E21 -> LED Lamp – L – 200mm – Acrylic Insert
B22: Nil | C22: china suppliers | D22: Led lamb Base | E22: LED Lamp – XL – 300mm – Acrylic Insert | F22: =IFERROR(VLOOKUP(I22,Guide!A:B,2,FALSE),"") -> LED Base | G22: =A22 -> 0 | H22: =B22 -> Nil | I22: PT251 | J22: =IFERROR(VLOOKUP(F22,Values!D:E,2,FALSE),"") -> DAT013 | L22: A29 | M22: 1D20 | N22: 1000000000021 | O22: https://www.alibaba.com/product-detail/Wholesale-Wooden-Lamp-Stand-Holder-Base_1600921737515.html?spm=a2700.details.you_may_like.1.1fe412d0y1kZlV | R22: Light Brown | S22: 300mm | T22: XL | V22: =IFERROR(VLOOKUP(I22,Guide!A:D,3,FALSE),"") -> PT251 | W22: =IFERROR(VLOOKUP(I22,Guide!A:F,5,FALSE),"") -> 0 | X22: =IFERROR(VLOOKUP(I22,Guide!A:G,6,FALSE),"") -> 0 | Y22: Rectangle | AA22: Wooden | AE22: LED | AF22: 104 - 240V ~ 50/60Hz 0.4A | AG22: =L22 -> A29 | AH22: =M22 -> 1D20 | AJ22: UV | AK22: UV | AN22: 1D20 | AO22: =T22 -> XL | AQ22: LG | AT22: P | AV22: =M22 -> 1D20 | AW22: =_xlfn.TEXTJOIN("-",TRUE,AQ22:AV22) -> LG-P-1D20 | AX22: =_xlfn.TEXTJOIN("-",TRUE,AS22:AV22) -> P-1D20 | AY22: =E22 -> LED Lamp – XL – 300mm – Acrylic Insert
B23: Nil | C23: Amari Plastics | D23: Clear Acrylic Sheet – 5mm Thick (XS–XL Size Options) | E23: Clear Acrylic – XS – 98mm – 5mm Thick | F23: =IFERROR(VLOOKUP(I23,Guide!A:B,2,FALSE),"") -> Acrylic Clear | G23: =A23 -> 0 | H23: =B23 -> Nil | I23: PT257 | J23: =IFERROR(VLOOKUP(F23,Values!D:E,2,FALSE),"") -> DAT014 | L23: A45 | M23: 1D21 | N23: 1000000000022 | O23: https://plasticexperts.co.uk/5mm-clear-acrylic-sheet-10ftx6-7ft.html | R23: clear | S23: 98mm | T23: XS | V23: =IFERROR(VLOOKUP(I23,Guide!A:D,3,FALSE),"") -> PT257 | W23: =IFERROR(VLOOKUP(I23,Guide!A:F,5,FALSE),"") -> 220 | X23: =IFERROR(VLOOKUP(I23,Guide!A:G,6,FALSE),"") -> 720 | Y23: Rectangle | AA23: Acrylic | AC23: 5mm | AG23: =L23 -> A45 | AH23: =M23 -> 1D21 | AJ23: UV | AK23: Laser Cut/CO₂ Laser Cutting/CO₂ Laser Engraving | AN23: 1D21 | AO23: =T23 -> XS | AP23: CT-1 | AQ23: LG | AR23: N53 | AT23: P | AV23: =M23 -> 1D21 | AW23: =_xlfn.TEXTJOIN("-",TRUE,AQ23:AV23) -> LG-N53-P-1D21 | AX23: =_xlfn.TEXTJOIN("-",TRUE,AS23:AV23) -> P-1D21 | AY23: =E23 -> Clear Acrylic – XS – 98mm – 5mm Thick
B24: Nil | C24: Amari Plastics | D24: Clear Acrylic Sheet – 5mm Thick (XS–XL Size Options) | E24: Clear Acrylic – S – 145mm – 5mm Thick | F24: =IFERROR(VLOOKUP(I24,Guide!A:B,2,FALSE),"") -> Acrylic Clear | G24: =A24 -> 0 | H24: =B24 -> Nil | I24: PT257 | J24: =IFERROR(VLOOKUP(F24,Values!D:E,2,FALSE),"") -> DAT014 | L24: A45 | M24: 1D22 | N24: 1000000000023 | O24: https://plasticexperts.co.uk/5mm-clear-acrylic-sheet-10ftx6-7ft.html | R24: clear | S24: 145mm | T24: S | V24: =IFERROR(VLOOKUP(I24,Guide!A:D,3,FALSE),"") -> PT257 | W24: =IFERROR(VLOOKUP(I24,Guide!A:F,5,FALSE),"") -> 220 | X24: =IFERROR(VLOOKUP(I24,Guide!A:G,6,FALSE),"") -> 720 | Y24: Rectangle | AA24: Acrylic | AC24: 5mm | AG24: =L24 -> A45 | AH24: =M24 -> 1D22 | AJ24: UV | AK24: Laser Cut/CO₂ Laser Cutting/CO₂ Laser Engraving | AN24: 1D22 | AO24: =T24 -> S | AP24: CT-2 | AQ24: LG | AR24: N54 | AT24: P | AV24: =M24 -> 1D22 | AW24: =_xlfn.TEXTJOIN("-",TRUE,AQ24:AV24) -> LG-N54-P-1D22 | AX24: =_xlfn.TEXTJOIN("-",TRUE,AS24:AV24) -> P-1D22 | AY24: =E24 -> Clear Acrylic – S – 145mm – 5mm Thick
B25: Nil | C25: Amari Plastics | D25: Clear Acrylic Sheet – 5mm Thick (XS–XL Size Options) | E25: Clear Acrylic – M – 150mm – 5mm Thick | F25: =IFERROR(VLOOKUP(I25,Guide!A:B,2,FALSE),"") -> Acrylic Clear | G25: =A25 -> 0 | H25: =B25 -> Nil | I25: PT257 | J25: =IFERROR(VLOOKUP(F25,Values!D:E,2,FALSE),"") -> DAT014 | L25: A45 | M25: 1D23 | N25: 1000000000024 | O25: https://plasticexperts.co.uk/5mm-clear-acrylic-sheet-10ftx6-7ft.html | R25: clear | S25: 150mm | T25: M | V25: =IFERROR(VLOOKUP(I25,Guide!A:D,3,FALSE),"") -> PT257 | W25: =IFERROR(VLOOKUP(I25,Guide!A:F,5,FALSE),"") -> 220 | X25: =IFERROR(VLOOKUP(I25,Guide!A:G,6,FALSE),"") -> 720 | Y25: Rectangle | AA25: Acrylic | AC25: 5mm | AG25: =L25 -> A45 | AH25: =M25 -> 1D23 | AJ25: UV | AK25: Laser Cut/CO₂ Laser Cutting/CO₂ Laser Engraving | AN25: 1D23 | AO25: =T25 -> M | AP25: CT-3 | AQ25: LG | AR25: N55 | AT25: P | AV25: =M25 -> 1D23 | AW25: =_xlfn.TEXTJOIN("-",TRUE,AQ25:AV25) -> LG-N55-P-1D23 | AX25: =_xlfn.TEXTJOIN("-",TRUE,AS25:AV25) -> P-1D23 | AY25: =E25 -> Clear Acrylic – M – 150mm – 5mm Thick
B26: Nil | C26: Amari Plastics | D26: Clear Acrylic Sheet – 5mm Thick (XS–XL Size Options) | E26: Clear Acrylic – L – 200mm – 5mm Thick | F26: =IFERROR(VLOOKUP(I26,Guide!A:B,2,FALSE),"") -> Acrylic Clear | G26: =A26 -> 0 | H26: =B26 -> Nil | I26: PT257 | J26: =IFERROR(VLOOKUP(F26,Values!D:E,2,FALSE),"") -> DAT014 | L26: A45 | M26: 1D24 | N26: 1000000000025 | O26: https://plasticexperts.co.uk/5mm-clear-acrylic-sheet-10ftx6-7ft.html | R26: clear | S26: 200mm | T26: L | V26: =IFERROR(VLOOKUP(I26,Guide!A:D,3,FALSE),"") -> PT257 | W26: =IFERROR(VLOOKUP(I26,Guide!A:F,5,FALSE),"") -> 220 | X26: =IFERROR(VLOOKUP(I26,Guide!A:G,6,FALSE),"") -> 720 | Y26: Rectangle | AA26: Acrylic | AC26: 5mm | AG26: =L26 -> A45 | AH26: =M26 -> 1D24 | AJ26: UV | AK26: Laser Cut/CO₂ Laser Cutting/CO₂ Laser Engraving | AN26: 1D24 | AO26: =T26 -> L | AP26: CT-4 | AQ26: LG | AR26: N56 | AT26: P | AV26: =M26 -> 1D24 | AW26: =_xlfn.TEXTJOIN("-",TRUE,AQ26:AV26) -> LG-N56-P-1D24 | AX26: =_xlfn.TEXTJOIN("-",TRUE,AS26:AV26) -> P-1D24 | AY26: =E26 -> Clear Acrylic – L – 200mm – 5mm Thick
B27: Nil | C27: Amari Plastics | D27: Clear Acrylic Sheet – 5mm Thick (XS–XL Size Options) | E27: Clear Acrylic – XL – 300mm – 5mm Thick | F27: =IFERROR(VLOOKUP(I27,Guide!A:B,2,FALSE),"") -> Acrylic Clear | G27: =A27 -> 0 | H27: =B27 -> Nil | I27: PT257 | J27: =IFERROR(VLOOKUP(F27,Values!D:E,2,FALSE),"") -> DAT014 | L27: A45 | M27: 1D25 | N27: 1000000000026 | O27: https://plasticexperts.co.uk/5mm-clear-acrylic-sheet-10ftx6-7ft.html | R27: clear | S27: 300mm | T27: XL | V27: =IFERROR(VLOOKUP(I27,Guide!A:D,3,FALSE),"") -> PT257 | W27: =IFERROR(VLOOKUP(I27,Guide!A:F,5,FALSE),"") -> 220 | X27: =IFERROR(VLOOKUP(I27,Guide!A:G,6,FALSE),"") -> 720 | Y27: Rectangle | AA27: Acrylic | AC27: 5mm | AG27: =L27 -> A45 | AH27: =M27 -> 1D25 | AJ27: UV | AK27: Laser Cut/CO₂ Laser Cutting/CO₂ Laser Engraving | AN27: 1D25 | AO27: =T27 -> XL | AP27: CT-5 | AQ27: LG | AR27: N57 | AT27: P | AV27: =M27 -> 1D25 | AW27: =_xlfn.TEXTJOIN("-",TRUE,AQ27:AV27) -> LG-N57-P-1D25 | AX27: =_xlfn.TEXTJOIN("-",TRUE,AS27:AV27) -> P-1D25 | AY27: =E27 -> Clear Acrylic – XL – 300mm – 5mm Thick
B28: Nil | C28: indian | D28: Acid Washed Heavy Oversized Tee | E28: Acid Wash Vintage Rust | F28: =IFERROR(VLOOKUP(I28,Guide!A:B,2,FALSE),"") -> Acid Washed Heavy Oversized Tee | G28: =A28 -> 0 | H28: =B28 -> Nil | I28: PT2006 | J28: =IFERROR(VLOOKUP(F28,Values!D:E,2,FALSE),"") -> DAT015 | L28: A3G | M28: 1D26 | N28: 1000000000027 | R28: Rust acid wash | T28: S | V28: =IFERROR(VLOOKUP(I28,Guide!A:D,3,FALSE),"") -> PT2006 | W28: =IFERROR(VLOOKUP(I28,Guide!A:F,5,FALSE),"") -> 60 | X28: =IFERROR(VLOOKUP(I28,Guide!A:G,6,FALSE),"") -> 300 | AC28: 260GSM | AG28: =L28 -> A3G | AH28: =M28 -> 1D26 | AJ28: DTF | AN28: 1D26 | AO28: =T28 -> S | AQ28: LG | AT28: P | AV28: =M28 -> 1D26 | AW28: =_xlfn.TEXTJOIN("-",TRUE,AQ28:AV28) -> LG-P-1D26 | AX28: =_xlfn.TEXTJOIN("-",TRUE,AS28:AV28) -> P-1D26 | AY28: =E28 -> Acid Wash Vintage Rust
B29: Nil | C29: indian | D29: Acid Washed Heavy Oversized Tee | E29: Acid Wash Vintage Rust | F29: =IFERROR(VLOOKUP(I29,Guide!A:B,2,FALSE),"") -> Acid Washed Heavy Oversized Tee | G29: =A29 -> 0 | H29: =B29 -> Nil | I29: PT2006 | J29: =IFERROR(VLOOKUP(F29,Values!D:E,2,FALSE),"") -> DAT015 | L29: A3G | M29: 1D27 | N29: 1000000000028 | R29: Rust acid wash | T29: M | V29: =IFERROR(VLOOKUP(I29,Guide!A:D,3,FALSE),"") -> PT2006 | W29: =IFERROR(VLOOKUP(I29,Guide!A:F,5,FALSE),"") -> 60 | X29: =IFERROR(VLOOKUP(I29,Guide!A:G,6,FALSE),"") -> 300 | AC29: 260GSM | AG29: =L29 -> A3G | AH29: =M29 -> 1D27 | AJ29: DTF | AN29: 1D27 | AO29: =T29 -> M | AQ29: LG | AT29: P | AV29: =M29 -> 1D27 | AW29: =_xlfn.TEXTJOIN("-",TRUE,AQ29:AV29) -> LG-P-1D27 | AX29: =_xlfn.TEXTJOIN("-",TRUE,AS29:AV29) -> P-1D27 | AY29: =E29 -> Acid Wash Vintage Rust
B30: Nil | C30: indian | D30: Acid Washed Heavy Oversized Tee | E30: Acid Wash Vintage Rust | F30: =IFERROR(VLOOKUP(I30,Guide!A:B,2,FALSE),"") -> Acid Washed Heavy Oversized Tee | G30: =A30 -> 0 | H30: =B30 -> Nil | I30: PT2006 | J30: =IFERROR(VLOOKUP(F30,Values!D:E,2,FALSE),"") -> DAT015 | L30: A3G | M30: 1D28 | N30: 1000000000029 | R30: Rust acid wash | T30: L | V30: =IFERROR(VLOOKUP(I30,Guide!A:D,3,FALSE),"") -> PT2006 | W30: =IFERROR(VLOOKUP(I30,Guide!A:F,5,FALSE),"") -> 60 | X30: =IFERROR(VLOOKUP(I30,Guide!A:G,6,FALSE),"") -> 300 | AC30: 260GSM | AG30: =L30 -> A3G | AH30: =M30 -> 1D28 | AJ30: DTF | AN30: 1D28 | AO30: =T30 -> L | AQ30: LG | AT30: P | AV30: =M30 -> 1D28 | AW30: =_xlfn.TEXTJOIN("-",TRUE,AQ30:AV30) -> LG-P-1D28 | AX30: =_xlfn.TEXTJOIN("-",TRUE,AS30:AV30) -> P-1D28 | AY30: =E30 -> Acid Wash Vintage Rust
B31: Nil | C31: indian | D31: Acid Washed Heavy Oversized Tee | E31: Acid Wash Vintage Rust | F31: =IFERROR(VLOOKUP(I31,Guide!A:B,2,FALSE),"") -> Acid Washed Heavy Oversized Tee | G31: =A31 -> 0 | H31: =B31 -> Nil | I31: PT2006 | J31: =IFERROR(VLOOKUP(F31,Values!D:E,2,FALSE),"") -> DAT015 | L31: A3G | M31: 1D29 | N31: 1000000000030 | R31: Rust acid wash | T31: XL | V31: =IFERROR(VLOOKUP(I31,Guide!A:D,3,FALSE),"") -> PT2006 | W31: =IFERROR(VLOOKUP(I31,Guide!A:F,5,FALSE),"") -> 60 | X31: =IFERROR(VLOOKUP(I31,Guide!A:G,6,FALSE),"") -> 300 | AC31: 260GSM | AG31: =L31 -> A3G | AH31: =M31 -> 1D29 | AJ31: DTF | AN31: 1D29 | AO31: =T31 -> XL | AQ31: LG | AT31: P | AV31: =M31 -> 1D29 | AW31: =_xlfn.TEXTJOIN("-",TRUE,AQ31:AV31) -> LG-P-1D29 | AX31: =_xlfn.TEXTJOIN("-",TRUE,AS31:AV31) -> P-1D29 | AY31: =E31 -> Acid Wash Vintage Rust
B32: Nil | C32: indian | D32: Acid Washed Heavy Oversized Tee | E32: Acid Wash Vintage Rust | F32: =IFERROR(VLOOKUP(I32,Guide!A:B,2,FALSE),"") -> Acid Washed Heavy Oversized Tee | G32: =A32 -> 0 | H32: =B32 -> Nil | I32: PT2006 | J32: =IFERROR(VLOOKUP(F32,Values!D:E,2,FALSE),"") -> DAT015 | L32: A3G | M32: 1D30 | N32: 1000000000031 | R32: Rust acid wash | T32: 2XL | V32: =IFERROR(VLOOKUP(I32,Guide!A:D,3,FALSE),"") -> PT2006 | W32: =IFERROR(VLOOKUP(I32,Guide!A:F,5,FALSE),"") -> 60 | X32: =IFERROR(VLOOKUP(I32,Guide!A:G,6,FALSE),"") -> 300 | AC32: 260GSM | AG32: =L32 -> A3G | AH32: =M32 -> 1D30 | AJ32: DTF | AN32: 1D30 | AO32: =T32 -> 2XL | AQ32: LG | AT32: P | AV32: =M32 -> 1D30 | AW32: =_xlfn.TEXTJOIN("-",TRUE,AQ32:AV32) -> LG-P-1D30 | AX32: =_xlfn.TEXTJOIN("-",TRUE,AS32:AV32) -> P-1D30 | AY32: =E32 -> Acid Wash Vintage Rust
B33: Nil | C33: indian | D33: Acid Washed Heavy Oversized Tee | E33: Acid Wash Optic Wash | F33: =IFERROR(VLOOKUP(I33,Guide!A:B,2,FALSE),"") -> Acid Washed Heavy Oversized Tee | G33: =A33 -> 0 | H33: =B33 -> Nil | I33: PT2006 | J33: =IFERROR(VLOOKUP(F33,Values!D:E,2,FALSE),"") -> DAT015 | L33: A3G | M33: 1D31 | N33: 1000000000032 | R33: carbon grey | T33: S | V33: =IFERROR(VLOOKUP(I33,Guide!A:D,3,FALSE),"") -> PT2006 | W33: =IFERROR(VLOOKUP(I33,Guide!A:F,5,FALSE),"") -> 60 | X33: =IFERROR(VLOOKUP(I33,Guide!A:G,6,FALSE),"") -> 300 | AC33: 260GSM | AG33: =L33 -> A3G | AH33: =M33 -> 1D31 | AJ33: DTF | AN33: 1D31 | AO33: =T33 -> S | AQ33: LG | AT33: P | AV33: =M33 -> 1D31 | AW33: =_xlfn.TEXTJOIN("-",TRUE,AQ33:AV33) -> LG-P-1D31 | AX33: =_xlfn.TEXTJOIN("-",TRUE,AS33:AV33) -> P-1D31 | AY33: =E33 -> Acid Wash Optic Wash
B34: Nil | C34: indian | D34: Acid Washed Heavy Oversized Tee | E34: Acid Wash Optic Wash | F34: =IFERROR(VLOOKUP(I34,Guide!A:B,2,FALSE),"") -> Acid Washed Heavy Oversized Tee | G34: =A34 -> 0 | H34: =B34 -> Nil | I34: PT2006 | J34: =IFERROR(VLOOKUP(F34,Values!D:E,2,FALSE),"") -> DAT015 | L34: A3G | M34: 1D32 | N34: 1000000000033 | R34: carbon grey | T34: M | V34: =IFERROR(VLOOKUP(I34,Guide!A:D,3,FALSE),"") -> PT2006 | W34: =IFERROR(VLOOKUP(I34,Guide!A:F,5,FALSE),"") -> 60 | X34: =IFERROR(VLOOKUP(I34,Guide!A:G,6,FALSE),"") -> 300 | AC34: 260GSM | AG34: =L34 -> A3G | AH34: =M34 -> 1D32 | AJ34: DTF | AN34: 1D32 | AO34: =T34 -> M | AQ34: LG | AT34: P | AV34: =M34 -> 1D32 | AW34: =_xlfn.TEXTJOIN("-",TRUE,AQ34:AV34) -> LG-P-1D32 | AX34: =_xlfn.TEXTJOIN("-",TRUE,AS34:AV34) -> P-1D32 | AY34: =E34 -> Acid Wash Optic Wash
B35: Nil | C35: indian | D35: Acid Washed Heavy Oversized Tee | E35: Acid Wash Optic Wash | F35: =IFERROR(VLOOKUP(I35,Guide!A:B,2,FALSE),"") -> Acid Washed Heavy Oversized Tee | G35: =A35 -> 0 | H35: =B35 -> Nil | I35: PT2006 | J35: =IFERROR(VLOOKUP(F35,Values!D:E,2,FALSE),"") -> DAT015 | L35: A3G | M35: 1D33 | N35: 1000000000034 | R35: carbon grey | T35: L | V35: =IFERROR(VLOOKUP(I35,Guide!A:D,3,FALSE),"") -> PT2006 | W35: =IFERROR(VLOOKUP(I35,Guide!A:F,5,FALSE),"") -> 60 | X35: =IFERROR(VLOOKUP(I35,Guide!A:G,6,FALSE),"") -> 300 | AC35: 260GSM | AG35: =L35 -> A3G | AH35: =M35 -> 1D33 | AJ35: DTF | AN35: 1D33 | AO35: =T35 -> L | AQ35: LG | AT35: P | AV35: =M35 -> 1D33 | AW35: =_xlfn.TEXTJOIN("-",TRUE,AQ35:AV35) -> LG-P-1D33 | AX35: =_xlfn.TEXTJOIN("-",TRUE,AS35:AV35) -> P-1D33 | AY35: =E35 -> Acid Wash Optic Wash
B36: Nil | C36: indian | D36: Acid Washed Heavy Oversized Tee | E36: Acid Wash Optic Wash | F36: =IFERROR(VLOOKUP(I36,Guide!A:B,2,FALSE),"") -> Acid Washed Heavy Oversized Tee | G36: =A36 -> 0 | H36: =B36 -> Nil | I36: PT2006 | J36: =IFERROR(VLOOKUP(F36,Values!D:E,2,FALSE),"") -> DAT015 | L36: A3G | M36: 1D34 | N36: 1000000000035 | R36: carbon grey | T36: XL | V36: =IFERROR(VLOOKUP(I36,Guide!A:D,3,FALSE),"") -> PT2006 | W36: =IFERROR(VLOOKUP(I36,Guide!A:F,5,FALSE),"") -> 60 | X36: =IFERROR(VLOOKUP(I36,Guide!A:G,6,FALSE),"") -> 300 | AC36: 260GSM | AG36: =L36 -> A3G | AH36: =M36 -> 1D34 | AJ36: DTF | AN36: 1D34 | AO36: =T36 -> XL | AQ36: LG | AT36: P | AV36: =M36 -> 1D34 | AW36: =_xlfn.TEXTJOIN("-",TRUE,AQ36:AV36) -> LG-P-1D34 | AX36: =_xlfn.TEXTJOIN("-",TRUE,AS36:AV36) -> P-1D34 | AY36: =E36 -> Acid Wash Optic Wash
B37: Nil | C37: indian | D37: Acid Washed Heavy Oversized Tee | E37: Acid Wash Optic Wash | F37: =IFERROR(VLOOKUP(I37,Guide!A:B,2,FALSE),"") -> Acid Washed Heavy Oversized Tee | G37: =A37 -> 0 | H37: =B37 -> Nil | I37: PT2006 | J37: =IFERROR(VLOOKUP(F37,Values!D:E,2,FALSE),"") -> DAT015 | L37: A3G | M37: 1D35 | N37: 1000000000036 | R37: carbon grey | T37: 2XL | V37: =IFERROR(VLOOKUP(I37,Guide!A:D,3,FALSE),"") -> PT2006 | W37: =IFERROR(VLOOKUP(I37,Guide!A:F,5,FALSE),"") -> 60 | X37: =IFERROR(VLOOKUP(I37,Guide!A:G,6,FALSE),"") -> 300 | AC37: 260GSM | AG37: =L37 -> A3G | AH37: =M37 -> 1D35 | AJ37: DTF | AN37: 1D35 | AO37: =T37 -> 2XL | AQ37: LG | AT37: P | AV37: =M37 -> 1D35 | AW37: =_xlfn.TEXTJOIN("-",TRUE,AQ37:AV37) -> LG-P-1D35 | AX37: =_xlfn.TEXTJOIN("-",TRUE,AS37:AV37) -> P-1D35 | AY37: =E37 -> Acid Wash Optic Wash
B38: Nil | C38: china+Amari Plastics | D38: LED Acrylic Block Light – Acrylic Block with LED Base (XS–XL Sizes) | E38: Acrylic Block with LED Base – XS – 98mm – 5mm Thick | F38: =IFERROR(VLOOKUP(I38,Guide!A:B,2,FALSE),"") -> Acrylic Block with LED Base | G38: =A38 -> 0 | H38: =B38 -> Nil | I38: PT2628 | J38: =IFERROR(VLOOKUP(F38,Values!D:E,2,FALSE),"") -> DAT016 | L38: A30 | M38: 1D42 | N38: 1000000000037 | O38: https://www.alibaba.com/product-detail/Wholesale-Wooden-Lamp-Stand-Holder-Base_1600921737515.html?spm=a2700.details.you_may_like.1.1fe412d0y1kZlV | R38: Light Brown | S38: 98mm | T38: XS | V38: =IFERROR(VLOOKUP(I38,Guide!A:D,3,FALSE),"") -> PT2628 | W38: =IFERROR(VLOOKUP(I38,Guide!A:F,5,FALSE),"") -> 250 | X38: =IFERROR(VLOOKUP(I38,Guide!A:G,6,FALSE),"") -> 850 | Y38: Round | AA38: Wooden | AE38: LED | AF38: 100 - 240V ~ 50/60Hz 0.4A | AG38: =L38 -> A30 | AH38: =M38 -> 1D42 | AI38: A29-A45 | AJ38: UV | AK38: Laser Cut/CO₂ Laser Cutting/CO₂ Laser Engraving | AN38: 1D42 | AO38: =T38 -> XS | AP38: CT-1 | AQ38: LG | AR38: N53 | AT38: P | AV38: =M38 -> 1D42 | AW38: =_xlfn.TEXTJOIN("-",TRUE,AQ38:AV38) -> LG-N53-P-1D42 | AX38: =_xlfn.TEXTJOIN("-",TRUE,AS38:AV38) -> P-1D42 | AY38: =E38 -> Acrylic Block with LED Base – XS – 98mm – 5mm Thick
B39: Nil | C39: china+Amari Plastics | D39: LED Acrylic Block Light – Acrylic Block with LED Base (XS–XL Sizes) | E39: Acrylic Block with LED Base – S – 145mm – 5mm Thick | F39: =IFERROR(VLOOKUP(I39,Guide!A:B,2,FALSE),"") -> Acrylic Block with LED Base | G39: =A39 -> 0 | H39: =B39 -> Nil | I39: PT2628 | J39: =IFERROR(VLOOKUP(F39,Values!D:E,2,FALSE),"") -> DAT016 | L39: A30 | M39: 1D43 | N39: 1000000000038 | O39: https://www.alibaba.com/product-detail/Wholesale-Wooden-Lamp-Stand-Holder-Base_1600921737515.html?spm=a2700.details.you_may_like.1.1fe412d0y1kZlV | R39: Light Brown | S39: 145mm | T39: S | V39: =IFERROR(VLOOKUP(I39,Guide!A:D,3,FALSE),"") -> PT2628 | W39: =IFERROR(VLOOKUP(I39,Guide!A:F,5,FALSE),"") -> 250 | X39: =IFERROR(VLOOKUP(I39,Guide!A:G,6,FALSE),"") -> 850 | Y39: Oval | AA39: Wooden | AE39: LED | AF39: 101 - 240V ~ 50/60Hz 0.4A | AG39: =L39 -> A30 | AH39: =M39 -> 1D43 | AI39: A29-A46 | AJ39: UV | AK39: Laser Cut/CO₂ Laser Cutting/CO₂ Laser Engraving | AN39: 1D43 | AO39: =T39 -> S | AP39: CT-2 | AQ39: LG | AR39: N54 | AT39: P | AV39: =M39 -> 1D43 | AW39: =_xlfn.TEXTJOIN("-",TRUE,AQ39:AV39) -> LG-N54-P-1D43 | AX39: =_xlfn.TEXTJOIN("-",TRUE,AS39:AV39) -> P-1D43 | AY39: =E39 -> Acrylic Block with LED Base – S – 145mm – 5mm Thick
B40: Nil | C40: china+Amari Plastics | D40: LED Acrylic Block Light – Acrylic Block with LED Base (XS–XL Sizes) | E40: Acrylic Block with LED Base – M – 150mm – 5mm Thick | F40: =IFERROR(VLOOKUP(I40,Guide!A:B,2,FALSE),"") -> Acrylic Block with LED Base | G40: =A40 -> 0 | H40: =B40 -> Nil | I40: PT2628 | J40: =IFERROR(VLOOKUP(F40,Values!D:E,2,FALSE),"") -> DAT016 | L40: A30 | M40: 1D44 | N40: 1000000000039 | O40: https://www.alibaba.com/product-detail/Wholesale-Wooden-Lamp-Stand-Holder-Base_1600921737515.html?spm=a2700.details.you_may_like.1.1fe412d0y1kZlV | R40: Light Brown | S40: 150mm | T40: M | V40: =IFERROR(VLOOKUP(I40,Guide!A:D,3,FALSE),"") -> PT2628 | W40: =IFERROR(VLOOKUP(I40,Guide!A:F,5,FALSE),"") -> 250 | X40: =IFERROR(VLOOKUP(I40,Guide!A:G,6,FALSE),"") -> 850 | Y40: Rectangle | AA40: Wooden | AE40: LED | AF40: 102 - 240V ~ 50/60Hz 0.4A | AG40: =L40 -> A30 | AH40: =M40 -> 1D44 | AI40: A29-A47 | AJ40: UV | AK40: Laser Cut/CO₂ Laser Cutting/CO₂ Laser Engraving | AN40: 1D44 | AO40: =T40 -> M | AP40: CT-3 | AQ40: LG | AR40: N55 | AT40: P | AV40: =M40 -> 1D44 | AW40: =_xlfn.TEXTJOIN("-",TRUE,AQ40:AV40) -> LG-N55-P-1D44 | AX40: =_xlfn.TEXTJOIN("-",TRUE,AS40:AV40) -> P-1D44 | AY40: =E40 -> Acrylic Block with LED Base – M – 150mm – 5mm Thick
B41: Nil | C41: china+Amari Plastics | D41: LED Acrylic Block Light – Acrylic Block with LED Base (XS–XL Sizes) | E41: Acrylic Block with LED Base – L – 200mm – 5mm Thick | F41: =IFERROR(VLOOKUP(I41,Guide!A:B,2,FALSE),"") -> Acrylic Block with LED Base | G41: =A41 -> 0 | H41: =B41 -> Nil | I41: PT2628 | J41: =IFERROR(VLOOKUP(F41,Values!D:E,2,FALSE),"") -> DAT016 | L41: A30 | M41: 1D45 | N41: 1000000000040 | O41: https://www.alibaba.com/product-detail/Wholesale-Wooden-Lamp-Stand-Holder-Base_1600921737515.html?spm=a2700.details.you_may_like.1.1fe412d0y1kZlV | R41: Light Brown | S41: 200mm | T41: L | V41: =IFERROR(VLOOKUP(I41,Guide!A:D,3,FALSE),"") -> PT2628 | W41: =IFERROR(VLOOKUP(I41,Guide!A:F,5,FALSE),"") -> 250 | X41: =IFERROR(VLOOKUP(I41,Guide!A:G,6,FALSE),"") -> 850 | Y41: Rectangle | AA41: Wooden | AE41: LED | AF41: 103 - 240V ~ 50/60Hz 0.4A | AG41: =L41 -> A30 | AH41: =M41 -> 1D45 | AI41: A29-A48 | AJ41: UV | AK41: Laser Cut/CO₂ Laser Cutting/CO₂ Laser Engraving | AN41: 1D45 | AO41: =T41 -> L | AP41: CT-4 | AQ41: LG | AR41: N56 | AT41: P | AV41: =M41 -> 1D45 | AW41: =_xlfn.TEXTJOIN("-",TRUE,AQ41:AV41) -> LG-N56-P-1D45 | AX41: =_xlfn.TEXTJOIN("-",TRUE,AS41:AV41) -> P-1D45 | AY41: =E41 -> Acrylic Block with LED Base – L – 200mm – 5mm Thick
B42: Nil | C42: china+Amari Plastics | D42: LED Acrylic Block Light – Acrylic Block with LED Base (XS–XL Sizes) | E42: Acrylic Block with LED Base – XL – 300mm – 5mm Thick | F42: =IFERROR(VLOOKUP(I42,Guide!A:B,2,FALSE),"") -> Acrylic Block with LED Base | G42: =A42 -> 0 | H42: =B42 -> Nil | I42: PT2628 | J42: =IFERROR(VLOOKUP(F42,Values!D:E,2,FALSE),"") -> DAT016 | L42: A30 | M42: 1D46 | N42: 1000000000041 | O42: https://www.alibaba.com/product-detail/Wholesale-Wooden-Lamp-Stand-Holder-Base_1600921737515.html?spm=a2700.details.you_may_like.1.1fe412d0y1kZlV | R42: Light Brown | S42: 300mm | T42: XL | V42: =IFERROR(VLOOKUP(I42,Guide!A:D,3,FALSE),"") -> PT2628 | W42: =IFERROR(VLOOKUP(I42,Guide!A:F,5,FALSE),"") -> 250 | X42: =IFERROR(VLOOKUP(I42,Guide!A:G,6,FALSE),"") -> 850 | Y42: Rectangle | AA42: Wooden | AE42: LED | AF42: 104 - 240V ~ 50/60Hz 0.4A | AG42: =L42 -> A30 | AH42: =M42 -> 1D46 | AI42: A29-A49 | AJ42: UV | AK42: Laser Cut/CO₂ Laser Cutting/CO₂ Laser Engraving | AN42: 1D46 | AO42: =T42 -> XL | AP42: CT-5 | AQ42: LG | AR42: N57 | AT42: P | AV42: =M42 -> 1D46 | AW42: =_xlfn.TEXTJOIN("-",TRUE,AQ42:AV42) -> LG-N57-P-1D46 | AX42: =_xlfn.TEXTJOIN("-",TRUE,AS42:AV42) -> P-1D46 | AY42: =E42 -> Acrylic Block with LED Base – XL – 300mm – 5mm Thick
B43: DSA000100 | C43: mdpsupplies | D43: Aluminium Sheets | E43: Dye Sub Aluminium White | F43: =IFERROR(VLOOKUP(I43,Guide!A:B,2,FALSE),"") -> Dye Sublimation Aluminium Sheets | G43: =A43 -> 0 | H43: =B43 -> DSA000100 | I43: PT254 | J43: =IFERROR(VLOOKUP(F43,Values!D:E,2,FALSE),"") -> DAT017 | L43: A31 | M43: 1D36 | N43: 1000000000042 | O43: https://www.mdpsupplies.co.uk/dye-sublimation/dye_sublimation_aluminium_sheets | R43: White | S43: 305 x 305mm | T43: O/S | V43: =IFERROR(VLOOKUP(I43,Guide!A:D,3,FALSE),"") -> PT254 | W43: =IFERROR(VLOOKUP(I43,Guide!A:F,5,FALSE),"") -> 0 | X43: =IFERROR(VLOOKUP(I43,Guide!A:G,6,FALSE),"") -> 0 | Y43: Square | AA43: Aluminium Sheets | AD43: 0.45mm | AG43: =L43 -> A31 | AH43: =M43 -> 1D36 | AN43: 1D36 | AO43: =T43 -> O/S | AQ43: LG | AT43: P | AV43: =M43 -> 1D36 | AW43: =_xlfn.TEXTJOIN("-",TRUE,AQ43:AV43) -> LG-P-1D36 | AX43: =_xlfn.TEXTJOIN("-",TRUE,AS43:AV43) -> P-1D36 | AY43: =E43 -> Dye Sub Aluminium White
B44: DSA000130 | C44: mdpsupplies | D44: Aluminium Sheets | E44: Dye Sub Aluminium Gloss Silver | F44: =IFERROR(VLOOKUP(I44,Guide!A:B,2,FALSE),"") -> Dye Sublimation Aluminium Sheets | G44: =A44 -> 0 | H44: =B44 -> DSA000130 | I44: PT254 | J44: =IFERROR(VLOOKUP(F44,Values!D:E,2,FALSE),"") -> DAT017 | L44: A31 | M44: 1D37 | N44: 1000000000043 | O44: https://www.mdpsupplies.co.uk/dye-sublimation/dye_sublimation_aluminium_sheets | R44: Gloss Silver | S44: 305 x 305mm | T44: O/S | V44: =IFERROR(VLOOKUP(I44,Guide!A:D,3,FALSE),"") -> PT254 | W44: =IFERROR(VLOOKUP(I44,Guide!A:F,5,FALSE),"") -> 0 | X44: =IFERROR(VLOOKUP(I44,Guide!A:G,6,FALSE),"") -> 0 | Y44: Square | AA44: Aluminium Sheets | AD44: 0.45mm | AG44: =L44 -> A31 | AH44: =M44 -> 1D37 | AN44: 1D37 | AO44: =T44 -> O/S | AQ44: LG | AT44: P | AV44: =M44 -> 1D37 | AW44: =_xlfn.TEXTJOIN("-",TRUE,AQ44:AV44) -> LG-P-1D37 | AX44: =_xlfn.TEXTJOIN("-",TRUE,AS44:AV44) -> P-1D37 | AY44: =E44 -> Dye Sub Aluminium Gloss Silver
B45: DSA000140 | C45: mdpsupplies | D45: Aluminium Sheets | E45: Dye Sub Aluminium Gloss Gold | F45: =IFERROR(VLOOKUP(I45,Guide!A:B,2,FALSE),"") -> Dye Sublimation Aluminium Sheets | G45: =A45 -> 0 | H45: =B45 -> DSA000140 | I45: PT254 | J45: =IFERROR(VLOOKUP(F45,Values!D:E,2,FALSE),"") -> DAT017 | L45: A31 | M45: 1D38 | N45: 1000000000044 | O45: https://www.mdpsupplies.co.uk/dye-sublimation/dye_sublimation_aluminium_sheets | R45: Gloss Gold | S45: 305 x 305mm | T45: O/S | V45: =IFERROR(VLOOKUP(I45,Guide!A:D,3,FALSE),"") -> PT254 | W45: =IFERROR(VLOOKUP(I45,Guide!A:F,5,FALSE),"") -> 0 | X45: =IFERROR(VLOOKUP(I45,Guide!A:G,6,FALSE),"") -> 0 | Y45: Square | AA45: Aluminium Sheets | AD45: 0.45mm | AG45: =L45 -> A31 | AH45: =M45 -> 1D38 | AN45: 1D38 | AO45: =T45 -> O/S | AQ45: LG | AT45: P | AV45: =M45 -> 1D38 | AW45: =_xlfn.TEXTJOIN("-",TRUE,AQ45:AV45) -> LG-P-1D38 | AX45: =_xlfn.TEXTJOIN("-",TRUE,AS45:AV45) -> P-1D38 | AY45: =E45 -> Dye Sub Aluminium Gloss Gold
B46: DSA000110 | C46: mdpsupplies | D46: Aluminium Sheets | E46: Dye Sub Aluminium Brushed Silver | F46: =IFERROR(VLOOKUP(I46,Guide!A:B,2,FALSE),"") -> Dye Sublimation Aluminium Sheets | G46: =A46 -> 0 | H46: =B46 -> DSA000110 | I46: PT254 | J46: =IFERROR(VLOOKUP(F46,Values!D:E,2,FALSE),"") -> DAT017 | L46: A31 | M46: 1D39 | N46: 1000000000045 | O46: https://www.mdpsupplies.co.uk/dye-sublimation/dye_sublimation_aluminium_sheets | R46: Brushed Silver | S46: 305 x 305mm | T46: O/S | V46: =IFERROR(VLOOKUP(I46,Guide!A:D,3,FALSE),"") -> PT254 | W46: =IFERROR(VLOOKUP(I46,Guide!A:F,5,FALSE),"") -> 0 | X46: =IFERROR(VLOOKUP(I46,Guide!A:G,6,FALSE),"") -> 0 | Y46: Square | AA46: Aluminium Sheets | AD46: 0.45mm | AG46: =L46 -> A31 | AH46: =M46 -> 1D39 | AN46: 1D39 | AO46: =T46 -> O/S | AQ46: LG | AT46: P | AV46: =M46 -> 1D39 | AW46: =_xlfn.TEXTJOIN("-",TRUE,AQ46:AV46) -> LG-P-1D39 | AX46: =_xlfn.TEXTJOIN("-",TRUE,AS46:AV46) -> P-1D39 | AY46: =E46 -> Dye Sub Aluminium Brushed Silver
B47: DSA000120 | C47: mdpsupplies | D47: Aluminium Sheets | E47: Dye Sub Aluminium Brushed Gold | F47: =IFERROR(VLOOKUP(I47,Guide!A:B,2,FALSE),"") -> Dye Sublimation Aluminium Sheets | G47: =A47 -> 0 | H47: =B47 -> DSA000120 | I47: PT254 | J47: =IFERROR(VLOOKUP(F47,Values!D:E,2,FALSE),"") -> DAT017 | L47: A31 | M47: 1D40 | N47: 1000000000046 | O47: https://www.mdpsupplies.co.uk/dye-sublimation/dye_sublimation_aluminium_sheets | R47: Brushed Gold | S47: 305 x 305mm | T47: O/S | V47: =IFERROR(VLOOKUP(I47,Guide!A:D,3,FALSE),"") -> PT254 | W47: =IFERROR(VLOOKUP(I47,Guide!A:F,5,FALSE),"") -> 0 | X47: =IFERROR(VLOOKUP(I47,Guide!A:G,6,FALSE),"") -> 0 | Y47: Square | AA47: Aluminium Sheets | AD47: 0.45mm | AG47: =L47 -> A31 | AH47: =M47 -> 1D40 | AN47: 1D40 | AO47: =T47 -> O/S | AQ47: LG | AT47: P | AV47: =M47 -> 1D40 | AW47: =_xlfn.TEXTJOIN("-",TRUE,AQ47:AV47) -> LG-P-1D40 | AX47: =_xlfn.TEXTJOIN("-",TRUE,AS47:AV47) -> P-1D40 | AY47: =E47 -> Dye Sub Aluminium Brushed Gold
B48: DSB000100 | C48: mdpsupplies | D48: Bottle Openers | E48: Long Metal Brushed | F48: =IFERROR(VLOOKUP(I48,Guide!A:B,2,FALSE),"") -> Wooden Bottle Opener | G48: =A48 -> 0 | H48: =B48 -> DSB000100 | I48: PT1827 | J48: DAT018 | L48: A32 | M48: 1D47 | N48: 1000000000047 | O48: https://www.mdpsupplies.co.uk/dye-sublimation/dye_sublimation_bottle_openers | V48: =IFERROR(VLOOKUP(I48,Guide!A:D,3,FALSE),"") -> PT1827 | W48: =IFERROR(VLOOKUP(I48,Guide!A:F,5,FALSE),"") -> 0 | X48: =IFERROR(VLOOKUP(I48,Guide!A:G,6,FALSE),"") -> 0 | AG48: =L48 -> A32 | AH48: =M48 -> 1D47 | AN48: 1D47 | AO48: =T48 -> 0 | AQ48: LG | AT48: P | AV48: =M48 -> 1D47 | AW48: =_xlfn.TEXTJOIN("-",TRUE,AQ48:AV48) -> LG-P-1D47 | AX48: =_xlfn.TEXTJOIN("-",TRUE,AS48:AV48) -> P-1D47 | AY48: =E48 -> Long Metal Brushed
B49: DSB000110 | C49: mdpsupplies | D49: Bottle Openers | E49: Rectangular Metal Brushed | F49: =IFERROR(VLOOKUP(I49,Guide!A:B,2,FALSE),"") -> Wooden Bottle Opener | G49: =A49 -> 0 | H49: =B49 -> DSB000110 | I49: PT1827 | J49: DAT018 | L49: A32 | M49: 1D48 | N49: 1000000000048 | O49: https://www.mdpsupplies.co.uk/dye-sublimation/dye_sublimation_bottle_openers | V49: =IFERROR(VLOOKUP(I49,Guide!A:D,3,FALSE),"") -> PT1827 | W49: =IFERROR(VLOOKUP(I49,Guide!A:F,5,FALSE),"") -> 0 | X49: =IFERROR(VLOOKUP(I49,Guide!A:G,6,FALSE),"") -> 0 | AG49: =L49 -> A32 | AH49: =M49 -> 1D48 | AN49: 1D48 | AO49: =T49 -> 0 | AQ49: LG | AT49: P | AV49: =M49 -> 1D48 | AW49: =_xlfn.TEXTJOIN("-",TRUE,AQ49:AV49) -> LG-P-1D48 | AX49: =_xlfn.TEXTJOIN("-",TRUE,AS49:AV49) -> P-1D48 | AY49: =E49 -> Rectangular Metal Brushed
B50: DSB000120 | C50: mdpsupplies | D50: Bottle Openers | E50: Long Metal White | F50: =IFERROR(VLOOKUP(I50,Guide!A:B,2,FALSE),"") -> Wooden Bottle Opener | G50: =A50 -> 0 | H50: =B50 -> DSB000120 | I50: PT1827 | J50: DAT018 | L50: A32 | M50: 1D49 | N50: 1000000000049 | O50: https://www.mdpsupplies.co.uk/dye-sublimation/dye_sublimation_bottle_openers | V50: =IFERROR(VLOOKUP(I50,Guide!A:D,3,FALSE),"") -> PT1827 | W50: =IFERROR(VLOOKUP(I50,Guide!A:F,5,FALSE),"") -> 0 | X50: =IFERROR(VLOOKUP(I50,Guide!A:G,6,FALSE),"") -> 0 | AG50: =L50 -> A32 | AH50: =M50 -> 1D49 | AN50: 1D49 | AO50: =T50 -> 0 | AQ50: LG | AT50: P | AV50: =M50 -> 1D49 | AW50: =_xlfn.TEXTJOIN("-",TRUE,AQ50:AV50) -> LG-P-1D49 | AX50: =_xlfn.TEXTJOIN("-",TRUE,AS50:AV50) -> P-1D49 | AY50: =E50 -> Long Metal White
B51: DSB000160 | C51: mdpsupplies | D51: Bottle Openers | E51: Rectangular White | F51: =IFERROR(VLOOKUP(I51,Guide!A:B,2,FALSE),"") -> Wooden Bottle Opener | G51: =A51 -> 0 | H51: =B51 -> DSB000160 | I51: PT1827 | J51: DAT018 | L51: A32 | M51: 1D50 | N51: 1000000000050 | O51: https://www.mdpsupplies.co.uk/dye-sublimation/dye_sublimation_bottle_openers | V51: =IFERROR(VLOOKUP(I51,Guide!A:D,3,FALSE),"") -> PT1827 | W51: =IFERROR(VLOOKUP(I51,Guide!A:F,5,FALSE),"") -> 0 | X51: =IFERROR(VLOOKUP(I51,Guide!A:G,6,FALSE),"") -> 0 | AG51: =L51 -> A32 | AH51: =M51 -> 1D50 | AN51: 1D50 | AO51: =T51 -> 0 | AQ51: LG | AT51: P | AV51: =M51 -> 1D50 | AW51: =_xlfn.TEXTJOIN("-",TRUE,AQ51:AV51) -> LG-P-1D50 | AX51: =_xlfn.TEXTJOIN("-",TRUE,AS51:AV51) -> P-1D50 | AY51: =E51 -> Rectangular White
B52: DSB000130 | C52: mdpsupplies | D52: Bottle Openers | E52: Leatherette White | F52: =IFERROR(VLOOKUP(I52,Guide!A:B,2,FALSE),"") -> Wooden Bottle Opener | G52: =A52 -> 0 | H52: =B52 -> DSB000130 | I52: PT1827 | J52: DAT018 | L52: A32 | M52: 1D51 | N52: 1000000000051 | O52: https://www.mdpsupplies.co.uk/dye-sublimation/dye_sublimation_bottle_openers | V52: =IFERROR(VLOOKUP(I52,Guide!A:D,3,FALSE),"") -> PT1827 | W52: =IFERROR(VLOOKUP(I52,Guide!A:F,5,FALSE),"") -> 0 | X52: =IFERROR(VLOOKUP(I52,Guide!A:G,6,FALSE),"") -> 0 | AG52: =L52 -> A32 | AH52: =M52 -> 1D51 | AN52: 1D51 | AO52: =T52 -> 0 | AQ52: LG | AT52: P | AV52: =M52 -> 1D51 | AW52: =_xlfn.TEXTJOIN("-",TRUE,AQ52:AV52) -> LG-P-1D51 | AX52: =_xlfn.TEXTJOIN("-",TRUE,AS52:AV52) -> P-1D51 | AY52: =E52 -> Leatherette White
B53: DSB000140 | C53: mdpsupplies | D53: Bottle Openers | E53: Leatherette Brown | F53: =IFERROR(VLOOKUP(I53,Guide!A:B,2,FALSE),"") -> Wooden Bottle Opener | G53: =A53 -> 0 | H53: =B53 -> DSB000140 | I53: PT1827 | J53: DAT018 | L53: A32 | M53: 1D52 | N53: 1000000000052 | O53: https://www.mdpsupplies.co.uk/dye-sublimation/dye_sublimation_bottle_openers | V53: =IFERROR(VLOOKUP(I53,Guide!A:D,3,FALSE),"") -> PT1827 | W53: =IFERROR(VLOOKUP(I53,Guide!A:F,5,FALSE),"") -> 0 | X53: =IFERROR(VLOOKUP(I53,Guide!A:G,6,FALSE),"") -> 0 | AG53: =L53 -> A32 | AH53: =M53 -> 1D52 | AN53: 1D52 | AO53: =T53 -> 0 | AQ53: LG | AT53: P | AV53: =M53 -> 1D52 | AW53: =_xlfn.TEXTJOIN("-",TRUE,AQ53:AV53) -> LG-P-1D52 | AX53: =_xlfn.TEXTJOIN("-",TRUE,AS53:AV53) -> P-1D52 | AY53: =E53 -> Leatherette Brown
B54: DSB000150 | C54: mdpsupplies | D54: Bottle Openers | E54: Leatherette Pink | F54: =IFERROR(VLOOKUP(I54,Guide!A:B,2,FALSE),"") -> Wooden Bottle Opener | G54: =A54 -> 0 | H54: =B54 -> DSB000150 | I54: PT1827 | J54: DAT018 | L54: A32 | M54: 1D53 | N54: 1000000000053 | O54: https://www.mdpsupplies.co.uk/dye-sublimation/dye_sublimation_bottle_openers | V54: =IFERROR(VLOOKUP(I54,Guide!A:D,3,FALSE),"") -> PT1827 | W54: =IFERROR(VLOOKUP(I54,Guide!A:F,5,FALSE),"") -> 0 | X54: =IFERROR(VLOOKUP(I54,Guide!A:G,6,FALSE),"") -> 0 | AG54: =L54 -> A32 | AH54: =M54 -> 1D53 | AN54: 1D53 | AO54: =T54 -> 0 | AQ54: LG | AT54: P | AV54: =M54 -> 1D53 | AW54: =_xlfn.TEXTJOIN("-",TRUE,AQ54:AV54) -> LG-P-1D53 | AX54: =_xlfn.TEXTJOIN("-",TRUE,AS54:AV54) -> P-1D53 | AY54: =E54 -> Leatherette Pink
B55: DSC000100 | C55: mdpsupplies | D55: Coasters | E55: Wooden Square | F55: =IFERROR(VLOOKUP(I55,Guide!A:B,2,FALSE),"") -> Coasters | G55: =A55 -> 0 | H55: =B55 -> DSC000100 | I55: PT256 | J55: DAT019 | L55: A33 | M55: 1D54 | N55: 1000000000054 | O55: https://www.mdpsupplies.co.uk/dye-sublimation/dye_sublimation_coasters | V55: =IFERROR(VLOOKUP(I55,Guide!A:D,3,FALSE),"") -> PT256 | W55: =IFERROR(VLOOKUP(I55,Guide!A:F,5,FALSE),"") -> 40 | X55: =IFERROR(VLOOKUP(I55,Guide!A:G,6,FALSE),"") -> 150 | AG55: =L55 -> A33 | AH55: =M55 -> 1D54 | AN55: 1D54 | AO55: =T55 -> 0 | AQ55: LG | AT55: P | AV55: =M55 -> 1D54 | AW55: =_xlfn.TEXTJOIN("-",TRUE,AQ55:AV55) -> LG-P-1D54 | AX55: =_xlfn.TEXTJOIN("-",TRUE,AS55:AV55) -> P-1D54 | AY55: =E55 -> Wooden Square
B56: DSC000110 | C56: mdpsupplies | D56: Coasters | E56: Wooden Round | F56: =IFERROR(VLOOKUP(I56,Guide!A:B,2,FALSE),"") -> Coasters | G56: =A56 -> 0 | H56: =B56 -> DSC000110 | I56: PT256 | J56: DAT019 | L56: A33 | M56: 1D55 | N56: 1000000000055 | O56: https://www.mdpsupplies.co.uk/dye-sublimation/dye_sublimation_coasters | V56: =IFERROR(VLOOKUP(I56,Guide!A:D,3,FALSE),"") -> PT256 | W56: =IFERROR(VLOOKUP(I56,Guide!A:F,5,FALSE),"") -> 40 | X56: =IFERROR(VLOOKUP(I56,Guide!A:G,6,FALSE),"") -> 150 | AG56: =L56 -> A33 | AH56: =M56 -> 1D55 | AN56: 1D55 | AO56: =T56 -> 0 | AQ56: LG | AT56: P | AV56: =M56 -> 1D55 | AW56: =_xlfn.TEXTJOIN("-",TRUE,AQ56:AV56) -> LG-P-1D55 | AX56: =_xlfn.TEXTJOIN("-",TRUE,AS56:AV56) -> P-1D55 | AY56: =E56 -> Wooden Round
B57: DSC000150 | C57: mdpsupplies | D57: Coasters | E57: Polymer Square with Cork | F57: =IFERROR(VLOOKUP(I57,Guide!A:B,2,FALSE),"") -> Coasters | G57: =A57 -> 0 | H57: =B57 -> DSC000150 | I57: PT256 | J57: DAT019 | L57: A33 | M57: 1D56 | N57: 1000000000056 | O57: https://www.mdpsupplies.co.uk/dye-sublimation/dye_sublimation_coasters | V57: =IFERROR(VLOOKUP(I57,Guide!A:D,3,FALSE),"") -> PT256 | W57: =IFERROR(VLOOKUP(I57,Guide!A:F,5,FALSE),"") -> 40 | X57: =IFERROR(VLOOKUP(I57,Guide!A:G,6,FALSE),"") -> 150 | AG57: =L57 -> A33 | AH57: =M57 -> 1D56 | AN57: 1D56 | AO57: =T57 -> 0 | AQ57: LG | AT57: P | AV57: =M57 -> 1D56 | AW57: =_xlfn.TEXTJOIN("-",TRUE,AQ57:AV57) -> LG-P-1D56 | AX57: =_xlfn.TEXTJOIN("-",TRUE,AS57:AV57) -> P-1D56 | AY57: =E57 -> Polymer Square with Cork
B58: DSC000152 | C58: mdpsupplies | D58: Coasters | E58: Polymer Round with Cork | F58: =IFERROR(VLOOKUP(I58,Guide!A:B,2,FALSE),"") -> Coasters | G58: =A58 -> 0 | H58: =B58 -> DSC000152 | I58: PT256 | J58: DAT019 | L58: A33 | M58: 1D57 | N58: 1000000000057 | O58: https://www.mdpsupplies.co.uk/dye-sublimation/dye_sublimation_coasters | V58: =IFERROR(VLOOKUP(I58,Guide!A:D,3,FALSE),"") -> PT256 | W58: =IFERROR(VLOOKUP(I58,Guide!A:F,5,FALSE),"") -> 40 | X58: =IFERROR(VLOOKUP(I58,Guide!A:G,6,FALSE),"") -> 150 | AG58: =L58 -> A33 | AH58: =M58 -> 1D57 | AN58: 1D57 | AO58: =T58 -> 0 | AQ58: LG | AT58: P | AV58: =M58 -> 1D57 | AW58: =_xlfn.TEXTJOIN("-",TRUE,AQ58:AV58) -> LG-P-1D57 | AX58: =_xlfn.TEXTJOIN("-",TRUE,AS58:AV58) -> P-1D57 | AY58: =E58 -> Polymer Round with Cork
B59: DSC000160 | C59: mdpsupplies | D59: Coasters | E59: Slate Square | F59: =IFERROR(VLOOKUP(I59,Guide!A:B,2,FALSE),"") -> Coasters | G59: =A59 -> 0 | H59: =B59 -> DSC000160 | I59: PT256 | J59: DAT019 | L59: A33 | M59: 1D58 | N59: 1000000000058 | O59: https://www.mdpsupplies.co.uk/dye-sublimation/dye_sublimation_coasters | V59: =IFERROR(VLOOKUP(I59,Guide!A:D,3,FALSE),"") -> PT256 | W59: =IFERROR(VLOOKUP(I59,Guide!A:F,5,FALSE),"") -> 40 | X59: =IFERROR(VLOOKUP(I59,Guide!A:G,6,FALSE),"") -> 150 | AG59: =L59 -> A33 | AH59: =M59 -> 1D58 | AN59: 1D58 | AO59: =T59 -> 0 | AQ59: LG | AT59: P | AV59: =M59 -> 1D58 | AW59: =_xlfn.TEXTJOIN("-",TRUE,AQ59:AV59) -> LG-P-1D58 | AX59: =_xlfn.TEXTJOIN("-",TRUE,AS59:AV59) -> P-1D58 | AY59: =E59 -> Slate Square
... B72: DSCD0040 | C72: mdpsupplies | D72: Crystal Photo Blocks | E72: Medal Cup | F72: =IFERROR(VLOOKUP(I72,Guide!A:B,2,FALSE),"") -> Crystal Photo Blocks | G72: =A72 -> 0 | H72: =B72 -> DSCD0040 | I72: PT267 | J72: DAT020 | L72: A2A | M72: 1D71 | N72: 1000000000071 | O72: https://www.mdpsupplies.co.uk/dye-sublimation/dye-sublimation-crystal-photo-blocks | V72: =IFERROR(VLOOKUP(I72,Guide!A:D,3,FALSE),"") -> PT267 | W72: =IFERROR(VLOOKUP(I72,Guide!A:F,5,FALSE),"") -> 300 | X72: =IFERROR(VLOOKUP(I72,Guide!A:G,6,FALSE),"") -> 1500 | AG72: =L72 -> A2A | AH72: =M72 -> 1D71 | AN72: 1D71 | AO72: =T72 -> 0 | AQ72: LG | AT72: P | AV72: =M72 -> 1D71 | AW72: =_xlfn.TEXTJOIN("-",TRUE,AQ72:AV72) -> LG-P-1D71 | AX72: =_xlfn.TEXTJOIN("-",TRUE,AS72:AV72) -> P-1D71 | AY72: =E72 -> Medal Cup
B73: DSS0120 | C73: mdpsupplies | D73: Slates | E73: 14x14cm Matt | F73: =IFERROR(VLOOKUP(I73,Guide!A:B,2,FALSE),"") -> Slates | G73: =A73 -> 0 | H73: =B73 -> DSS0120 | I73: PT252 | J73: DAT021 | L73: A2B | M73: 1D72 | N73: 1000000000072 | O73: https://www.mdpsupplies.co.uk/dye-sublimation/dye_sublimation_photo_slates | R73: White | S73: 140 × 140 mm | T73: CT-7 | V73: =IFERROR(VLOOKUP(I73,Guide!A:D,3,FALSE),"") -> PT252 | W73: =IFERROR(VLOOKUP(I73,Guide!A:F,5,FALSE),"") -> 250 | X73: =IFERROR(VLOOKUP(I73,Guide!A:G,6,FALSE),"") -> 1250 | Y73: Square | AG73: =L73 -> A2B | AH73: =M73 -> 1D72 | AN73: 1D72 | AO73: =#REF! -> #REF! | AQ73: LG | AR73: N213 | AT73: P | AV73: =M73 -> 1D72 | AW73: =_xlfn.TEXTJOIN("-",TRUE,AQ73:AV73) -> LG-N213-P-1D72 | AX73: =_xlfn.TEXTJOIN("-",TRUE,AS73:AV73) -> P-1D72 | AY73: =E73 -> 14x14cm Matt | AZ73: Slate 14 × 14 cm Matt | BA73: £2.50 | BB73: £2.00 | BC73: £3.39 | BD73: £7.89 | BE73: £9.47 | BF73: £11.36 | BG73: £11.99 | BH73: ~500g | BI73: Royal Mail Tracked 48 Small Parcel
B74: DSS0130 | C74: mdpsupplies | D74: Slates | E74: 19x19cm Matt | F74: =IFERROR(VLOOKUP(I74,Guide!A:B,2,FALSE),"") -> Slates | G74: =A74 -> 0 | H74: =B74 -> DSS0130 | I74: PT252 | J74: DAT021 | L74: A2B | M74: 1D73 | N74: 1000000000073 | O74: https://www.mdpsupplies.co.uk/dye-sublimation/dye_sublimation_photo_slates | R74: White | S74: 190 × 190 mm | T74: CT-8 | V74: =IFERROR(VLOOKUP(I74,Guide!A:D,3,FALSE),"") -> PT252 | W74: =IFERROR(VLOOKUP(I74,Guide!A:F,5,FALSE),"") -> 250 | X74: =IFERROR(VLOOKUP(I74,Guide!A:G,6,FALSE),"") -> 1250 | Y74: Square | AG74: =L74 -> A2B | AH74: =M74 -> 1D73 | AN74: 1D73 | AO74: =#REF! -> #REF! | AQ74: LG | AR74: N214 | AT74: P | AV74: =M74 -> 1D73 | AW74: =_xlfn.TEXTJOIN("-",TRUE,AQ74:AV74) -> LG-N214-P-1D73 | AX74: =_xlfn.TEXTJOIN("-",TRUE,AS74:AV74) -> P-1D73 | AY74: =E74 -> 19x19cm Matt | AZ74: Slate 19 × 19 cm Matt | BA74: £3.50 | BB74: £2.01 | BC74: £3.39 | BD74: £8.89 | BE74: £10.67 | BF74: £12.80 | BG74: £12.99 | BH74: ~800g | BI74: Royal Mail Tracked 48 Small Parcel
B75: DSS0100 | C75: mdpsupplies | D75: Slates | E75: 14x19cm Matt | F75: =IFERROR(VLOOKUP(I75,Guide!A:B,2,FALSE),"") -> Slates | G75: =A75 -> 0 | H75: =B75 -> DSS0100 | I75: PT252 | J75: DAT021 | L75: A2B | M75: 1D74 | N75: 1000000000074 | O75: https://www.mdpsupplies.co.uk/dye-sublimation/dye_sublimation_photo_slates | R75: White | S75: 140 × 190 mm | T75: CT-9 | V75: =IFERROR(VLOOKUP(I75,Guide!A:D,3,FALSE),"") -> PT252 | W75: =IFERROR(VLOOKUP(I75,Guide!A:F,5,FALSE),"") -> 250 | X75: =IFERROR(VLOOKUP(I75,Guide!A:G,6,FALSE),"") -> 1250 | Y75: Rectangle | AG75: =L75 -> A2B | AH75: =M75 -> 1D74 | AN75: 1D74 | AO75: =#REF! -> #REF! | AQ75: LG | AR75: N215 | AT75: P | AV75: =M75 -> 1D74 | AW75: =_xlfn.TEXTJOIN("-",TRUE,AQ75:AV75) -> LG-N215-P-1D74 | AX75: =_xlfn.TEXTJOIN("-",TRUE,AS75:AV75) -> P-1D74 | AY75: =E75 -> 14x19cm Matt | AZ75: Slate 14 × 19 cm Matt | BA75: £3.00 | BB75: £2.02 | BC75: £3.39 | BD75: £8.39 | BE75: £10.07 | BF75: £12.08 | BG75: £12.49 | BH75: ~650g | BI75: Royal Mail Tracked 48 Small Parcel
B76: DSS0110 | C76: mdpsupplies | D76: Slates | E76: 19x29cm Matt | F76: =IFERROR(VLOOKUP(I76,Guide!A:B,2,FALSE),"") -> Slates | G76: =A76 -> 0 | H76: =B76 -> DSS0110 | I76: PT252 | J76: DAT021 | L76: A2B | M76: 1D75 | N76: 1000000000075 | O76: https://www.mdpsupplies.co.uk/dye-sublimation/dye_sublimation_photo_slates | R76: White | S76: 190 × 290 mm | T76: CT-10 | V76: =IFERROR(VLOOKUP(I76,Guide!A:D,3,FALSE),"") -> PT252 | W76: =IFERROR(VLOOKUP(I76,Guide!A:F,5,FALSE),"") -> 250 | X76: =IFERROR(VLOOKUP(I76,Guide!A:G,6,FALSE),"") -> 1250 | Y76: Rectangle | AG76: =L76 -> A2B | AH76: =M76 -> 1D75 | AN76: 1D75 | AO76: =#REF! -> #REF! | AQ76: LG | AR76: N216 | AT76: P | AV76: =M76 -> 1D75 | AW76: =_xlfn.TEXTJOIN("-",TRUE,AQ76:AV76) -> LG-N216-P-1D75 | AX76: =_xlfn.TEXTJOIN("-",TRUE,AS76:AV76) -> P-1D75 | AY76: =E76 -> 19x29cm Matt | AZ76: Slate 19 × 29 cm Matt | BA76: £5.50 | BB76: £2.03 | BC76: £3.39 | BD76: £11.39 | BE76: £13.67 | BF76: £16.40 | BG76: £16.99 | BH76: ~1.2kg | BI76: Royal Mail Tracked 48 Small Parcel
B77: DSS0150 | C77: mdpsupplies | D77: Slates | E77: Curved Top Matt | F77: =IFERROR(VLOOKUP(I77,Guide!A:B,2,FALSE),"") -> Slates | G77: =A77 -> 0 | H77: =B77 -> DSS0150 | I77: PT252 | J77: DAT021 | L77: A2B | M77: 1D76 | N77: 1000000000076 | O77: https://www.mdpsupplies.co.uk/dye-sublimation/dye_sublimation_photo_slates | R77: White | S77: 200*200 mm | T77: CT-24 | V77: =IFERROR(VLOOKUP(I77,Guide!A:D,3,FALSE),"") -> PT252 | W77: =IFERROR(VLOOKUP(I77,Guide!A:F,5,FALSE),"") -> 250 | X77: =IFERROR(VLOOKUP(I77,Guide!A:G,6,FALSE),"") -> 1250 | Y77: Curved | AG77: =L77 -> A2B | AH77: =M77 -> 1D76 | AN77: 1D76 | AO77: =#REF! -> #REF! | AQ77: LG | AR77: N52 | AT77: P | AV77: =M77 -> 1D76 | AW77: =_xlfn.TEXTJOIN("-",TRUE,AQ77:AV77) -> LG-N52-P-1D76 | AX77: =_xlfn.TEXTJOIN("-",TRUE,AS77:AV77) -> P-1D76 | AY77: =E77 -> Curved Top Matt
B78: DSS0154 | C78: mdpsupplies | D78: Slates | E78: Round 15cm Matt | F78: =IFERROR(VLOOKUP(I78,Guide!A:B,2,FALSE),"") -> Slates | G78: =A78 -> 0 | H78: =B78 -> DSS0154 | I78: PT252 | J78: DAT021 | L78: A2B | M78: 1D77 | N78: 1000000000077 | O78: https://www.mdpsupplies.co.uk/dye-sublimation/dye_sublimation_photo_slates | R78: White | S78: 150 × 150 mm | T78: CT-11 | V78: =IFERROR(VLOOKUP(I78,Guide!A:D,3,FALSE),"") -> PT252 | W78: =IFERROR(VLOOKUP(I78,Guide!A:F,5,FALSE),"") -> 250 | X78: =IFERROR(VLOOKUP(I78,Guide!A:G,6,FALSE),"") -> 1250 | Y78: Round | AG78: =L78 -> A2B | AH78: =M78 -> 1D77 | AN78: 1D77 | AO78: =#REF! -> #REF! | AQ78: LG | AR78: N217 | AT78: P | AV78: =M78 -> 1D77 | AW78: =_xlfn.TEXTJOIN("-",TRUE,AQ78:AV78) -> LG-N217-P-1D77 | AX78: =_xlfn.TEXTJOIN("-",TRUE,AS78:AV78) -> P-1D77 | AY78: =E78 -> Round 15cm Matt | AZ78: Slate Round 15 cm Matt | BA78: £2.75 | BB78: £2.00 | BC78: £3.39 | BD78: £8.14 | BE78: £9.77 | BF78: £11.72 | BG78: £11.99 | BH78: ~500g | BI78: Royal Mail Tracked 48 Small Parcel
B79: DSS0140 | C79: mdpsupplies | D79: Slates | E79: 28x36cm Matt | F79: =IFERROR(VLOOKUP(I79,Guide!A:B,2,FALSE),"") -> Slates | G79: =A79 -> 0 | H79: =B79 -> DSS0140 | I79: PT252 | J79: DAT021 | L79: A2B | M79: 1D78 | N79: 1000000000078 | O79: https://www.mdpsupplies.co.uk/dye-sublimation/dye_sublimation_photo_slates | R79: White | S79: 280 × 360 mm | T79: CT-12 | V79: =IFERROR(VLOOKUP(I79,Guide!A:D,3,FALSE),"") -> PT252 | W79: =IFERROR(VLOOKUP(I79,Guide!A:F,5,FALSE),"") -> 250 | X79: =IFERROR(VLOOKUP(I79,Guide!A:G,6,FALSE),"") -> 1250 | Y79: Rectangle | AG79: =L79 -> A2B | AH79: =M79 -> 1D78 | AN79: 1D78 | AO79: =#REF! -> #REF! | AQ79: LG | AR79: N218 | AT79: P | AV79: =M79 -> 1D78 | AW79: =_xlfn.TEXTJOIN("-",TRUE,AQ79:AV79) -> LG-N218-P-1D78 | AX79: =_xlfn.TEXTJOIN("-",TRUE,AS79:AV79) -> P-1D78 | AY79: =E79 -> 28x36cm Matt | AZ79: Slate 28 × 36 cm Matt | BA79: £8.50 | BB79: £2.01 | BC79: £5.49 | BD79: £17.49 | BE79: £20.99 | BF79: £25.19 | BG79: £25.99 | BH79: ~2.2kg | BI79: Royal Mail/Courier Parcel
B80: DSS0152 | C80: mdpsupplies | D80: Slates | E80: Heart 15cm Matt | F80: =IFERROR(VLOOKUP(I80,Guide!A:B,2,FALSE),"") -> Slates | G80: =A80 -> 0 | H80: =B80 -> DSS0152 | I80: PT252 | J80: DAT021 | L80: A2B | M80: 1D79 | N80: 1000000000079 | O80: https://www.mdpsupplies.co.uk/dye-sublimation/dye_sublimation_photo_slates | R80: White | S80: 150 × 150 mm | T80: CT-13 | V80: =IFERROR(VLOOKUP(I80,Guide!A:D,3,FALSE),"") -> PT252 | W80: =IFERROR(VLOOKUP(I80,Guide!A:F,5,FALSE),"") -> 250 | X80: =IFERROR(VLOOKUP(I80,Guide!A:G,6,FALSE),"") -> 1250 | Y80: Heart | AG80: =L80 -> A2B | AH80: =M80 -> 1D79 | AN80: 1D79 | AO80: =#REF! -> #REF! | AQ80: LG | AR80: N219 | AT80: P | AV80: =M80 -> 1D79 | AW80: =_xlfn.TEXTJOIN("-",TRUE,AQ80:AV80) -> LG-N219-P-1D79 | AX80: =_xlfn.TEXTJOIN("-",TRUE,AS80:AV80) -> P-1D79 | AY80: =E80 -> Heart 15cm Matt | AZ80: Slate Heart 15 cm Matt | BA80: £2.75 | BB80: £2.02 | BC80: £3.39 | BD80: £8.14 | BE80: £9.77 | BF80: £11.72 | BG80: £11.99 | BH80: ~500g | BI80: Royal Mail Tracked 48 Small Parcel
B81: DSS0220 | C81: mdpsupplies | D81: Slates | E81: 14x14cm Gloss | F81: =IFERROR(VLOOKUP(I81,Guide!A:B,2,FALSE),"") -> Slates | G81: =A81 -> 0 | H81: =B81 -> DSS0220 | I81: PT252 | J81: DAT021 | L81: A2B | M81: 1D80 | N81: 1000000000080 | O81: https://www.mdpsupplies.co.uk/dye-sublimation/dye_sublimation_photo_slates | R81: White | S81: 140 × 140 mm | T81: CT-7 | V81: =IFERROR(VLOOKUP(I81,Guide!A:D,3,FALSE),"") -> PT252 | W81: =IFERROR(VLOOKUP(I81,Guide!A:F,5,FALSE),"") -> 250 | X81: =IFERROR(VLOOKUP(I81,Guide!A:G,6,FALSE),"") -> 1250 | Y81: Square | AG81: =L81 -> A2B | AH81: =M81 -> 1D80 | AN81: 1D80 | AO81: =#REF! -> #REF! | AQ81: LG | AR81: N213 | AT81: P | AV81: =M81 -> 1D80 | AW81: =_xlfn.TEXTJOIN("-",TRUE,AQ81:AV81) -> LG-N213-P-1D80 | AX81: =_xlfn.TEXTJOIN("-",TRUE,AS81:AV81) -> P-1D80 | AY81: =E81 -> 14x14cm Gloss | AZ81: Slate 14 × 14 cm Gloss | BA81: £2.75 | BB81: £2.03 | BC81: £3.39 | BD81: £8.14 | BE81: £9.77 | BF81: £11.72 | BG81: £11.99 | BH81: ~500g | BI81: Royal Mail Tracked 48 Small Parcel
B82: DSS0230 | C82: mdpsupplies | D82: Slates | E82: 19x19cm Gloss | F82: =IFERROR(VLOOKUP(I82,Guide!A:B,2,FALSE),"") -> Slates | G82: =A82 -> 0 | H82: =B82 -> DSS0230 | I82: PT252 | J82: DAT021 | L82: A2B | M82: 1D81 | N82: 1000000000081 | O82: https://www.mdpsupplies.co.uk/dye-sublimation/dye_sublimation_photo_slates | R82: White | S82: 190 × 190 mm | T82: CT-8 | V82: =IFERROR(VLOOKUP(I82,Guide!A:D,3,FALSE),"") -> PT252 | W82: =IFERROR(VLOOKUP(I82,Guide!A:F,5,FALSE),"") -> 250 | X82: =IFERROR(VLOOKUP(I82,Guide!A:G,6,FALSE),"") -> 1250 | Y82: Square | AG82: =L82 -> A2B | AH82: =M82 -> 1D81 | AN82: 1D81 | AO82: =#REF! -> #REF! | AQ82: LG | AR82: N214 | AT82: P | AV82: =M82 -> 1D81 | AW82: =_xlfn.TEXTJOIN("-",TRUE,AQ82:AV82) -> LG-N214-P-1D81 | AX82: =_xlfn.TEXTJOIN("-",TRUE,AS82:AV82) -> P-1D81 | AY82: =E82 -> 19x19cm Gloss | AZ82: Slate 19 × 19 cm Gloss | BA82: £3.75 | BB82: £2.04 | BC82: £3.39 | BD82: £9.14 | BE82: £10.97 | BF82: £13.16 | BG82: £13.49 | BH82: ~800g | BI82: Royal Mail Tracked 48 Small Parcel
B83: DSS0200 | C83: mdpsupplies | D83: Slates | E83: 14x19cm Gloss | F83: =IFERROR(VLOOKUP(I83,Guide!A:B,2,FALSE),"") -> Slates | G83: =A83 -> 0 | H83: =B83 -> DSS0200 | I83: PT252 | J83: DAT021 | L83: A2B | M83: 1D82 | N83: 1000000000082 | O83: https://www.mdpsupplies.co.uk/dye-sublimation/dye_sublimation_photo_slates | R83: White | S83: 140 × 190 mm | T83: CT-9 | V83: =IFERROR(VLOOKUP(I83,Guide!A:D,3,FALSE),"") -> PT252 | W83: =IFERROR(VLOOKUP(I83,Guide!A:F,5,FALSE),"") -> 250 | X83: =IFERROR(VLOOKUP(I83,Guide!A:G,6,FALSE),"") -> 1250 | Y83: Rectangle | AG83: =L83 -> A2B | AH83: =M83 -> 1D82 | AN83: 1D82 | AO83: =#REF! -> #REF! | AQ83: LG | AR83: N215 | AT83: P | AV83: =M83 -> 1D82 | AW83: =_xlfn.TEXTJOIN("-",TRUE,AQ83:AV83) -> LG-N215-P-1D82 | AX83: =_xlfn.TEXTJOIN("-",TRUE,AS83:AV83) -> P-1D82 | AY83: =E83 -> 14x19cm Gloss | AZ83: Slate 14 × 19 cm Gloss | BA83: £3.25 | BB83: £2.05 | BC83: £3.39 | BD83: £8.64 | BE83: £10.37 | BF83: £12.44 | BG83: £12.99 | BH83: ~650g | BI83: Royal Mail Tracked 48 Small Parcel
B84: DSS0153 | C84: mdpsupplies | D84: Slates | E84: Heart 15cm Gloss | F84: =IFERROR(VLOOKUP(I84,Guide!A:B,2,FALSE),"") -> Slates | G84: =A84 -> 0 | H84: =B84 -> DSS0153 | I84: PT252 | J84: DAT021 | L84: A2B | M84: 1D83 | N84: 1000000000083 | O84: https://www.mdpsupplies.co.uk/dye-sublimation/dye_sublimation_photo_slates | R84: White | S84: 150 × 150 mm | T84: CT-11 | V84: =IFERROR(VLOOKUP(I84,Guide!A:D,3,FALSE),"") -> PT252 | W84: =IFERROR(VLOOKUP(I84,Guide!A:F,5,FALSE),"") -> 250 | X84: =IFERROR(VLOOKUP(I84,Guide!A:G,6,FALSE),"") -> 1250 | Y84: Heart | AG84: =L84 -> A2B | AH84: =M84 -> 1D83 | AN84: 1D83 | AO84: =#REF! -> #REF! | AQ84: LG | AR84: N219 | AT84: P | AV84: =M84 -> 1D83 | AW84: =_xlfn.TEXTJOIN("-",TRUE,AQ84:AV84) -> LG-N219-P-1D83 | AX84: =_xlfn.TEXTJOIN("-",TRUE,AS84:AV84) -> P-1D83 | AY84: =E84 -> Heart 15cm Gloss | AZ84: Slate Heart 15 cm Gloss | BA84: £3.00 | BB84: £2.06 | BC84: £3.39 | BD84: £8.39 | BE84: £10.07 | BF84: £12.08 | BG84: £12.49 | BH84: ~500g | BI84: Royal Mail Tracked 48 Small Parcel
B85: DSS0155 | C85: mdpsupplies | D85: Slates | E85: Round 15cm Gloss | F85: =IFERROR(VLOOKUP(I85,Guide!A:B,2,FALSE),"") -> Slates | G85: =A85 -> 0 | H85: =B85 -> DSS0155 | I85: PT252 | J85: DAT021 | L85: A2B | M85: 1D84 | N85: 1000000000084 | O85: https://www.mdpsupplies.co.uk/dye-sublimation/dye_sublimation_photo_slates | R85: White | S85: 150 × 150 mm | T85: CT-13 | V85: =IFERROR(VLOOKUP(I85,Guide!A:D,3,FALSE),"") -> PT252 | W85: =IFERROR(VLOOKUP(I85,Guide!A:F,5,FALSE),"") -> 250 | X85: =IFERROR(VLOOKUP(I85,Guide!A:G,6,FALSE),"") -> 1250 | Y85: Round | AG85: =L85 -> A2B | AH85: =M85 -> 1D84 | AN85: 1D84 | AO85: =#REF! -> #REF! | AQ85: LG | AR85: N217 | AT85: P | AV85: =M85 -> 1D84 | AW85: =_xlfn.TEXTJOIN("-",TRUE,AQ85:AV85) -> LG-N217-P-1D84 | AX85: =_xlfn.TEXTJOIN("-",TRUE,AS85:AV85) -> P-1D84 | AY85: =E85 -> Round 15cm Gloss | AZ85: Slate Round 15 cm Gloss | BA85: £3.00 | BB85: £2.07 | BC85: £3.39 | BD85: £8.39 | BE85: £10.07 | BF85: £12.08 | BG85: £12.49 | BH85: ~500g | BI85: Royal Mail Tracked
C86: mdpsupplies | G86: =A86 -> 0 | H86: =B86 -> 0 | I86: =IFERROR(VLOOKUP(D86,Guide!B:C,2,FALSE),"") | M86: 1D85 | N86: 1000000000085 | O86: https://www.mdpsupplies.co.uk/dye-sublimation/dye-sub-candle-holders | V86: =IFERROR(VLOOKUP(I86,Guide!A:D,3,FALSE),"") | W86: =IFERROR(VLOOKUP(I86,Guide!A:F,5,FALSE),"") | X86: =IFERROR(VLOOKUP(I86,Guide!A:G,6,FALSE),"") | AG86: =L86 -> 0 | AH86: =M86 -> 1D85 | AN86: 1D85 | AO86: =T86 -> 0 | AQ86: LG | AT86: P | AV86: =M86 -> 1D85 | AW86: =_xlfn.TEXTJOIN("-",TRUE,AQ86:AV86) -> LG-P-1D85 | AX86: =_xlfn.TEXTJOIN("-",TRUE,AS86:AV86) -> P-1D85 | AY86: =E86 -> 0 | AZ86: Slate Round 15 cm Gloss
C87: mdpsupplies | G87: =A87 -> 0 | H87: =B87 -> 0 | I87: =IFERROR(VLOOKUP(D87,Guide!B:C,2,FALSE),"") | M87: 1D86 | N87: 1000000000086 | O87: https://www.mdpsupplies.co.uk/dye-sublimation/dye-sub-chopping-boards | V87: =IFERROR(VLOOKUP(I87,Guide!A:D,3,FALSE),"") | W87: =IFERROR(VLOOKUP(I87,Guide!A:F,5,FALSE),"") | X87: =IFERROR(VLOOKUP(I87,Guide!A:G,6,FALSE),"") | AG87: =L87 -> 0 | AH87: =M87 -> 1D86 | AN87: 1D86 | AO87: =T87 -> 0 | AQ87: LG | AT87: P | AV87: =M87 -> 1D86 | AW87: =_xlfn.TEXTJOIN("-",TRUE,AQ87:AV87) -> LG-P-1D86 | AX87: =_xlfn.TEXTJOIN("-",TRUE,AS87:AV87) -> P-1D86 | AY87: =E87 -> 0
C88: mdpsupplies | G88: =A88 -> 0 | H88: =B88 -> 0 | I88: =IFERROR(VLOOKUP(D88,Guide!B:C,2,FALSE),"") | M88: 1D87 | N88: 1000000000087 | O88: https://www.mdpsupplies.co.uk/dye-sublimation/dye-sub-chopping-boards | V88: =IFERROR(VLOOKUP(I88,Guide!A:D,3,FALSE),"") | W88: =IFERROR(VLOOKUP(I88,Guide!A:F,5,FALSE),"") | X88: =IFERROR(VLOOKUP(I88,Guide!A:G,6,FALSE),"") | AG88: =L88 -> 0 | AH88: =M88 -> 1D87 | AN88: 1D87 | AO88: =T88 -> 0 | AQ88: LG | AT88: P | AV88: =M88 -> 1D87 | AW88: =_xlfn.TEXTJOIN("-",TRUE,AQ88:AV88) -> LG-P-1D87 | AX88: =_xlfn.TEXTJOIN("-",TRUE,AS88:AV88) -> P-1D87 | AY88: =E88 -> 0
C89: mdpsupplies | G89: =A89 -> 0 | H89: =B89 -> 0 | I89: =IFERROR(VLOOKUP(D89,Guide!B:C,2,FALSE),"") | M89: 1D88 | N89: 1000000000088 | O89: https://www.mdpsupplies.co.uk/dye-sublimation/dye-sub-cushion-covers | V89: =IFERROR(VLOOKUP(I89,Guide!A:D,3,FALSE),"") | W89: =IFERROR(VLOOKUP(I89,Guide!A:F,5,FALSE),"") | X89: =IFERROR(VLOOKUP(I89,Guide!A:G,6,FALSE),"") | AG89: =L89 -> 0 | AH89: =M89 -> 1D88 | AN89: 1D88 | AO89: =T89 -> 0 | AQ89: LG | AT89: P | AV89: =M89 -> 1D88 | AW89: =_xlfn.TEXTJOIN("-",TRUE,AQ89:AV89) -> LG-P-1D88 | AX89: =_xlfn.TEXTJOIN("-",TRUE,AS89:AV89) -> P-1D88 | AY89: =E89 -> 0
C90: mdpsupplies | G90: =A90 -> 0 | H90: =B90 -> 0 | I90: =IFERROR(VLOOKUP(D90,Guide!B:C,2,FALSE),"") | M90: 1D89 | N90: 1000000000089 | O90: https://www.mdpsupplies.co.uk/dye-sublimation/dye-sub-cushion-covers | V90: =IFERROR(VLOOKUP(I90,Guide!A:D,3,FALSE),"") | W90: =IFERROR(VLOOKUP(I90,Guide!A:F,5,FALSE),"") | X90: =IFERROR(VLOOKUP(I90,Guide!A:G,6,FALSE),"") | AG90: =L90 -> 0 | AH90: =M90 -> 1D89 | AN90: 1D89 | AO90: =T90 -> 0 | AQ90: LG | AT90: P | AV90: =M90 -> 1D89 | AW90: =_xlfn.TEXTJOIN("-",TRUE,AQ90:AV90) -> LG-P-1D89 | AX90: =_xlfn.TEXTJOIN("-",TRUE,AS90:AV90) -> P-1D89 | AY90: =E90 -> 0
C91: mdpsupplies | G91: =A91 -> 0 | H91: =B91 -> 0 | I91: =IFERROR(VLOOKUP(D91,Guide!B:C,2,FALSE),"") | M91: 1D90 | N91: 1000000000090 | O91: https://www.mdpsupplies.co.uk/dye-sublimation/dye-sub-door-signs | V91: =IFERROR(VLOOKUP(I91,Guide!A:D,3,FALSE),"") | W91: =IFERROR(VLOOKUP(I91,Guide!A:F,5,FALSE),"") | X91: =IFERROR(VLOOKUP(I91,Guide!A:G,6,FALSE),"") | AG91: =L91 -> 0 | AH91: =M91 -> 1D90 | AN91: 1D90 | AO91: =T91 -> 0 | AQ91: LG | AT91: P | AV91: =M91 -> 1D90 | AW91: =_xlfn.TEXTJOIN("-",TRUE,AQ91:AV91) -> LG-P-1D90 | AX91: =_xlfn.TEXTJOIN("-",TRUE,AS91:AV91) -> P-1D90 | AY91: =E91 -> 0
C92: mdpsupplies | G92: =A92 -> 0 | H92: =B92 -> 0 | I92: =IFERROR(VLOOKUP(D92,Guide!B:C,2,FALSE),"") | M92: 1D91 | N92: 1000000000091 | O92: https://www.mdpsupplies.co.uk/dye-sublimation/dye-sub-fridge-magnets | V92: =IFERROR(VLOOKUP(I92,Guide!A:D,3,FALSE),"") | W92: =IFERROR(VLOOKUP(I92,Guide!A:F,5,FALSE),"") | X92: =IFERROR(VLOOKUP(I92,Guide!A:G,6,FALSE),"") | AG92: =L92 -> 0 | AH92: =M92 -> 1D91 | AN92: 1D91 | AO92: =T92 -> 0 | AQ92: LG | AT92: P | AV92: =M92 -> 1D91 | AW92: =_xlfn.TEXTJOIN("-",TRUE,AQ92:AV92) -> LG-P-1D91 | AX92: =_xlfn.TEXTJOIN("-",TRUE,AS92:AV92) -> P-1D91 | AY92: =E92 -> 0
C93: mdpsupplies | G93: =A93 -> 0 | H93: =B93 -> 0 | I93: =IFERROR(VLOOKUP(D93,Guide!B:C,2,FALSE),"") | M93: 1D92 | N93: 1000000000092 | O93: https://www.mdpsupplies.co.uk/dye-sublimation/dye-sub-fridge-magnets | V93: =IFERROR(VLOOKUP(I93,Guide!A:D,3,FALSE),"") | W93: =IFERROR(VLOOKUP(I93,Guide!A:F,5,FALSE),"") | X93: =IFERROR(VLOOKUP(I93,Guide!A:G,6,FALSE),"") | AG93: =L93 -> 0 | AH93: =M93 -> 1D92 | AN93: 1D92 | AO93: =T93 -> 0 | AQ93: LG | AT93: P | AV93: =M93 -> 1D92 | AW93: =_xlfn.TEXTJOIN("-",TRUE,AQ93:AV93) -> LG-P-1D92 | AX93: =_xlfn.TEXTJOIN("-",TRUE,AS93:AV93) -> P-1D92 | AY93: =E93 -> 0
C94: mdpsupplies | G94: =A94 -> 0 | H94: =B94 -> 0 | I94: =IFERROR(VLOOKUP(D94,Guide!B:C,2,FALSE),"") | M94: 1D93 | N94: 1000000000093 | O94: https://www.mdpsupplies.co.uk/dye-sublimation/dye-sub-keyrings | V94: =IFERROR(VLOOKUP(I94,Guide!A:D,3,FALSE),"") | W94: =IFERROR(VLOOKUP(I94,Guide!A:F,5,FALSE),"") | X94: =IFERROR(VLOOKUP(I94,Guide!A:G,6,FALSE),"") | AG94: =L94 -> 0 | AH94: =M94 -> 1D93 | AN94: 1D93 | AO94: =T94 -> 0 | AQ94: LG | AT94: P | AV94: =M94 -> 1D93 | AW94: =_xlfn.TEXTJOIN("-",TRUE,AQ94:AV94) -> LG-P-1D93 | AX94: =_xlfn.TEXTJOIN("-",TRUE,AS94:AV94) -> P-1D93 | AY94: =E94 -> 0
C95: mdpsupplies | G95: =A95 -> 0 | H95: =B95 -> 0 | I95: =IFERROR(VLOOKUP(D95,Guide!B:C,2,FALSE),"") | M95: 1D94 | N95: 1000000000094 | O95: https://www.mdpsupplies.co.uk/dye-sublimation/dye-sub-keyrings | V95: =IFERROR(VLOOKUP(I95,Guide!A:D,3,FALSE),"") | W95: =IFERROR(VLOOKUP(I95,Guide!A:F,5,FALSE),"") | X95: =IFERROR(VLOOKUP(I95,Guide!A:G,6,FALSE),"") | AG95: =L95 -> 0 | AH95: =M95 -> 1D94 | AN95: 1D94 | AO95: =T95 -> 0 | AQ95: LG | AT95: P | AV95: =M95 -> 1D94 | AW95: =_xlfn.TEXTJOIN("-",TRUE,AQ95:AV95) -> LG-P-1D94 | AX95: =_xlfn.TEXTJOIN("-",TRUE,AS95:AV95) -> P-1D94 | AY95: =E95 -> 0
C96: mdpsupplies | G96: =A96 -> 0 | H96: =B96 -> 0 | I96: =IFERROR(VLOOKUP(D96,Guide!B:C,2,FALSE),"") | M96: 1D95 | N96: 1000000000095 | O96: https://www.mdpsupplies.co.uk/dye-sublimation/dye-sub-jigsaws | V96: =IFERROR(VLOOKUP(I96,Guide!A:D,3,FALSE),"") | W96: =IFERROR(VLOOKUP(I96,Guide!A:F,5,FALSE),"") | X96: =IFERROR(VLOOKUP(I96,Guide!A:G,6,FALSE),"") | AG96: =L96 -> 0 | AH96: =M96 -> 1D95 | AN96: 1D95 | AO96: =T96 -> 0 | AQ96: LG | AT96: P | AV96: =M96 -> 1D95 | AW96: =_xlfn.TEXTJOIN("-",TRUE,AQ96:AV96) -> LG-P-1D95 | AX96: =_xlfn.TEXTJOIN("-",TRUE,AS96:AV96) -> P-1D95 | AY96: =E96 -> 0
C97: mdpsupplies | G97: =A97 -> 0 | H97: =B97 -> 0 | I97: =IFERROR(VLOOKUP(D97,Guide!B:C,2,FALSE),"") | M97: 1D96 | N97: 1000000000096 | O97: https://www.mdpsupplies.co.uk/dye-sublimation/dye-sub-jigsaws | V97: =IFERROR(VLOOKUP(I97,Guide!A:D,3,FALSE),"") | W97: =IFERROR(VLOOKUP(I97,Guide!A:F,5,FALSE),"") | X97: =IFERROR(VLOOKUP(I97,Guide!A:G,6,FALSE),"") | AG97: =L97 -> 0 | AH97: =M97 -> 1D96 | AN97: 1D96 | AO97: =T97 -> 0 | AQ97: LG | AT97: P | AV97: =M97 -> 1D96 | AW97: =_xlfn.TEXTJOIN("-",TRUE,AQ97:AV97) -> LG-P-1D96 | AX97: =_xlfn.TEXTJOIN("-",TRUE,AS97:AV97) -> P-1D96 | AY97: =E97 -> 0
C98: mdpsupplies | G98: =A98 -> 0 | H98: =B98 -> 0 | I98: =IFERROR(VLOOKUP(D98,Guide!B:C,2,FALSE),"") | M98: 1D97 | N98: 1000000000097 | O98: https://www.mdpsupplies.co.uk/dye-sublimation/dye-sub-lapel-badges | V98: =IFERROR(VLOOKUP(I98,Guide!A:D,3,FALSE),"") | W98: =IFERROR(VLOOKUP(I98,Guide!A:F,5,FALSE),"") | X98: =IFERROR(VLOOKUP(I98,Guide!A:G,6,FALSE),"") | AG98: =L98 -> 0 | AH98: =M98 -> 1D97 | AN98: 1D97 | AO98: =T98 -> 0 | AQ98: LG | AT98: P | AV98: =M98 -> 1D97 | AW98: =_xlfn.TEXTJOIN("-",TRUE,AQ98:AV98) -> LG-P-1D97 | AX98: =_xlfn.TEXTJOIN("-",TRUE,AS98:AV98) -> P-1D97 | AY98: =E98 -> 0
... C109: mdpsupplies | G109: =A109 -> 0 | H109: =B109 -> 0 | I109: =IFERROR(VLOOKUP(D109,Guide!B:C,2,FALSE),"") | M109: 1D108 | N109: 1000000000108 | O109: https://www.mdpsupplies.co.uk/dye-sublimation/dye-sub-xmas-decorations | V109: =IFERROR(VLOOKUP(I109,Guide!A:D,3,FALSE),"") | W109: =IFERROR(VLOOKUP(I109,Guide!A:F,5,FALSE),"") | X109: =IFERROR(VLOOKUP(I109,Guide!A:G,6,FALSE),"") | AG109: =L109 -> 0 | AH109: =M109 -> 1D108 | AN109: 1D108 | AO109: =T109 -> 0 | AQ109: LG | AT109: P | AV109: =M109 -> 1D108 | AW109: =_xlfn.TEXTJOIN("-",TRUE,AQ109:AV109) -> LG-P-1D108 | AX109: =_xlfn.TEXTJOIN("-",TRUE,AS109:AV109) -> P-1D108 | AY109: =E109 -> 0
A110: Nil | B110: Nil | C110: Amari Plastics | D110: Acrylic clear | E110: Clear Acrylic Sheet – 10mm Thick (A7 Size Options) | F110: =IFERROR(VLOOKUP(I110,Guide!A:B,2,FALSE),"") -> Acrylic Clear | G110: =A110 -> Nil | H110: =B110 -> Nil | I110: =IFERROR(VLOOKUP(D110,Guide!B:C,2,FALSE),"") -> PT257 | J110: DAT021 | L110: A2C | M110: 1D109 | N110: 1000000000109 | O110: https://amariplastics.com/plastics/acrylic | R110: clear | S110: 74 mm × 105 mm | T110: A7 | V110: =IFERROR(VLOOKUP(I110,Guide!A:D,3,FALSE),"") -> PT257 | W110: =IFERROR(VLOOKUP(I110,Guide!A:F,5,FALSE),"") -> 220 | X110: =IFERROR(VLOOKUP(I110,Guide!A:G,6,FALSE),"") -> 720 | Y110: Rectangle | AA110: Acrylic | AC110: 10mm | AG110: =L110 -> A2C | AH110: =M110 -> 1D109 | AJ110: UV | AN110: 1D109 | AO110: =T110 -> A7 | AQ110: LG | AR110: N42 | AT110: P | AV110: =M110 -> 1D109 | AW110: =_xlfn.TEXTJOIN("-",TRUE,AQ110:AV110) -> LG-N42-P-1D109 | AX110: =_xlfn.TEXTJOIN("-",TRUE,AS110:AV110) -> P-1D109 | AY110: =E110 -> Clear Acrylic Sheet – 10mm Thick (A7 Size Options) | AZ110: Clear Acrylic Sheet – 10mm A7 | BA110: £0.36 | BB110: £2.00 | BC110: £3.39 | BD110: £5.75 | BE110: £6.90 | BF110: £8.28 | BG110: £8.29 | BH110: 0.20 kg | BI110: Royal Mail Tracked 48 Small Parcel | BR110: 3
A111: Nil | B111: Nil | C111: Amari Plastics | D111: Acrylic clear | E111: Clear Acrylic Sheet – 10mm Thick (A6 Size Options) | F111: =IFERROR(VLOOKUP(I111,Guide!A:B,2,FALSE),"") -> Acrylic Clear | G111: =A111 -> Nil | H111: =B111 -> Nil | I111: =IFERROR(VLOOKUP(D111,Guide!B:C,2,FALSE),"") -> PT257 | J111: DAT021 | L111: A2C | M111: 1D110 | N111: 1000000000110 | O111: https://amariplastics.com/plastics/acrylic | R111: clear | S111: 105 mm × 148 mm | T111: A6 | V111: =IFERROR(VLOOKUP(I111,Guide!A:D,3,FALSE),"") -> PT257 | W111: =IFERROR(VLOOKUP(I111,Guide!A:F,5,FALSE),"") -> 220 | X111: =IFERROR(VLOOKUP(I111,Guide!A:G,6,FALSE),"") -> 720 | Y111: Rectangle | AA111: Acrylic | AC111: 10mm | AG111: =L111 -> A2C | AH111: =M111 -> 1D110 | AJ111: UV | AN111: 1D110 | AO111: =T111 -> A6 | AQ111: LG | AR111: N41 | AT111: P | AV111: =M111 -> 1D110 | AW111: =_xlfn.TEXTJOIN("-",TRUE,AQ111:AV111) -> LG-N41-P-1D110 | AX111: =_xlfn.TEXTJOIN("-",TRUE,AS111:AV111) -> P-1D110 | AY111: =E111 -> Clear Acrylic Sheet – 10mm Thick (A6 Size Options) | AZ111: Clear Acrylic Sheet – 10mm A6 | BA111: £0.74 | BB111: £2.00 | BC111: £3.39 | BD111: £6.13 | BE111: £7.36 | BF111: £8.83 | BG111: £8.99 | BH111: 0.30 kg | BI111: Royal Mail Tracked 48 Small Parcel | BR111: 3
A112: Nil | B112: Nil | C112: Amari Plastics | D112: Acrylic clear | E112: Clear Acrylic Sheet – 10mm Thick (A5 Size Options) | F112: =IFERROR(VLOOKUP(I112,Guide!A:B,2,FALSE),"") -> Acrylic Clear | G112: =A112 -> Nil | H112: =B112 -> Nil | I112: =IFERROR(VLOOKUP(D112,Guide!B:C,2,FALSE),"") -> PT257 | J112: DAT021 | L112: A2C | M112: 1D111 | N112: 1000000000111 | O112: https://amariplastics.com/plastics/acrylic | R112: clear | S112: 148 mm × 210 mm | T112: A5 | V112: =IFERROR(VLOOKUP(I112,Guide!A:D,3,FALSE),"") -> PT257 | W112: =IFERROR(VLOOKUP(I112,Guide!A:F,5,FALSE),"") -> 220 | X112: =IFERROR(VLOOKUP(I112,Guide!A:G,6,FALSE),"") -> 720 | Y112: Rectangle | AA112: Acrylic | AC112: 10mm | AG112: =L112 -> A2C | AH112: =M112 -> 1D111 | AJ112: UV | AN112: 1D111 | AO112: =T112 -> A5 | AQ112: LG | AR112: N40 | AT112: P | AV112: =M112 -> 1D111 | AW112: =_xlfn.TEXTJOIN("-",TRUE,AQ112:AV112) -> LG-N40-P-1D111 | AX112: =_xlfn.TEXTJOIN("-",TRUE,AS112:AV112) -> P-1D111 | AY112: =E112 -> Clear Acrylic Sheet – 10mm Thick (A5 Size Options) | AZ112: Clear Acrylic Sheet – 10mm A5 | BA112: £1.55 | BB112: £2.00 | BC112: £3.39 | BD112: £6.94 | BE112: £8.33 | BF112: £10.00 | BG112: £9.99 | BH112: 0.55 kg | BI112: Royal Mail Tracked 48 Small Parcel | BR112: 3
A113: Nil | B113: Nil | C113: Amari Plastics | D113: Acrylic clear | E113: Clear Acrylic Sheet – 10mm Thick (A4 Size Options) | F113: =IFERROR(VLOOKUP(I113,Guide!A:B,2,FALSE),"") -> Acrylic Clear | G113: =A113 -> Nil | H113: =B113 -> Nil | I113: =IFERROR(VLOOKUP(D113,Guide!B:C,2,FALSE),"") -> PT257 | J113: DAT021 | L113: A2C | M113: 1D112 | N113: 1000000000112 | O113: https://amariplastics.com/plastics/acrylic | R113: clear | S113: 210 mm × 297 mm | T113: A4 | V113: =IFERROR(VLOOKUP(I113,Guide!A:D,3,FALSE),"") -> PT257 | W113: =IFERROR(VLOOKUP(I113,Guide!A:F,5,FALSE),"") -> 220 | X113: =IFERROR(VLOOKUP(I113,Guide!A:G,6,FALSE),"") -> 720 | Y113: Rectangle | AA113: Acrylic | AC113: 10mm | AG113: =L113 -> A2C | AH113: =M113 -> 1D112 | AJ113: UV | AN113: 1D112 | AO113: =T113 -> A4 | AQ113: LG | AR113: N39 | AT113: P | AV113: =M113 -> 1D112 | AW113: =_xlfn.TEXTJOIN("-",TRUE,AQ113:AV113) -> LG-N39-P-1D112 | AX113: =_xlfn.TEXTJOIN("-",TRUE,AS113:AV113) -> P-1D112 | AY113: =E113 -> Clear Acrylic Sheet – 10mm Thick (A4 Size Options) | AZ113: Clear Acrylic Sheet – 10mm A4 | BA113: £3.14 | BB113: £2.00 | BC113: £3.39 | BD113: £8.53 | BE113: £10.24 | BF113: £12.29 | BG113: £11.99 | BH113: 0.90 kg | BI113: Royal Mail Tracked 48 Small Parcel | BR113: 3
A114: Nil | B114: Nil | C114: Amari Plastics | D114: Acrylic clear | E114: Clear Acrylic Sheet – 15mm Thick (A7 Size Options) | F114: =IFERROR(VLOOKUP(I114,Guide!A:B,2,FALSE),"") -> Acrylic Clear | G114: =A114 -> Nil | H114: =B114 -> Nil | I114: =IFERROR(VLOOKUP(D114,Guide!B:C,2,FALSE),"") -> PT257 | J114: DAT021 | L114: A2C | M114: 1D113 | N114: 1000000000113 | O114: https://amariplastics.com/plastics/acrylic | R114: clear | S114: 74 mm × 105 mm | T114: A7 | V114: =IFERROR(VLOOKUP(I114,Guide!A:D,3,FALSE),"") -> PT257 | W114: =IFERROR(VLOOKUP(I114,Guide!A:F,5,FALSE),"") -> 220 | X114: =IFERROR(VLOOKUP(I114,Guide!A:G,6,FALSE),"") -> 720 | Y114: Rectangle | AA114: Acrylic | AC114: 15 mm | AG114: =L114 -> A2C | AH114: =M114 -> 1D113 | AJ114: UV | AN114: 1D113 | AO114: =T114 -> A7 | AQ114: LG | AR114: N42 | AT114: P | AV114: =M114 -> 1D113 | AW114: =_xlfn.TEXTJOIN("-",TRUE,AQ114:AV114) -> LG-N42-P-1D113 | AX114: =_xlfn.TEXTJOIN("-",TRUE,AS114:AV114) -> P-1D113 | AY114: =E114 -> Clear Acrylic Sheet – 15mm Thick (A7 Size Options) | AZ114: Clear Acrylic Sheet – 15mm A7 | BA114: £0.54 | BB114: £2.00 | BC114: £3.39 | BD114: £5.93 | BE114: £7.12 | BF114: £8.54 | BG114: £8.49 | BH114: 0.25 kg | BI114: Royal Mail Tracked 48 Small Parcel | BR114: 3
